Workbook

Sheet Sheet1
C2: TABLE I: STAFF ESTABLISHMENT AND PROJECTIONS-KENYA INSTITUTE OF PRIMATE RESEARCH (KIPRE)
A5: Programme Code | B5: Programme Title | C5: Designation /Position Title | D5: PRN | E5: Names | F5: Highest qualifications | G5: KIP Grade | H5: Job Group (KIP Grade) | I5: Career guideline page no. | J5: current grade | K5: Authorized Establishment | L5: In Post as at June 2025 | M5: 2025/2026 | N5: 2026/2027 | O5: 2027/2028 | P5: 2028/2029
M6: Funded positions | N6: Positions to be funded | O6: Positions to be funded
C7: OFFICE OF THE DIRECTOR GENERAL/ CEO
C8: Director General / CEO | D8: 19901899045 | E8: Dr. Mwethera, Peter Gichuhi | F8: =IF(D8="", "", VLOOKUP(D8, Sheet3!C:P, 14, FALSE) & ", " & DATEDIF(VLOOKUP(D8, Sheet3!C:N, 12, FALSE), TODAY(), "y") & " Years Experience") -> PhD, MSc, Bachelors, KCSE, KCPE, 36 Years Experience | H8: 1 | K8: 1 | L8: 1
C9: Technical Assistant | F9: =IF(D9="", "", VLOOKUP(D9, Sheet3!C:P, 14, FALSE) & ", " & DATEDIF(VLOOKUP(D9, Sheet3!C:N, 12, FALSE), TODAY(), "y") & " Years Experience") | H9: 0 | K9: 0 | L9: 0 | N9: 0
C10: Principal Office Administrator | F10: =IF(D10="", "", VLOOKUP(D10, Sheet3!C:P, 14, FALSE) & ", " & DATEDIF(VLOOKUP(D10, Sheet3!C:N, 12, FALSE), TODAY(), "y") & " Years Experience") | H10: 5 | K10: 1 | L10: 1
C11: Office Administrator/ Senior | D11: 19990495773 | E11: Mrs. Hassan, Hamida Adam | F11: =IF(D11="", "", VLOOKUP(D11, Sheet3!C:P, 14, FALSE) & ", " & DATEDIF(VLOOKUP(D11, Sheet3!C:N, 12, FALSE), TODAY(), "y") & " Years Experience") -> Dip, KCSE, KCPE, 27 Years Experience | H11: 7/6
C12: Principal Driver | F12: =IF(D12="", "", VLOOKUP(D12, Sheet3!C:P, 14, FALSE) & ", " & DATEDIF(VLOOKUP(D12, Sheet3!C:N, 12, FALSE), TODAY(), "y") & " Years Experience") | H12: 9 | K12: 1 | L12: 1
C13: Driver/Senior | F13: =IF(D13="", "", VLOOKUP(D13, Sheet3!C:P, 14, FALSE) & ", " & DATEDIF(VLOOKUP(D13, Sheet3!C:N, 12, FALSE), TODAY(), "y") & " Years Experience") | H13: 11/10
C14: Principal Office Assistant | F14: =IF(D14="", "", VLOOKUP(D14, Sheet3!C:P, 14, FALSE) & ", " & DATEDIF(VLOOKUP(D14, Sheet3!C:N, 12, FALSE), TODAY(), "y") & " Years Experience") | H14: 10 | K14: 1 | L14: 1
C15: Office Assistant/Senior | D15: 20220598130 | E15: Miss. Koech, Beatrice Chebet | F15: =IF(D15="", "", VLOOKUP(D15, Sheet3!C:P, 14, FALSE) & ", " & DATEDIF(VLOOKUP(D15, Sheet3!C:N, 12, FALSE), TODAY(), "y") & " Years Experience") -> KCSE, KCPE, 4 Years Experience | H15: 12/11
C16: CORPORATION SECRETARY AND DIRECTOR LEGAL SERVICES DIRECTORATE | F16: =IF(D16="", "", VLOOKUP(D16, Sheet3!C:P, 14, FALSE) & ", " & DATEDIF(VLOOKUP(D16, Sheet3!C:N, 12, FALSE), TODAY(), "y") & " Years Experience")
C17: Corporation Secretary and Director Legal Services | F17: =IF(D17="", "", VLOOKUP(D17, Sheet3!C:P, 14, FALSE) & ", " & DATEDIF(VLOOKUP(D17, Sheet3!C:N, 12, FALSE), TODAY(), "y") & " Years Experience") | H17: 2 | K17: 1 | L17: 0
C18: Deputy Director, Legal Services | F18: =IF(D18="", "", VLOOKUP(D18, Sheet3!C:P, 14, FALSE) & ", " & DATEDIF(VLOOKUP(D18, Sheet3!C:N, 12, FALSE), TODAY(), "y") & " Years Experience") | H18: 3 | K18: 1 | L18: 0
C19: Assistant Director | F19: =IF(D19="", "", VLOOKUP(D19, Sheet3!C:P, 14, FALSE) & ", " & DATEDIF(VLOOKUP(D19, Sheet3!C:N, 12, FALSE), TODAY(), "y") & " Years Experience") | H19: 4 | K19: 0 | L19: 0
C20: Principal Legal Officer | F20: =IF(D20="", "", VLOOKUP(D20, Sheet3!C:P, 14, FALSE) & ", " & DATEDIF(VLOOKUP(D20, Sheet3!C:N, 12, FALSE), TODAY(), "y") & " Years Experience") | H20: 5 | K20: 0 | L20: 0
C21: Legal Officer/Senior | F21: =IF(D21="", "", VLOOKUP(D21, Sheet3!C:P, 14, FALSE) & ", " & DATEDIF(VLOOKUP(D21, Sheet3!C:N, 12, FALSE), TODAY(), "y") & " Years Experience") | H21: 7/6 | K21: 0 | L21: 0
C22: Principal Assistant Legal Officer | F22: =IF(D22="", "", VLOOKUP(D22, Sheet3!C:P, 14, FALSE) & ", " & DATEDIF(VLOOKUP(D22, Sheet3!C:N, 12, FALSE), TODAY(), "y") & " Years Experience") | H22: 7 | K22: 1 | L22: 0
C23: Assistant Legal Officer / Senior | F23: =IF(D23="", "", VLOOKUP(D23, Sheet3!C:P, 14, FALSE) & ", " & DATEDIF(VLOOKUP(D23, Sheet3!C:N, 12, FALSE), TODAY(), "y") & " Years Experience") | H23: 9/8 | K23: 0 | L23: 0
C24: Assistant Office Administrator/ Senior | F24: =IF(D24="", "", VLOOKUP(D24, Sheet3!C:P, 14, FALSE) & ", " & DATEDIF(VLOOKUP(D24, Sheet3!C:N, 12, FALSE), TODAY(), "y") & " Years Experience") | H24: 9/8 | K24: 1 | L24: 0
C25: RESEARCH AND PRODUCT DEVELOPMENT DIRECTORATE | F25: =IF(D25="", "", VLOOKUP(D25, Sheet3!C:P, 14, FALSE) & ", " & DATEDIF(VLOOKUP(D25, Sheet3!C:N, 12, FALSE), TODAY(), "y") & " Years Experience")
C26: Director, Research and Product Development | F26: =IF(D26="", "", VLOOKUP(D26, Sheet3!C:P, 14, FALSE) & ", " & DATEDIF(VLOOKUP(D26, Sheet3!C:N, 12, FALSE), TODAY(), "y") & " Years Experience") | H26: 2 | K26: 1 | L26: 1
C27: Chief Research Scientist | F27: =IF(D27="", "", VLOOKUP(D27, Sheet3!C:P, 14, FALSE) & ", " & DATEDIF(VLOOKUP(D27, Sheet3!C:N, 12, FALSE), TODAY(), "y") & " Years Experience") | H27: 2 | K27: 1 | L27: 1
C28: Assistant Office Administrator/ Senior | F28: =IF(D28="", "", VLOOKUP(D28, Sheet3!C:P, 14, FALSE) & ", " & DATEDIF(VLOOKUP(D28, Sheet3!C:N, 12, FALSE), TODAY(), "y") & " Years Experience") | H28: 9/8 | K28: 1 | L28: 1
C29: Driver / Senior | F29: =IF(D29="", "", VLOOKUP(D29, Sheet3!C:P, 14, FALSE) & ", " & DATEDIF(VLOOKUP(D29, Sheet3!C:N, 12, FALSE), TODAY(), "y") & " Years Experience") | H29: 11/10 | K29: 1 | L29: 0
C30: Office Assistant / Senior | F30: =IF(D30="", "", VLOOKUP(D30, Sheet3!C:P, 14, FALSE) & ", " & DATEDIF(VLOOKUP(D30, Sheet3!C:N, 12, FALSE), TODAY(), "y") & " Years Experience") | H30: 12/11 | K30: 1 | L30: 0
C31: INFECTIOUS DISEASES AND ONE HEALTH DIVISION | F31: =IF(D31="", "", VLOOKUP(D31, Sheet3!C:P, 14, FALSE) & ", " & DATEDIF(VLOOKUP(D31, Sheet3!C:N, 12, FALSE), TODAY(), "y") & " Years Experience")
C32: Deputy Director, Infectious Diseases and One Health | F32: =IF(D32="", "", VLOOKUP(D32, Sheet3!C:P, 14, FALSE) & ", " & DATEDIF(VLOOKUP(D32, Sheet3!C:N, 12, FALSE), TODAY(), "y") & " Years Experience") | H32: 3 | K32: 1 | L32: 0
C33: Senior Principal, Research Scientist | F33: =IF(D33="", "", VLOOKUP(D33, Sheet3!C:P, 14, FALSE) & ", " & DATEDIF(VLOOKUP(D33, Sheet3!C:N, 12, FALSE), TODAY(), "y") & " Years Experience") | H33: 3 | K33: 1 | L33: 0
C34: VIROLOGY SECTION | F34: =IF(D34="", "", VLOOKUP(D34, Sheet3!C:P, 14, FALSE) & ", " & DATEDIF(VLOOKUP(D34, Sheet3!C:N, 12, FALSE), TODAY(), "y") & " Years Experience")
C35: Assistant Director, Research | F35: =IF(D35="", "", VLOOKUP(D35, Sheet3!C:P, 14, FALSE) & ", " & DATEDIF(VLOOKUP(D35, Sheet3!C:N, 12, FALSE), TODAY(), "y") & " Years Experience") | H35: 4 | K35: 1 | L35: 1
C36: Principal Research Scientist | F36: =IF(D36="", "", VLOOKUP(D36, Sheet3!C:P, 14, FALSE) & ", " & DATEDIF(VLOOKUP(D36, Sheet3!C:N, 12, FALSE), TODAY(), "y") & " Years Experience") | H36: 4 | K36: 1 | L36: 1
C37: Senior Research Scientist | F37: =IF(D37="", "", VLOOKUP(D37, Sheet3!C:P, 14, FALSE) & ", " & DATEDIF(VLOOKUP(D37, Sheet3!C:N, 12, FALSE), TODAY(), "y") & " Years Experience") | H37: 5 | K37: 2 | L37: 1
C38: Assistant Research Scientist / Research Scientist | F38: =IF(D38="", "", VLOOKUP(D38, Sheet3!C:P, 14, FALSE) & ", " & DATEDIF(VLOOKUP(D38, Sheet3!C:N, 12, FALSE), TODAY(), "y") & " Years Experience") | H38: 7/6 | K38: 2 | L38: 2
C39: Principal Laboratory Technician | F39: =IF(D39="", "", VLOOKUP(D39, Sheet3!C:P, 14, FALSE) & ", " & DATEDIF(VLOOKUP(D39, Sheet3!C:N, 12, FALSE), TODAY(), "y") & " Years Experience") | H39: 7 | K39: 2 | L39: 2
C40: Laboratory Technician/Senior | F40: =IF(D40="", "", VLOOKUP(D40, Sheet3!C:P, 14, FALSE) & ", " & DATEDIF(VLOOKUP(D40, Sheet3!C:N, 12, FALSE), TODAY(), "y") & " Years Experience") | H40: 9/8 | K40: 0 | L40: 0
C41: MICROBIOLOGY, PARASITOLOGY AND VECTOR BIOLOGY SECTION | F41: =IF(D41="", "", VLOOKUP(D41, Sheet3!C:P, 14, FALSE) & ", " & DATEDIF(VLOOKUP(D41, Sheet3!C:N, 12, FALSE), TODAY(), "y") & " Years Experience")
C42: Assistant Director, Research | F42: =IF(D42="", "", VLOOKUP(D42, Sheet3!C:P, 14, FALSE) & ", " & DATEDIF(VLOOKUP(D42, Sheet3!C:N, 12, FALSE), TODAY(), "y") & " Years Experience") | H42: 4 | K42: 1 | L42: 0
C43: Principal Research Scientist | F43: =IF(D43="", "", VLOOKUP(D43, Sheet3!C:P, 14, FALSE) & ", " & DATEDIF(VLOOKUP(D43, Sheet3!C:N, 12, FALSE), TODAY(), "y") & " Years Experience") | H43: 4 | K43: 1 | L43: 0
C44: Senior Research Scientist | F44: =IF(D44="", "", VLOOKUP(D44, Sheet3!C:P, 14, FALSE) & ", " & DATEDIF(VLOOKUP(D44, Sheet3!C:N, 12, FALSE), TODAY(), "y") & " Years Experience") | H44: 5 | K44: 2 | L44: 0
C45: Assistant Research Scientist / Research Scientist | F45: =IF(D45="", "", VLOOKUP(D45, Sheet3!C:P, 14, FALSE) & ", " & DATEDIF(VLOOKUP(D45, Sheet3!C:N, 12, FALSE), TODAY(), "y") & " Years Experience") | H45: 7/6 | K45: 2 | L45: 2
C46: Principal Laboratory Technician | F46: =IF(D46="", "", VLOOKUP(D46, Sheet3!C:P, 14, FALSE) & ", " & DATEDIF(VLOOKUP(D46, Sheet3!C:N, 12, FALSE), TODAY(), "y") & " Years Experience") | H46: 7 | K46: 2 | L46: 2
C47: Laboratory Technician/Senior | F47: =IF(D47="", "", VLOOKUP(D47, Sheet3!C:P, 14, FALSE) & ", " & DATEDIF(VLOOKUP(D47, Sheet3!C:N, 12, FALSE), TODAY(), "y") & " Years Experience") | H47: 9/8 | K47: 0 | L47: 0
C48: IMMUNOLOGY AND VACCINE DEVELOPMENT SECTION | F48: =IF(D48="", "", VLOOKUP(D48, Sheet3!C:P, 14, FALSE) & ", " & DATEDIF(VLOOKUP(D48, Sheet3!C:N, 12, FALSE), TODAY(), "y") & " Years Experience")
C49: Assistant Director, Research | F49: =IF(D49="", "", VLOOKUP(D49, Sheet3!C:P, 14, FALSE) & ", " & DATEDIF(VLOOKUP(D49, Sheet3!C:N, 12, FALSE), TODAY(), "y") & " Years Experience") | H49: 4 | K49: 1 | L49: 0
C50: Principal Research Scientist | F50: =IF(D50="", "", VLOOKUP(D50, Sheet3!C:P, 14, FALSE) & ", " & DATEDIF(VLOOKUP(D50, Sheet3!C:N, 12, FALSE), TODAY(), "y") & " Years Experience") | H50: 4 | K50: 1 | L50: 0
C51: Senior Research Scientist | F51: =IF(D51="", "", VLOOKUP(D51, Sheet3!C:P, 14, FALSE) & ", " & DATEDIF(VLOOKUP(D51, Sheet3!C:N, 12, FALSE), TODAY(), "y") & " Years Experience") | H51: 5 | K51: 2 | L51: 0
C52: Assistant Research Scientist / Research Scientist | F52: =IF(D52="", "", VLOOKUP(D52, Sheet3!C:P, 14, FALSE) & ", " & DATEDIF(VLOOKUP(D52, Sheet3!C:N, 12, FALSE), TODAY(), "y") & " Years Experience") | H52: 7/6 | K52: 2 | L52: 2
C53: Principal Laboratory Technician | F53: =IF(D53="", "", VLOOKUP(D53, Sheet3!C:P, 14, FALSE) & ", " & DATEDIF(VLOOKUP(D53, Sheet3!C:N, 12, FALSE), TODAY(), "y") & " Years Experience") | H53: 7 | K53: 2 | L53: 2
C54: Laboratory Technician/Senior | F54: =IF(D54="", "", VLOOKUP(D54, Sheet3!C:P, 14, FALSE) & ", " & DATEDIF(VLOOKUP(D54, Sheet3!C:N, 12, FALSE), TODAY(), "y") & " Years Experience") | H54: 9/8 | K54: 0 | L54: 1
C55: ZOONOTIC SURVEILLANCE & DISEASE ECOLOGY SECTION | F55: =IF(D55="", "", VLOOKUP(D55, Sheet3!C:P, 14, FALSE) & ", " & DATEDIF(VLOOKUP(D55, Sheet3!C:N, 12, FALSE), TODAY(), "y") & " Years Experience")
C56: Assistant Director, Research | F56: =IF(D56="", "", VLOOKUP(D56, Sheet3!C:P, 14, FALSE) & ", " & DATEDIF(VLOOKUP(D56, Sheet3!C:N, 12, FALSE), TODAY(), "y") & " Years Experience") | H56: 4 | K56: 1 | L56: 0
C57: Principal Research Scientist | F57: =IF(D57="", "", VLOOKUP(D57, Sheet3!C:P, 14, FALSE) & ", " & DATEDIF(VLOOKUP(D57, Sheet3!C:N, 12, FALSE), TODAY(), "y") & " Years Experience") | H57: 4 | K57: 1 | L57: 0
C58: Senior Research Scientist | F58: =IF(D58="", "", VLOOKUP(D58, Sheet3!C:P, 14, FALSE) & ", " & DATEDIF(VLOOKUP(D58, Sheet3!C:N, 12, FALSE), TODAY(), "y") & " Years Experience") | H58: 5 | K58: 2 | L58: 0
C59: Assistant Research Scientist / Research Scientist | F59: =IF(D59="", "", VLOOKUP(D59, Sheet3!C:P, 14, FALSE) & ", " & DATEDIF(VLOOKUP(D59, Sheet3!C:N, 12, FALSE), TODAY(), "y") & " Years Experience") | H59: 7/6 | K59: 2 | L59: 2
C60: Principal Laboratory Technician | F60: =IF(D60="", "", VLOOKUP(D60, Sheet3!C:P, 14, FALSE) & ", " & DATEDIF(VLOOKUP(D60, Sheet3!C:N, 12, FALSE), TODAY(), "y") & " Years Experience") | H60: 7 | K60: 2 | L60: 2
C61: Laboratory Technician/Senior | F61: =IF(D61="", "", VLOOKUP(D61, Sheet3!C:P, 14, FALSE) & ", " & DATEDIF(VLOOKUP(D61, Sheet3!C:N, 12, FALSE), TODAY(), "y") & " Years Experience") | H61: 9/8 | K61: 0 | L61: 0
C62: CLIMATE & HEALTH SECTION | F62: =IF(D62="", "", VLOOKUP(D62, Sheet3!C:P, 14, FALSE) & ", " & DATEDIF(VLOOKUP(D62, Sheet3!C:N, 12, FALSE), TODAY(), "y") & " Years Experience")
C63: Assistant Director, Research | F63: =IF(D63="", "", VLOOKUP(D63, Sheet3!C:P, 14, FALSE) & ", " & DATEDIF(VLOOKUP(D63, Sheet3!C:N, 12, FALSE), TODAY(), "y") & " Years Experience") | H63: 4 | K63: 1 | L63: 0
C64: Principal Research Scientist | F64: =IF(D64="", "", VLOOKUP(D64, Sheet3!C:P, 14, FALSE) & ", " & DATEDIF(VLOOKUP(D64, Sheet3!C:N, 12, FALSE), TODAY(), "y") & " Years Experience") | H64: 4 | K64: 1 | L64: 0
C65: Senior Research Scientist | F65: =IF(D65="", "", VLOOKUP(D65, Sheet3!C:P, 14, FALSE) & ", " & DATEDIF(VLOOKUP(D65, Sheet3!C:N, 12, FALSE), TODAY(), "y") & " Years Experience") | H65: 5 | K65: 2 | L65: 0
C66: Assistant Research Scientist / Research Scientist | F66: =IF(D66="", "", VLOOKUP(D66, Sheet3!C:P, 14, FALSE) & ", " & DATEDIF(VLOOKUP(D66, Sheet3!C:N, 12, FALSE), TODAY(), "y") & " Years Experience") | H66: 7/6 | K66: 2 | L66: 2
C67: Principal Laboratory Technician | F67: =IF(D67="", "", VLOOKUP(D67, Sheet3!C:P, 14, FALSE) & ", " & DATEDIF(VLOOKUP(D67, Sheet3!C:N, 12, FALSE), TODAY(), "y") & " Years Experience") | H67: 7 | K67: 2 | L67: 1
C68: Laboratory Technician/Senior | F68: =IF(D68="", "", VLOOKUP(D68, Sheet3!C:P, 14, FALSE) & ", " & DATEDIF(VLOOKUP(D68, Sheet3!C:N, 12, FALSE), TODAY(), "y") & " Years Experience") | H68: 9/8 | K68: 0 | L68: 0
C69: REPRODUCTIVE HEALTH & BIOLOGY DIVISION | F69: =IF(D69="", "", VLOOKUP(D69, Sheet3!C:P, 14, FALSE) & ", " & DATEDIF(VLOOKUP(D69, Sheet3!C:N, 12, FALSE), TODAY(), "y") & " Years Experience")
C70: Deputy Director, Reproductive Health & Biology | F70: =IF(D70="", "", VLOOKUP(D70, Sheet3!C:P, 14, FALSE) & ", " & DATEDIF(VLOOKUP(D70, Sheet3!C:N, 12, FALSE), TODAY(), "y") & " Years Experience") | H70: 3 | K70: 1 | L70: 0
C71: Senior Principal Research Scientist | F71: =IF(D71="", "", VLOOKUP(D71, Sheet3!C:P, 14, FALSE) & ", " & DATEDIF(VLOOKUP(D71, Sheet3!C:N, 12, FALSE), TODAY(), "y") & " Years Experience") | H71: 3 | K71: 1 | L71: 0
C72: REPRODUCTIVE DISEASES AND DISORDERS SECTION | F72: =IF(D72="", "", VLOOKUP(D72, Sheet3!C:P, 14, FALSE) & ", " & DATEDIF(VLOOKUP(D72, Sheet3!C:N, 12, FALSE), TODAY(), "y") & " Years Experience")
C73: Assistant Director, Research | F73: =IF(D73="", "", VLOOKUP(D73, Sheet3!C:P, 14, FALSE) & ", " & DATEDIF(VLOOKUP(D73, Sheet3!C:N, 12, FALSE), TODAY(), "y") & " Years Experience") | H73: 4 | K73: 1 | L73: 1
C74: Principal Research Scientist | F74: =IF(D74="", "", VLOOKUP(D74, Sheet3!C:P, 14, FALSE) & ", " & DATEDIF(VLOOKUP(D74, Sheet3!C:N, 12, FALSE), TODAY(), "y") & " Years Experience") | H74: 4 | K74: 1 | L74: 1
C75: Senior Research Scientist | F75: =IF(D75="", "", VLOOKUP(D75, Sheet3!C:P, 14, FALSE) & ", " & DATEDIF(VLOOKUP(D75, Sheet3!C:N, 12, FALSE), TODAY(), "y") & " Years Experience") | H75: 5 | K75: 2 | L75: 2
C76: Assistant Research Scientist / Research Scientist | F76: =IF(D76="", "", VLOOKUP(D76, Sheet3!C:P, 14, FALSE) & ", " & DATEDIF(VLOOKUP(D76, Sheet3!C:N, 12, FALSE), TODAY(), "y") & " Years Experience") | H76: 7/6 | K76: 2 | L76: 2
C77: Principal Laboratory Technician | F77: =IF(D77="", "", VLOOKUP(D77, Sheet3!C:P, 14, FALSE) & ", " & DATEDIF(VLOOKUP(D77, Sheet3!C:N, 12, FALSE), TODAY(), "y") & " Years Experience") | H77: 7 | K77: 2 | L77: 2
C78: Laboratory Technician/Senior | F78: =IF(D78="", "", VLOOKUP(D78, Sheet3!C:P, 14, FALSE) & ", " & DATEDIF(VLOOKUP(D78, Sheet3!C:N, 12, FALSE), TODAY(), "y") & " Years Experience") | H78: 9/8 | K78: 0 | L78: 0
C79: CONTRACEPTION AND FAMILY PLANNING SECTION | F79: =IF(D79="", "", VLOOKUP(D79, Sheet3!C:P, 14, FALSE) & ", " & DATEDIF(VLOOKUP(D79, Sheet3!C:N, 12, FALSE), TODAY(), "y") & " Years Experience")
C80: Assistant Director, Research | F80: =IF(D80="", "", VLOOKUP(D80, Sheet3!C:P, 14, FALSE) & ", " & DATEDIF(VLOOKUP(D80, Sheet3!C:N, 12, FALSE), TODAY(), "y") & " Years Experience") | H80: 4 | K80: 1 | L80: 0
C81: Principal Research Scientist | F81: =IF(D81="", "", VLOOKUP(D81, Sheet3!C:P, 14, FALSE) & ", " & DATEDIF(VLOOKUP(D81, Sheet3!C:N, 12, FALSE), TODAY(), "y") & " Years Experience") | H81: 4 | K81: 1 | L81: 1
C82: Senior Research Scientist | F82: =IF(D82="", "", VLOOKUP(D82, Sheet3!C:P, 14, FALSE) & ", " & DATEDIF(VLOOKUP(D82, Sheet3!C:N, 12, FALSE), TODAY(), "y") & " Years Experience") | H82: 5 | K82: 2 | L82: 1
C83: Assistant Research Scientist / Research Scientist | F83: =IF(D83="", "", VLOOKUP(D83, Sheet3!C:P, 14, FALSE) & ", " & DATEDIF(VLOOKUP(D83, Sheet3!C:N, 12, FALSE), TODAY(), "y") & " Years Experience") | H83: 7/6 | K83: 2 | L83: 2
C84: Principal Laboratory Technician | F84: =IF(D84="", "", VLOOKUP(D84, Sheet3!C:P, 14, FALSE) & ", " & DATEDIF(VLOOKUP(D84, Sheet3!C:N, 12, FALSE), TODAY(), "y") & " Years Experience") | H84: 7 | K84: 2 | L84: 2
C85: Laboratory Technician/Senior | F85: =IF(D85="", "", VLOOKUP(D85, Sheet3!C:P, 14, FALSE) & ", " & DATEDIF(VLOOKUP(D85, Sheet3!C:N, 12, FALSE), TODAY(), "y") & " Years Experience") | H85: 9/8 | K85: 0 | L85: 0
C86: ASSISTED REPRODUCTIVE TECHNOLOGIES SECTION | F86: =IF(D86="", "", VLOOKUP(D86, Sheet3!C:P, 14, FALSE) & ", " & DATEDIF(VLOOKUP(D86, Sheet3!C:N, 12, FALSE), TODAY(), "y") & " Years Experience")
C87: Assistant Director, Research | F87: =IF(D87="", "", VLOOKUP(D87, Sheet3!C:P, 14, FALSE) & ", " & DATEDIF(VLOOKUP(D87, Sheet3!C:N, 12, FALSE), TODAY(), "y") & " Years Experience") | H87: 4 | K87: 1 | L87: 0
C88: Principal Research Scientist | F88: =IF(D88="", "", VLOOKUP(D88, Sheet3!C:P, 14, FALSE) & ", " & DATEDIF(VLOOKUP(D88, Sheet3!C:N, 12, FALSE), TODAY(), "y") & " Years Experience") | H88: 4 | K88: 1 | L88: 0
C89: Senior Research Scientist | F89: =IF(D89="", "", VLOOKUP(D89, Sheet3!C:P, 14, FALSE) & ", " & DATEDIF(VLOOKUP(D89, Sheet3!C:N, 12, FALSE), TODAY(), "y") & " Years Experience") | H89: 5 | K89: 2 | L89: 0
C90: Assistant Research Scientist / Research Scientist | F90: =IF(D90="", "", VLOOKUP(D90, Sheet3!C:P, 14, FALSE) & ", " & DATEDIF(VLOOKUP(D90, Sheet3!C:N, 12, FALSE), TODAY(), "y") & " Years Experience") | H90: 7/6 | K90: 2 | L90: 2
C91: Principal Laboratory Technician | F91: =IF(D91="", "", VLOOKUP(D91, Sheet3!C:P, 14, FALSE) & ", " & DATEDIF(VLOOKUP(D91, Sheet3!C:N, 12, FALSE), TODAY(), "y") & " Years Experience") | H91: 7 | K91: 2 | L91: 0
C92: Laboratory Technician/Senior | F92: =IF(D92="", "", VLOOKUP(D92, Sheet3!C:P, 14, FALSE) & ", " & DATEDIF(VLOOKUP(D92, Sheet3!C:N, 12, FALSE), TODAY(), "y") & " Years Experience") | H92: 9/8 | K92: 0 | L92: 1
C93: MICROBICIDES AND SEXUALLY TRANSMITTED INFECTIONS SECTION | F93: =IF(D93="", "", VLOOKUP(D93, Sheet3!C:P, 14, FALSE) & ", " & DATEDIF(VLOOKUP(D93, Sheet3!C:N, 12, FALSE), TODAY(), "y") & " Years Experience")
C94: Assistant Director, Research | F94: =IF(D94="", "", VLOOKUP(D94, Sheet3!C:P, 14, FALSE) & ", " & DATEDIF(VLOOKUP(D94, Sheet3!C:N, 12, FALSE), TODAY(), "y") & " Years Experience") | H94: 4 | K94: 1 | L94: 0
C95: Principal Research Scientist | F95: =IF(D95="", "", VLOOKUP(D95, Sheet3!C:P, 14, FALSE) & ", " & DATEDIF(VLOOKUP(D95, Sheet3!C:N, 12, FALSE), TODAY(), "y") & " Years Experience") | H95: 4 | K95: 1 | L95: 0
C96: Senior Research Scientist | F96: =IF(D96="", "", VLOOKUP(D96, Sheet3!C:P, 14, FALSE) & ", " & DATEDIF(VLOOKUP(D96, Sheet3!C:N, 12, FALSE), TODAY(), "y") & " Years Experience") | H96: 5 | K96: 2 | L96: 0
C97: Assistant Research Scientist / Research Scientist | F97: =IF(D97="", "", VLOOKUP(D97, Sheet3!C:P, 14, FALSE) & ", " & DATEDIF(VLOOKUP(D97, Sheet3!C:N, 12, FALSE), TODAY(), "y") & " Years Experience") | H97: 7/6 | K97: 2 | L97: 0
C98: Principal Laboratory Technician | F98: =IF(D98="", "", VLOOKUP(D98, Sheet3!C:P, 14, FALSE) & ", " & DATEDIF(VLOOKUP(D98, Sheet3!C:N, 12, FALSE), TODAY(), "y") & " Years Experience") | H98: 7 | K98: 2 | L98: 0
C99: Laboratory Technician/Senior | F99: =IF(D99="", "", VLOOKUP(D99, Sheet3!C:P, 14, FALSE) & ", " & DATEDIF(VLOOKUP(D99, Sheet3!C:N, 12, FALSE), TODAY(), "y") & " Years Experience") | H99: 9/8 | K99: 0 | L99: 1
C100: KENYA SNAKEBITE RESEARCH AND INTERVENTION DIVISION | F100: =IF(D100="", "", VLOOKUP(D100, Sheet3!C:P, 14, FALSE) & ", " & DATEDIF(VLOOKUP(D100, Sheet3!C:N, 12, FALSE), TODAY(), "y") & " Years Experience")
C101: Deputy Director, Kenya Snakebite Research and Intervention | F101: =IF(D101="", "", VLOOKUP(D101, Sheet3!C:P, 14, FALSE) & ", " & DATEDIF(VLOOKUP(D101, Sheet3!C:N, 12, FALSE), TODAY(), "y") & " Years Experience") | H101: 3 | K101: 1 | L101: 0
C102: Senior Principal Research Scientist | F102: =IF(D102="", "", VLOOKUP(D102, Sheet3!C:P, 14, FALSE) & ", " & DATEDIF(VLOOKUP(D102, Sheet3!C:N, 12, FALSE), TODAY(), "y") & " Years Experience") | H102: 3 | K102: 1 | L102: 0
C103: ANTIVENOM (BIOLOGICS) QUALITY CONTROL, DEVELOPMENT AND PRODUCTION SECTION | F103: =IF(D103="", "", VLOOKUP(D103, Sheet3!C:P, 14, FALSE) & ", " & DATEDIF(VLOOKUP(D103, Sheet3!C:N, 12, FALSE), TODAY(), "y") & " Years Experience")
...

Sheet Sheet3
A1: S/No. | B1: {=+B1:H41H214B1:H47B1:H47H214B1:H47B1:H53H2B1:I47} -> #NAME? | C1: Payroll Number | D1: Full Name | F1: ID Number | G1: Gender | H1: Age | I1: Designation | J1: Department | K1: Job Group | L1: Employment Status | M1: ROD | N1: DOE | Q1: 0 | Y1: Terms of Employment | Z1: Ethnicity
D2: ADMINISTRATION & HUMAN RESOURCE | Q2: PhD | R2: Masters | S2: Bachelors/Higher Diploma | T2: Diploma | U2: Certificate | V2: KCSE | W2: KCPE | X2: Proffesional Qualification
A3: 1 | B3: 1 | C3: 19901899045 | D3: Dr. Mwethera, Peter Gichuhi | F3: 3731123 | G3: M | H3: 61 | I3: Director General - EL - C01AT | J3: Reproductive Health & Biology | K3: T | L3: 0 - Active | M3: 01/09/2029 | N3: 32908 | O3: Dr. Mwethera, Peter Gichuhi | P3: =SUBSTITUTE(TRIM( IF(COUNTIF(Q3:X3, "*Philosophy*"), "PhD ", "") & IF(COUNTIF(Q3:X3, "*Master*"), "MSc ", "") & IF(COUNTIF(Q3:X3, "*Bachelor*"), "Bachelors ", "") & IF(COUNTIF(Q3:X3, "*Diploma*"), "Dip ", "") & IF(COUNTIF(Q3:X3, "*KCSE*"), "KCSE ", "") & IF(COUNTIF(Q3:X3, "*KCPE*"), "KCPE ", "") & IF(COUNTIF(Q3:X3, "*IHRM*"), "IHRM ", "") & IF(COUNTIF(Q3:X3, "*HRMPB*"), "HRMPB ", "") & IF(COUNTIF(Q3:X3, "*KISM*"), "KISM ", "") & IF(COUNTIF(Q3:X3, "*ICPAK*"), "ICPAK ", "") & IF(COUNTIF(Q3:X3, "*CPA*"), "CPA ", "") & IF(COUNTIF(Q3:X3, "*Strategic Leadership*"), "SLDP ", "") & IF(COUNTIF(Q3:X3, "*Senior Management*"), "SMC ", "") & IF(COUNTIF(Q3:X3, "*Nursing*"), "NCK ", "") & IF(COUNTIF(Q3:X3, "*KMLTTB*"), "KMLTTB ", "") & IF(COUNTIF(Q3:X3, "*Cstat*"), "Cstat ", "") & IF(SUMPRODUCT(LEN(Q3:X3)-LEN(SUBSTITUTE(UPPER(Q3:X3),"CERTIFICATE","")))/11>0, SUMPRODUCT(LEN(Q3:X3)-LEN(SUBSTITUTE(UPPER(Q3:X3),"CERTIFICATE","")))/11 & " Certificates ", "") ), " ", ", ") -> PhD, MSc, Bachelors, KCSE, KCPE | Q3: PhD in Philosophy | R3: Master in Science | S3: Bachelor of Science | V3: KCSE | W3: KCPE | Y3: Local Contract | Z3: Kikuyu
A4: 2 | B4: 2 | C4: 19990495773 | D4: Mrs. Hassan, Hamida Adam | F4: 12701644 | G4: F | H4: 50 | I4: Senior Personal Assistant - EL - T02AN | J4: Administration & HR | K4: N | L4: 0 - Active | M4: 14/08/2034 | N4: 36167 | O4: Mrs. Hassan, Hamida Adam | P4: =SUBSTITUTE(TRIM( IF(COUNTIF(Q4:X4, "*Philosophy*"), "PhD ", "") & IF(COUNTIF(Q4:X4, "*Master*"), "MSc ", "") & IF(COUNTIF(Q4:X4, "*Bachelor*"), "Bachelors ", "") & IF(COUNTIF(Q4:X4, "*Diploma*"), "Dip ", "") & IF(COUNTIF(Q4:X4, "*KCSE*"), "KCSE ", "") & IF(COUNTIF(Q4:X4, "*KCPE*"), "KCPE ", "") & IF(COUNTIF(Q4:X4, "*IHRM*"), "IHRM ", "") & IF(COUNTIF(Q4:X4, "*HRMPB*"), "HRMPB ", "") & IF(COUNTIF(Q4:X4, "*KISM*"), "KISM ", "") & IF(COUNTIF(Q4:X4, "*ICPAK*"), "ICPAK ", "") & IF(COUNTIF(Q4:X4, "*CPA*"), "CPA ", "") & IF(COUNTIF(Q4:X4, "*Strategic Leadership*"), "SLDP ", "") & IF(COUNTIF(Q4:X4, "*Senior Management*"), "SMC ", "") & IF(COUNTIF(Q4:X4, "*Nursing*"), "NCK ", "") & IF(COUNTIF(Q4:X4, "*KMLTTB*"), "KMLTTB ", "") & IF(COUNTIF(Q4:X4, "*Cstat*"), "Cstat ", "") & IF(SUMPRODUCT(LEN(Q4:X4)-LEN(SUBSTITUTE(UPPER(Q4:X4),"CERTIFICATE","")))/11>0, SUMPRODUCT(LEN(Q4:X4)-LEN(SUBSTITUTE(UPPER(Q4:X4),"CERTIFICATE","")))/11 & " Certificates ", "") ), " ", ", ") -> Dip, KCSE, KCPE | T4: Diploma in HRM, PR | V4: KCSE | W4: KCPE | Y4: Permanent | Z4: Luhya
A5: 3 | B5: 3 | C5: 20114215626 | D5: Mr. Manene, Patrick Kimathi | F5: 13361887 | G5: M | H5: 53 | I5: Administrative Officer [1] - EL - C01AN | J5: Administration & HR | K5: N | L5: 0 - Active | M5: 05/04/2032 | N5: 40546 | O5: Mr. Manene, Patrick Kimathi | P5: =SUBSTITUTE(TRIM( IF(COUNTIF(Q5:X5, "*Philosophy*"), "PhD ", "") & IF(COUNTIF(Q5:X5, "*Master*"), "MSc ", "") & IF(COUNTIF(Q5:X5, "*Bachelor*"), "Bachelors ", "") & IF(COUNTIF(Q5:X5, "*Diploma*"), "Dip ", "") & IF(COUNTIF(Q5:X5, "*KCSE*"), "KCSE ", "") & IF(COUNTIF(Q5:X5, "*KCPE*"), "KCPE ", "") & IF(COUNTIF(Q5:X5, "*IHRM*"), "IHRM ", "") & IF(COUNTIF(Q5:X5, "*HRMPB*"), "HRMPB ", "") & IF(COUNTIF(Q5:X5, "*KISM*"), "KISM ", "") & IF(COUNTIF(Q5:X5, "*ICPAK*"), "ICPAK ", "") & IF(COUNTIF(Q5:X5, "*CPA*"), "CPA ", "") & IF(COUNTIF(Q5:X5, "*Strategic Leadership*"), "SLDP ", "") & IF(COUNTIF(Q5:X5, "*Senior Management*"), "SMC ", "") & IF(COUNTIF(Q5:X5, "*Nursing*"), "NCK ", "") & IF(COUNTIF(Q5:X5, "*KMLTTB*"), "KMLTTB ", "") & IF(COUNTIF(Q5:X5, "*Cstat*"), "Cstat ", "") & IF(SUMPRODUCT(LEN(Q5:X5)-LEN(SUBSTITUTE(UPPER(Q5:X5),"CERTIFICATE","")))/11>0, SUMPRODUCT(LEN(Q5:X5)-LEN(SUBSTITUTE(UPPER(Q5:X5),"CERTIFICATE","")))/11 & " Certificates ", "") ), " ", ", ") -> MSc, Bachelors, Dip, KCSE, KCPE, IHRM, HRMPB, SLDP, SMC | R5: Master in Public Policy and Administration | S5: Bachelor of Arts | T5: Diploma in Human Resource Management | V5: KCSE | W5: KCPE | X5: IHRM, HRMPB, KSG (Strategic Leadership Development Programme, Senior Management Course) | Y5: Permanent | Z5: Meru
A6: 4 | B6: 4 | C6: 20060933912 | D6: Mrs. Maimuna, Juma Alhamid | F6: 23888972 | G6: F | H6: 43 | I6: Human Resource Officer [2] - EL - C04AM | J6: Administration & HR | K6: M | L6: 0 - Active | M6: 24/05/2041 | N6: 38724 | O6: Mrs. Maimuna, Juma Alhamid | P6: =SUBSTITUTE(TRIM( IF(COUNTIF(Q6:X6, "*Philosophy*"), "PhD ", "") & IF(COUNTIF(Q6:X6, "*Master*"), "MSc ", "") & IF(COUNTIF(Q6:X6, "*Bachelor*"), "Bachelors ", "") & IF(COUNTIF(Q6:X6, "*Diploma*"), "Dip ", "") & IF(COUNTIF(Q6:X6, "*KCSE*"), "KCSE ", "") & IF(COUNTIF(Q6:X6, "*KCPE*"), "KCPE ", "") & IF(COUNTIF(Q6:X6, "*IHRM*"), "IHRM ", "") & IF(COUNTIF(Q6:X6, "*HRMPB*"), "HRMPB ", "") & IF(COUNTIF(Q6:X6, "*KISM*"), "KISM ", "") & IF(COUNTIF(Q6:X6, "*ICPAK*"), "ICPAK ", "") & IF(COUNTIF(Q6:X6, "*CPA*"), "CPA ", "") & IF(COUNTIF(Q6:X6, "*Strategic Leadership*"), "SLDP ", "") & IF(COUNTIF(Q6:X6, "*Senior Management*"), "SMC ", "") & IF(COUNTIF(Q6:X6, "*Nursing*"), "NCK ", "") & IF(COUNTIF(Q6:X6, "*KMLTTB*"), "KMLTTB ", "") & IF(COUNTIF(Q6:X6, "*Cstat*"), "Cstat ", "") & IF(SUMPRODUCT(LEN(Q6:X6)-LEN(SUBSTITUTE(UPPER(Q6:X6),"CERTIFICATE","")))/11>0, SUMPRODUCT(LEN(Q6:X6)-LEN(SUBSTITUTE(UPPER(Q6:X6),"CERTIFICATE","")))/11 & " Certificates ", "") ), " ", ", ") -> Bachelors, KCSE, KCPE, KISM | S6: Bachelorof Business Management ( Supplies and Procurement option) | V6: KCSE | W6: KCPE | X6: KISM | Y6: Permanent | Z6: Bajun
A7: 5 | B7: 5 | C7: 20210646216 | D7: Mrs. Kamanda, Cynicah Nyaboke | F7: 24212658 | G7: F | H7: 40 | I7: Accountant [1] - EL - D01AM | J7: Administration & HR | K7: M | L7: 0 - Active | M7: 31/07/2027 | N7: 44197 | O7: Mrs. Kamanda, Cynicah Nyaboke | P7: =SUBSTITUTE(TRIM( IF(COUNTIF(Q7:X7, "*Philosophy*"), "PhD ", "") & IF(COUNTIF(Q7:X7, "*Master*"), "MSc ", "") & IF(COUNTIF(Q7:X7, "*Bachelor*"), "Bachelors ", "") & IF(COUNTIF(Q7:X7, "*Diploma*"), "Dip ", "") & IF(COUNTIF(Q7:X7, "*KCSE*"), "KCSE ", "") & IF(COUNTIF(Q7:X7, "*KCPE*"), "KCPE ", "") & IF(COUNTIF(Q7:X7, "*IHRM*"), "IHRM ", "") & IF(COUNTIF(Q7:X7, "*HRMPB*"), "HRMPB ", "") & IF(COUNTIF(Q7:X7, "*KISM*"), "KISM ", "") & IF(COUNTIF(Q7:X7, "*ICPAK*"), "ICPAK ", "") & IF(COUNTIF(Q7:X7, "*CPA*"), "CPA ", "") & IF(COUNTIF(Q7:X7, "*Strategic Leadership*"), "SLDP ", "") & IF(COUNTIF(Q7:X7, "*Senior Management*"), "SMC ", "") & IF(COUNTIF(Q7:X7, "*Nursing*"), "NCK ", "") & IF(COUNTIF(Q7:X7, "*KMLTTB*"), "KMLTTB ", "") & IF(COUNTIF(Q7:X7, "*Cstat*"), "Cstat ", "") & IF(SUMPRODUCT(LEN(Q7:X7)-LEN(SUBSTITUTE(UPPER(Q7:X7),"CERTIFICATE","")))/11>0, SUMPRODUCT(LEN(Q7:X7)-LEN(SUBSTITUTE(UPPER(Q7:X7),"CERTIFICATE","")))/11 & " Certificates ", "") ), " ", ", ") -> MSc, Bachelors, Dip, KCSE, KCPE, ICPAK, CPA, 1, Certificates | R7: Master of Business Administration,Finace Option | S7: Bachelor of Arts in Commerce | T7: Diploma in Business Management in TEP | U7: Certificate in Public Accounts | V7: KCSE | W7: KCPE | X7: ICPAK | Y7: Local Contract | Z7: Kisii
A8: 6 | B8: 6 | C8: 20160708902 | D8: Mr. Ochien'g, Zaddock Ojall | F8: 24938714 | G8: M | H8: 38 | I8: Administrative Officer [3] - EL - C01AL | J8: Administration & HR | K8: L | L8: 0 - Active | M8: 31/07/2027 | N8: 42377 | O8: Mr. Ochien'g, Zaddock Ojall | P8: =SUBSTITUTE(TRIM( IF(COUNTIF(Q8:X8, "*Philosophy*"), "PhD ", "") & IF(COUNTIF(Q8:X8, "*Master*"), "MSc ", "") & IF(COUNTIF(Q8:X8, "*Bachelor*"), "Bachelors ", "") & IF(COUNTIF(Q8:X8, "*Diploma*"), "Dip ", "") & IF(COUNTIF(Q8:X8, "*KCSE*"), "KCSE ", "") & IF(COUNTIF(Q8:X8, "*KCPE*"), "KCPE ", "") & IF(COUNTIF(Q8:X8, "*IHRM*"), "IHRM ", "") & IF(COUNTIF(Q8:X8, "*HRMPB*"), "HRMPB ", "") & IF(COUNTIF(Q8:X8, "*KISM*"), "KISM ", "") & IF(COUNTIF(Q8:X8, "*ICPAK*"), "ICPAK ", "") & IF(COUNTIF(Q8:X8, "*CPA*"), "CPA ", "") & IF(COUNTIF(Q8:X8, "*Strategic Leadership*"), "SLDP ", "") & IF(COUNTIF(Q8:X8, "*Senior Management*"), "SMC ", "") & IF(COUNTIF(Q8:X8, "*Nursing*"), "NCK ", "") & IF(COUNTIF(Q8:X8, "*KMLTTB*"), "KMLTTB ", "") & IF(COUNTIF(Q8:X8, "*Cstat*"), "Cstat ", "") & IF(SUMPRODUCT(LEN(Q8:X8)-LEN(SUBSTITUTE(UPPER(Q8:X8),"CERTIFICATE","")))/11>0, SUMPRODUCT(LEN(Q8:X8)-LEN(SUBSTITUTE(UPPER(Q8:X8),"CERTIFICATE","")))/11 & " Certificates ", "") ), " ", ", ") -> Bachelors, KCSE, KCPE | S8: Bachelor of Arts In Human Resource | V8: KCSE | W8: KCPE | Y8: Local Contract | Z8: Luo
A9: 7 | B9: 7 | C9: 20220598180 | D9: Mr. Owuor, John Robert | F9: 31860798 | G9: M | H9: 30 | I9: Human Resource Officer [3] - EL - C04AL | J9: Administration & HR | K9: L | L9: 0 - Active | M9: 30/01/2028 | N9: 44563 | O9: Mr. Owuor, John Robert | P9: =SUBSTITUTE(TRIM( IF(COUNTIF(Q9:X9, "*Philosophy*"), "PhD ", "") & IF(COUNTIF(Q9:X9, "*Master*"), "MSc ", "") & IF(COUNTIF(Q9:X9, "*Bachelor*"), "Bachelors ", "") & IF(COUNTIF(Q9:X9, "*Diploma*"), "Dip ", "") & IF(COUNTIF(Q9:X9, "*KCSE*"), "KCSE ", "") & IF(COUNTIF(Q9:X9, "*KCPE*"), "KCPE ", "") & IF(COUNTIF(Q9:X9, "*IHRM*"), "IHRM ", "") & IF(COUNTIF(Q9:X9, "*HRMPB*"), "HRMPB ", "") & IF(COUNTIF(Q9:X9, "*KISM*"), "KISM ", "") & IF(COUNTIF(Q9:X9, "*ICPAK*"), "ICPAK ", "") & IF(COUNTIF(Q9:X9, "*CPA*"), "CPA ", "") & IF(COUNTIF(Q9:X9, "*Strategic Leadership*"), "SLDP ", "") & IF(COUNTIF(Q9:X9, "*Senior Management*"), "SMC ", "") & IF(COUNTIF(Q9:X9, "*Nursing*"), "NCK ", "") & IF(COUNTIF(Q9:X9, "*KMLTTB*"), "KMLTTB ", "") & IF(COUNTIF(Q9:X9, "*Cstat*"), "Cstat ", "") & IF(SUMPRODUCT(LEN(Q9:X9)-LEN(SUBSTITUTE(UPPER(Q9:X9),"CERTIFICATE","")))/11>0, SUMPRODUCT(LEN(Q9:X9)-LEN(SUBSTITUTE(UPPER(Q9:X9),"CERTIFICATE","")))/11 & " Certificates ", "") ), " ", ", ") -> Bachelors, KCSE, KCPE | S9: Bachelor of Business Administration,with IT(Finance Option) | V9: KCSE | W9: KCPE | Y9: Local Contract | Z9: Luo
A10: 8 | B10: 8 | C10: 19990495812 | D10: Ms. Rotich, Celestine Jepkoech | F10: 20257607 | G10: F | H10: 48 | I10: Librarian [2] - EL - M05AK | J10: Administration & HR | K10: K | L10: 0 - Active | M10: 27/11/2036 | N10: 36166 | O10: Ms. Rotich, Celestine Jepkoech | P10: =SUBSTITUTE(TRIM( IF(COUNTIF(Q10:X10, "*Philosophy*"), "PhD ", "") & IF(COUNTIF(Q10:X10, "*Master*"), "MSc ", "") & IF(COUNTIF(Q10:X10, "*Bachelor*"), "Bachelors ", "") & IF(COUNTIF(Q10:X10, "*Diploma*"), "Dip ", "") & IF(COUNTIF(Q10:X10, "*KCSE*"), "KCSE ", "") & IF(COUNTIF(Q10:X10, "*KCPE*"), "KCPE ", "") & IF(COUNTIF(Q10:X10, "*IHRM*"), "IHRM ", "") & IF(COUNTIF(Q10:X10, "*HRMPB*"), "HRMPB ", "") & IF(COUNTIF(Q10:X10, "*KISM*"), "KISM ", "") & IF(COUNTIF(Q10:X10, "*ICPAK*"), "ICPAK ", "") & IF(COUNTIF(Q10:X10, "*CPA*"), "CPA ", "") & IF(COUNTIF(Q10:X10, "*Strategic Leadership*"), "SLDP ", "") & IF(COUNTIF(Q10:X10, "*Senior Management*"), "SMC ", "") & IF(COUNTIF(Q10:X10, "*Nursing*"), "NCK ", "") & IF(COUNTIF(Q10:X10, "*KMLTTB*"), "KMLTTB ", "") & IF(COUNTIF(Q10:X10, "*Cstat*"), "Cstat ", "") & IF(SUMPRODUCT(LEN(Q10:X10)-LEN(SUBSTITUTE(UPPER(Q10:X10),"CERTIFICATE","")))/11>0, SUMPRODUCT(LEN(Q10:X10)-LEN(SUBSTITUTE(UPPER(Q10:X10),"CERTIFICATE","")))/11 & " Certificates ", "") ), " ", ", ") -> Dip, KCSE, KCPE | S10: Higher Diploma in Archives and Records Management | V10: KCSE | W10: KCPE | Y10: Permanent | Z10: Kalenjin
A11: 9 | B11: 9 | C11: 20077018333 | D11: Mrs. Muthoni, Elizabeth Ng'ang'a | F11: 10998397 | G11: F | H11: 53 | I11: Telephone Officer [1] - EL - M09AJ | J11: Administration & HR | K11: J | L11: 0 - Active | M11: 19/12/2031 | N11: 39083 | O11: Mrs. Muthoni, Elizabeth Ng'ang'a | P11: =SUBSTITUTE(TRIM( IF(COUNTIF(Q11:X11, "*Philosophy*"), "PhD ", "") & IF(COUNTIF(Q11:X11, "*Master*"), "MSc ", "") & IF(COUNTIF(Q11:X11, "*Bachelor*"), "Bachelors ", "") & IF(COUNTIF(Q11:X11, "*Diploma*"), "Dip ", "") & IF(COUNTIF(Q11:X11, "*KCSE*"), "KCSE ", "") & IF(COUNTIF(Q11:X11, "*KCPE*"), "KCPE ", "") & IF(COUNTIF(Q11:X11, "*IHRM*"), "IHRM ", "") & IF(COUNTIF(Q11:X11, "*HRMPB*"), "HRMPB ", "") & IF(COUNTIF(Q11:X11, "*KISM*"), "KISM ", "") & IF(COUNTIF(Q11:X11, "*ICPAK*"), "ICPAK ", "") & IF(COUNTIF(Q11:X11, "*CPA*"), "CPA ", "") & IF(COUNTIF(Q11:X11, "*Strategic Leadership*"), "SLDP ", "") & IF(COUNTIF(Q11:X11, "*Senior Management*"), "SMC ", "") & IF(COUNTIF(Q11:X11, "*Nursing*"), "NCK ", "") & IF(COUNTIF(Q11:X11, "*KMLTTB*"), "KMLTTB ", "") & IF(COUNTIF(Q11:X11, "*Cstat*"), "Cstat ", "") & IF(SUMPRODUCT(LEN(Q11:X11)-LEN(SUBSTITUTE(UPPER(Q11:X11),"CERTIFICATE","")))/11>0, SUMPRODUCT(LEN(Q11:X11)-LEN(SUBSTITUTE(UPPER(Q11:X11),"CERTIFICATE","")))/11 & " Certificates ", "") ), " ", ", ") -> Dip, KCSE, KCPE | T11: Diploma in Telephone Receptionist | V11: KCSE | W11: KCPE | Y11: Permanent | Z11: Kikuyu
A12: 10 | B12: 10 | C12: 20077018202 | D12: Ms. Lithira, Sabina Nkoyai | F12: 13133273 | G12: F | H12: 51 | I12: Telephone Officer [2] - EL - M09AH | J12: Administration & HR | K12: H | L12: 0 - Active | M12: 27/08/2033 | N12: 39417 | O12: Ms. Lithira, Sabina Nkoyai | P12: =SUBSTITUTE(TRIM( IF(COUNTIF(Q12:X12, "*Philosophy*"), "PhD ", "") & IF(COUNTIF(Q12:X12, "*Master*"), "MSc ", "") & IF(COUNTIF(Q12:X12, "*Bachelor*"), "Bachelors ", "") & IF(COUNTIF(Q12:X12, "*Diploma*"), "Dip ", "") & IF(COUNTIF(Q12:X12, "*KCSE*"), "KCSE ", "") & IF(COUNTIF(Q12:X12, "*KCPE*"), "KCPE ", "") & IF(COUNTIF(Q12:X12, "*IHRM*"), "IHRM ", "") & IF(COUNTIF(Q12:X12, "*HRMPB*"), "HRMPB ", "") & IF(COUNTIF(Q12:X12, "*KISM*"), "KISM ", "") & IF(COUNTIF(Q12:X12, "*ICPAK*"), "ICPAK ", "") & IF(COUNTIF(Q12:X12, "*CPA*"), "CPA ", "") & IF(COUNTIF(Q12:X12, "*Strategic Leadership*"), "SLDP ", "") & IF(COUNTIF(Q12:X12, "*Senior Management*"), "SMC ", "") & IF(COUNTIF(Q12:X12, "*Nursing*"), "NCK ", "") & IF(COUNTIF(Q12:X12, "*KMLTTB*"), "KMLTTB ", "") & IF(COUNTIF(Q12:X12, "*Cstat*"), "Cstat ", "") & IF(SUMPRODUCT(LEN(Q12:X12)-LEN(SUBSTITUTE(UPPER(Q12:X12),"CERTIFICATE","")))/11>0, SUMPRODUCT(LEN(Q12:X12)-LEN(SUBSTITUTE(UPPER(Q12:X12),"CERTIFICATE","")))/11 & " Certificates ", "") ), " ", ", ") -> KCSE, KCPE, 1, Certificates | U12: Certificate in Telephone Teceptionist and Supervision | V12: KCSE | W12: KCPE | Y12: Permanent | Z12: Meru
A13: 11 | B13: 11 | C13: 20220598130 | D13: Miss. Koech, Beatrice Chebet | F13: 35698228 | G13: F | H13: 27 | I13: Office Assistant [2] - EL - T04DH | J13: Administration & HR | K13: H | L13: 0 - Active | M13: 30/01/2028 | N13: 44563 | O13: Miss. Koech, Beatrice Chebet | P13: =SUBSTITUTE(TRIM( IF(COUNTIF(Q13:X13, "*Philosophy*"), "PhD ", "") & IF(COUNTIF(Q13:X13, "*Master*"), "MSc ", "") & IF(COUNTIF(Q13:X13, "*Bachelor*"), "Bachelors ", "") & IF(COUNTIF(Q13:X13, "*Diploma*"), "Dip ", "") & IF(COUNTIF(Q13:X13, "*KCSE*"), "KCSE ", "") & IF(COUNTIF(Q13:X13, "*KCPE*"), "KCPE ", "") & IF(COUNTIF(Q13:X13, "*IHRM*"), "IHRM ", "") & IF(COUNTIF(Q13:X13, "*HRMPB*"), "HRMPB ", "") & IF(COUNTIF(Q13:X13, "*KISM*"), "KISM ", "") & IF(COUNTIF(Q13:X13, "*ICPAK*"), "ICPAK ", "") & IF(COUNTIF(Q13:X13, "*CPA*"), "CPA ", "") & IF(COUNTIF(Q13:X13, "*Strategic Leadership*"), "SLDP ", "") & IF(COUNTIF(Q13:X13, "*Senior Management*"), "SMC ", "") & IF(COUNTIF(Q13:X13, "*Nursing*"), "NCK ", "") & IF(COUNTIF(Q13:X13, "*KMLTTB*"), "KMLTTB ", "") & IF(COUNTIF(Q13:X13, "*Cstat*"), "Cstat ", "") & IF(SUMPRODUCT(LEN(Q13:X13)-LEN(SUBSTITUTE(UPPER(Q13:X13),"CERTIFICATE","")))/11>0, SUMPRODUCT(LEN(Q13:X13)-LEN(SUBSTITUTE(UPPER(Q13:X13),"CERTIFICATE","")))/11 & " Certificates ", "") ), " ", ", ") -> KCSE, KCPE | V13: KCSE | W13: KCPE | Y13: Local Contract | Z13: Kalenjin
A14: 12 | B14: 12 | C14: 20077018391 | D14: Mrs. Kassim, Kulthum Mohamed | F14: 11625899 | G14: F | H14: 52 | I14: Clerical Officer - EL - T03AG | J14: Administration & HR | K14: G | L14: 0 - Active | M14: 30/04/2032 | N14: 39083 | O14: Mrs. Kassim, Kulthum Mohamed | P14: =SUBSTITUTE(TRIM( IF(COUNTIF(Q14:X14, "*Philosophy*"), "PhD ", "") & IF(COUNTIF(Q14:X14, "*Master*"), "MSc ", "") & IF(COUNTIF(Q14:X14, "*Bachelor*"), "Bachelors ", "") & IF(COUNTIF(Q14:X14, "*Diploma*"), "Dip ", "") & IF(COUNTIF(Q14:X14, "*KCSE*"), "KCSE ", "") & IF(COUNTIF(Q14:X14, "*KCPE*"), "KCPE ", "") & IF(COUNTIF(Q14:X14, "*IHRM*"), "IHRM ", "") & IF(COUNTIF(Q14:X14, "*HRMPB*"), "HRMPB ", "") & IF(COUNTIF(Q14:X14, "*KISM*"), "KISM ", "") & IF(COUNTIF(Q14:X14, "*ICPAK*"), "ICPAK ", "") & IF(COUNTIF(Q14:X14, "*CPA*"), "CPA ", "") & IF(COUNTIF(Q14:X14, "*Strategic Leadership*"), "SLDP ", "") & IF(COUNTIF(Q14:X14, "*Senior Management*"), "SMC ", "") & IF(COUNTIF(Q14:X14, "*Nursing*"), "NCK ", "") & IF(COUNTIF(Q14:X14, "*KMLTTB*"), "KMLTTB ", "") & IF(COUNTIF(Q14:X14, "*Cstat*"), "Cstat ", "") & IF(SUMPRODUCT(LEN(Q14:X14)-LEN(SUBSTITUTE(UPPER(Q14:X14),"CERTIFICATE","")))/11>0, SUMPRODUCT(LEN(Q14:X14)-LEN(SUBSTITUTE(UPPER(Q14:X14),"CERTIFICATE","")))/11 & " Certificates ", "") ), " ", ", ") -> Dip, KCSE, KCPE | T14: Diploma in Human Resource | V14: KCSE | W14: KCPE | Y14: Permanent | Z14: Bajun
A15: 13 | B15: 13 | C15: 20240300989 | D15: Miss. Opanga, Brenda Kwamboka | F15: 36675697 | G15: F | H15: 26 | I15: Clerical Officer - EL - T03AG | J15: Administration & HR | K15: G | L15: 0 - Active | M15: 22/01/2028 | N15: 45334 | O15: Miss. Opanga, Brenda Kwamboka | P15: =SUBSTITUTE(TRIM( IF(COUNTIF(Q15:X15, "*Philosophy*"), "PhD ", "") & IF(COUNTIF(Q15:X15, "*Master*"), "MSc ", "") & IF(COUNTIF(Q15:X15, "*Bachelor*"), "Bachelors ", "") & IF(COUNTIF(Q15:X15, "*Diploma*"), "Dip ", "") & IF(COUNTIF(Q15:X15, "*KCSE*"), "KCSE ", "") & IF(COUNTIF(Q15:X15, "*KCPE*"), "KCPE ", "") & IF(COUNTIF(Q15:X15, "*IHRM*"), "IHRM ", "") & IF(COUNTIF(Q15:X15, "*HRMPB*"), "HRMPB ", "") & IF(COUNTIF(Q15:X15, "*KISM*"), "KISM ", "") & IF(COUNTIF(Q15:X15, "*ICPAK*"), "ICPAK ", "") & IF(COUNTIF(Q15:X15, "*CPA*"), "CPA ", "") & IF(COUNTIF(Q15:X15, "*Strategic Leadership*"), "SLDP ", "") & IF(COUNTIF(Q15:X15, "*Senior Management*"), "SMC ", "") & IF(COUNTIF(Q15:X15, "*Nursing*"), "NCK ", "") & IF(COUNTIF(Q15:X15, "*KMLTTB*"), "KMLTTB ", "") & IF(COUNTIF(Q15:X15, "*Cstat*"), "Cstat ", "") & IF(SUMPRODUCT(LEN(Q15:X15)-LEN(SUBSTITUTE(UPPER(Q15:X15),"CERTIFICATE","")))/11>0, SUMPRODUCT(LEN(Q15:X15)-LEN(SUBSTITUTE(UPPER(Q15:X15),"CERTIFICATE","")))/11 & " Certificates ", "") ), " ", ", ") -> KCSE, KCPE | V15: KCSE | W15: KCPE | Y15: Local Contract | Z15: Kisii
F16: ANIMANL SCIENCE WELFARE & ETHICS | P16: =SUBSTITUTE(TRIM( IF(COUNTIF(Q16:X16, "*Philosophy*"), "PhD ", "") & IF(COUNTIF(Q16:X16, "*Master*"), "MSc ", "") & IF(COUNTIF(Q16:X16, "*Bachelor*"), "Bachelors ", "") & IF(COUNTIF(Q16:X16, "*Diploma*"), "Dip ", "") & IF(COUNTIF(Q16:X16, "*KCSE*"), "KCSE ", "") & IF(COUNTIF(Q16:X16, "*KCPE*"), "KCPE ", "") & IF(COUNTIF(Q16:X16, "*IHRM*"), "IHRM ", "") & IF(COUNTIF(Q16:X16, "*HRMPB*"), "HRMPB ", "") & IF(COUNTIF(Q16:X16, "*KISM*"), "KISM ", "") & IF(COUNTIF(Q16:X16, "*ICPAK*"), "ICPAK ", "") & IF(COUNTIF(Q16:X16, "*CPA*"), "CPA ", "") & IF(COUNTIF(Q16:X16, "*Strategic Leadership*"), "SLDP ", "") & IF(COUNTIF(Q16:X16, "*Senior Management*"), "SMC ", "") & IF(COUNTIF(Q16:X16, "*Nursing*"), "NCK ", "") & IF(COUNTIF(Q16:X16, "*KMLTTB*"), "KMLTTB ", "") & IF(COUNTIF(Q16:X16, "*Cstat*"), "Cstat ", "") & IF(SUMPRODUCT(LEN(Q16:X16)-LEN(SUBSTITUTE(UPPER(Q16:X16),"CERTIFICATE","")))/11>0, SUMPRODUCT(LEN(Q16:X16)-LEN(SUBSTITUTE(UPPER(Q16:X16),"CERTIFICATE","")))/11 & " Certificates ", "") ), " ", ", ") -> KCSE | V16: KCSE
A17: 14 | B17: 14 | C17: 19871318408 | D17: Dr. Chivatsi, Chai Daniel | F17: 5336502 | G17: M | H17: 65 | I17: Chief Veterinary Officer - EL - H04AQ | J17: Animal Science &Welfare ethics | K17: Q | L17: 0 - Active | M17: 01/07/2025 | N17: 31930 | O17: Dr. Chivatsi, Chai Daniel | P17: =SUBSTITUTE(TRIM( IF(COUNTIF(Q17:X17, "*Philosophy*"), "PhD ", "") & IF(COUNTIF(Q17:X17, "*Master*"), "MSc ", "") & IF(COUNTIF(Q17:X17, "*Bachelor*"), "Bachelors ", "") & IF(COUNTIF(Q17:X17, "*Diploma*"), "Dip ", "") & IF(COUNTIF(Q17:X17, "*KCSE*"), "KCSE ", "") & IF(COUNTIF(Q17:X17, "*KCPE*"), "KCPE ", "") & IF(COUNTIF(Q17:X17, "*IHRM*"), "IHRM ", "") & IF(COUNTIF(Q17:X17, "*HRMPB*"), "HRMPB ", "") & IF(COUNTIF(Q17:X17, "*KISM*"), "KISM ", "") & IF(COUNTIF(Q17:X17, "*ICPAK*"), "ICPAK ", "") & IF(COUNTIF(Q17:X17, "*CPA*"), "CPA ", "") & IF(COUNTIF(Q17:X17, "*Strategic Leadership*"), "SLDP ", "") & IF(COUNTIF(Q17:X17, "*Senior Management*"), "SMC ", "") & IF(COUNTIF(Q17:X17, "*Nursing*"), "NCK ", "") & IF(COUNTIF(Q17:X17, "*KMLTTB*"), "KMLTTB ", "") & IF(COUNTIF(Q17:X17, "*Cstat*"), "Cstat ", "") & IF(SUMPRODUCT(LEN(Q17:X17)-LEN(SUBSTITUTE(UPPER(Q17:X17),"CERTIFICATE","")))/11>0, SUMPRODUCT(LEN(Q17:X17)-LEN(SUBSTITUTE(UPPER(Q17:X17),"CERTIFICATE","")))/11 & " Certificates ", "") ), " ", ", ") -> MSc, Bachelors, KCSE, KCPE, SMC, 1, Certificates | R17: Master of Science in Veterinary Pathology and Diagnostics | S17: Bachelor of Veterinary Medicine | U17: Advanced Certificate of Education | V17: KCSE | W17: KCPE | X17: Senior Management Course | Y17: Permanent | Z17: Mijikenda
A18: 15 | B18: 15 | C18: 20077017769 | D18: Dr. Akinyi, Mercy Yvonne | F18: 21963939 | G18: F | H18: 44 | I18: Senior Research Scientist [2] - ET - R01AP | J18: Animal Science &Welfare ethics | K18: P | L18: 0 - Active | M18: 30/01/2051 | N18: 39427 | O18: Mrs. Akinyi, Mercy Yvonne | P18: =SUBSTITUTE(TRIM( IF(COUNTIF(Q18:X18, "*Philosophy*"), "PhD ", "") & IF(COUNTIF(Q18:X18, "*Master*"), "MSc ", "") & IF(COUNTIF(Q18:X18, "*Bachelor*"), "Bachelors ", "") & IF(COUNTIF(Q18:X18, "*Diploma*"), "Dip ", "") & IF(COUNTIF(Q18:X18, "*KCSE*"), "KCSE ", "") & IF(COUNTIF(Q18:X18, "*KCPE*"), "KCPE ", "") & IF(COUNTIF(Q18:X18, "*IHRM*"), "IHRM ", "") & IF(COUNTIF(Q18:X18, "*HRMPB*"), "HRMPB ", "") & IF(COUNTIF(Q18:X18, "*KISM*"), "KISM ", "") & IF(COUNTIF(Q18:X18, "*ICPAK*"), "ICPAK ", "") & IF(COUNTIF(Q18:X18, "*CPA*"), "CPA ", "") & IF(COUNTIF(Q18:X18, "*Strategic Leadership*"), "SLDP ", "") & IF(COUNTIF(Q18:X18, "*Senior Management*"), "SMC ", "") & IF(COUNTIF(Q18:X18, "*Nursing*"), "NCK ", "") & IF(COUNTIF(Q18:X18, "*KMLTTB*"), "KMLTTB ", "") & IF(COUNTIF(Q18:X18, "*Cstat*"), "Cstat ", "") & IF(SUMPRODUCT(LEN(Q18:X18)-LEN(SUBSTITUTE(UPPER(Q18:X18),"CERTIFICATE","")))/11>0, SUMPRODUCT(LEN(Q18:X18)-LEN(SUBSTITUTE(UPPER(Q18:X18),"CERTIFICATE","")))/11 & " Certificates ", "") ), " ", ", ") -> PhD, MSc, Bachelors, KCSE, KCPE, 1, Certificates | Q18: Doctor of Philosophy | R18: Master of Science in Medical physiology | S18: Bachelor o of veterinary medicine | V18: KCSE | W18: KCPE | X18: Certificate of Registration of a Veterinary Surgeon | Y18: Permanent | Z18: Luo
A19: 16 | B19: 16 | C19: 20030731445 | D19: Mr. Kariuki, Kenneth Waititu | F19: 20742989 | G19: M | H19: 47 | I19: Senior Laboratory Technologist - EL - L07CM | J19: Animal Science &Welfare ethics | K19: M | L19: 0 - Active | M19: 09/10/2037 | N19: 37867 | O19: Mr. Kariuki, Kenneth Waititu | P19: =SUBSTITUTE(TRIM( IF(COUNTIF(Q19:X19, "*Philosophy*"), "PhD ", "") & IF(COUNTIF(Q19:X19, "*Master*"), "MSc ", "") & IF(COUNTIF(Q19:X19, "*Bachelor*"), "Bachelors ", "") & IF(COUNTIF(Q19:X19, "*Diploma*"), "Dip ", "") & IF(COUNTIF(Q19:X19, "*KCSE*"), "KCSE ", "") & IF(COUNTIF(Q19:X19, "*KCPE*"), "KCPE ", "") & IF(COUNTIF(Q19:X19, "*IHRM*"), "IHRM ", "") & IF(COUNTIF(Q19:X19, "*HRMPB*"), "HRMPB ", "") & IF(COUNTIF(Q19:X19, "*KISM*"), "KISM ", "") & IF(COUNTIF(Q19:X19, "*ICPAK*"), "ICPAK ", "") & IF(COUNTIF(Q19:X19, "*CPA*"), "CPA ", "") & IF(COUNTIF(Q19:X19, "*Strategic Leadership*"), "SLDP ", "") & IF(COUNTIF(Q19:X19, "*Senior Management*"), "SMC ", "") & IF(COUNTIF(Q19:X19, "*Nursing*"), "NCK ", "") & IF(COUNTIF(Q19:X19, "*KMLTTB*"), "KMLTTB ", "") & IF(COUNTIF(Q19:X19, "*Cstat*"), "Cstat ", "") & IF(SUMPRODUCT(LEN(Q19:X19)-LEN(SUBSTITUTE(UPPER(Q19:X19),"CERTIFICATE","")))/11>0, SUMPRODUCT(LEN(Q19:X19)-LEN(SUBSTITUTE(UPPER(Q19:X19),"CERTIFICATE","")))/11 & " Certificates ", "") ), " ", ", ") -> MSc, Bachelors, Dip, KCSE, KCPE | R19: Master of Science in Medical Microbiology | S19: Bachelor of Science in Public Health | T19: Diploma in Medical Laboratory Technology | V19: KCSE | W19: KCPE | Y19: Permanent | Z19: Kikuyu
A20: 17 | B20: 17 | C20: 20178600817 | D20: Mr. Nashon, Wanjala Wavumbah | F20: 28951215 | G20: M | H20: 33 | I20: Veterinary Officer - EL - H04AM | J20: Animal Science &Welfare ethics | K20: M | L20: 0 - Active | M20: 30/11/2027 | N20: 42747 | O20: Mr. Nashon, Wanjala Wavumbah | P20: =SUBSTITUTE(TRIM( IF(COUNTIF(Q20:X20, "*Philosophy*"), "PhD ", "") & IF(COUNTIF(Q20:X20, "*Master*"), "MSc ", "") & IF(COUNTIF(Q20:X20, "*Bachelor*"), "Bachelors ", "") & IF(COUNTIF(Q20:X20, "*Diploma*"), "Dip ", "") & IF(COUNTIF(Q20:X20, "*KCSE*"), "KCSE ", "") & IF(COUNTIF(Q20:X20, "*KCPE*"), "KCPE ", "") & IF(COUNTIF(Q20:X20, "*IHRM*"), "IHRM ", "") & IF(COUNTIF(Q20:X20, "*HRMPB*"), "HRMPB ", "") & IF(COUNTIF(Q20:X20, "*KISM*"), "KISM ", "") & IF(COUNTIF(Q20:X20, "*ICPAK*"), "ICPAK ", "") & IF(COUNTIF(Q20:X20, "*CPA*"), "CPA ", "") & IF(COUNTIF(Q20:X20, "*Strategic Leadership*"), "SLDP ", "") & IF(COUNTIF(Q20:X20, "*Senior Management*"), "SMC ", "") & IF(COUNTIF(Q20:X20, "*Nursing*"), "NCK ", "") & IF(COUNTIF(Q20:X20, "*KMLTTB*"), "KMLTTB ", "") & IF(COUNTIF(Q20:X20, "*Cstat*"), "Cstat ", "") & IF(SUMPRODUCT(LEN(Q20:X20)-LEN(SUBSTITUTE(UPPER(Q20:X20),"CERTIFICATE","")))/11>0, SUMPRODUCT(LEN(Q20:X20)-LEN(SUBSTITUTE(UPPER(Q20:X20),"CERTIFICATE","")))/11 & " Certificates ", "") ), " ", ", ") -> MSc, Bachelors, KCSE, KCPE, 1, Certificates | R20: Master of Science in Veterinary Epidemiology and Economics. | S20: Bachelor of veterinary medicine | V20: KCSE | W20: KCPE | X20: Certificate of Registration of a Veterinary Surgeon | Y20: Local Contract | Z20: Luhya
A21: 18 | B21: 18 | C21: 20178600833 | D21: Mrs. Mwadime, Janet Mghambi | F21: 28189079 | G21: F | H21: 34 | I21: Veterinary Officer - EL - H04AM | J21: Animal Science &Welfare ethics | K21: M | L21: 0 - Active | M21: 30/11/2027 | N21: 42747 | O21: Mrs. Mwadime, Janet Mghambi | P21: =SUBSTITUTE(TRIM( IF(COUNTIF(Q21:X21, "*Philosophy*"), "PhD ", "") & IF(COUNTIF(Q21:X21, "*Master*"), "MSc ", "") & IF(COUNTIF(Q21:X21, "*Bachelor*"), "Bachelors ", "") & IF(COUNTIF(Q21:X21, "*Diploma*"), "Dip ", "") & IF(COUNTIF(Q21:X21, "*KCSE*"), "KCSE ", "") & IF(COUNTIF(Q21:X21, "*KCPE*"), "KCPE ", "") & IF(COUNTIF(Q21:X21, "*IHRM*"), "IHRM ", "") & IF(COUNTIF(Q21:X21, "*HRMPB*"), "HRMPB ", "") & IF(COUNTIF(Q21:X21, "*KISM*"), "KISM ", "") & IF(COUNTIF(Q21:X21, "*ICPAK*"), "ICPAK ", "") & IF(COUNTIF(Q21:X21, "*CPA*"), "CPA ", "") & IF(COUNTIF(Q21:X21, "*Strategic Leadership*"), "SLDP ", "") & IF(COUNTIF(Q21:X21, "*Senior Management*"), "SMC ", "") & IF(COUNTIF(Q21:X21, "*Nursing*"), "NCK ", "") & IF(COUNTIF(Q21:X21, "*KMLTTB*"), "KMLTTB ", "") & IF(COUNTIF(Q21:X21, "*Cstat*"), "Cstat ", "") & IF(SUMPRODUCT(LEN(Q21:X21)-LEN(SUBSTITUTE(UPPER(Q21:X21),"CERTIFICATE","")))/11>0, SUMPRODUCT(LEN(Q21:X21)-LEN(SUBSTITUTE(UPPER(Q21:X21),"CERTIFICATE","")))/11 & " Certificates ", "") ), " ", ", ") -> MSc, Bachelors, KCSE, KCPE, 1, Certificates | R21: Master of Science of Health of Acquatic Animal Resources | S21: Bachelor of veterinary medicine | V21: KCSE | W21: KCPE | X21: Certificate of Registration of a Veterinary Surgeon | Y21: Local Contract | Z21: Taita
A22: 19 | B22: 19 | C22: 20010746137 | D22: Mrs. Kavurani, Rose Owino | F22: 13634152 | G22: F | H22: 49 | I22: Animal Health Technologist [1] - EL - H03FL | J22: Animal Science &Welfare ethics | K22: L | L22: 0 - Active | M22: 20/12/2035 | N22: 36896 | O22: Mrs. Kavurani, Rose Owino | P22: =SUBSTITUTE(TRIM( IF(COUNTIF(Q22:X22, "*Philosophy*"), "PhD ", "") & IF(COUNTIF(Q22:X22, "*Master*"), "MSc ", "") & IF(COUNTIF(Q22:X22, "*Bachelor*"), "Bachelors ", "") & IF(COUNTIF(Q22:X22, "*Diploma*"), "Dip ", "") & IF(COUNTIF(Q22:X22, "*KCSE*"), "KCSE ", "") & IF(COUNTIF(Q22:X22, "*KCPE*"), "KCPE ", "") & IF(COUNTIF(Q22:X22, "*IHRM*"), "IHRM ", "") & IF(COUNTIF(Q22:X22, "*HRMPB*"), "HRMPB ", "") & IF(COUNTIF(Q22:X22, "*KISM*"), "KISM ", "") & IF(COUNTIF(Q22:X22, "*ICPAK*"), "ICPAK ", "") & IF(COUNTIF(Q22:X22, "*CPA*"), "CPA ", "") & IF(COUNTIF(Q22:X22, "*Strategic Leadership*"), "SLDP ", "") & IF(COUNTIF(Q22:X22, "*Senior Management*"), "SMC ", "") & IF(COUNTIF(Q22:X22, "*Nursing*"), "NCK ", "") & IF(COUNTIF(Q22:X22, "*KMLTTB*"), "KMLTTB ", "") & IF(COUNTIF(Q22:X22, "*Cstat*"), "Cstat ", "") & IF(SUMPRODUCT(LEN(Q22:X22)-LEN(SUBSTITUTE(UPPER(Q22:X22),"CERTIFICATE","")))/11>0, SUMPRODUCT(LEN(Q22:X22)-LEN(SUBSTITUTE(UPPER(Q22:X22),"CERTIFICATE","")))/11 & " Certificates ", "") ), " ", ", ") -> MSc, Bachelors, Dip, KCSE, KCPE, 1, Certificates | R22: Master of Science in Molecular Biology and Bionformatics | S22: Bachelor of Science in Medical Microbiology | T22: Higher Diploma in Biotechnology, Diploma in Applied Biology. | U22: Certificate in Science Laboratory Technician. | V22: KCSE | W22: KCPE | Y22: Permanent | Z22: Luhya
A23: 20 | B23: 20 | C23: 20220597833 | D23: Mrs. Woche, Fatuma Galgalo | F23: 34811881 | G23: F | H23: 28 | I23: Assistant Research Scientist - EL - R01BL | J23: Animal Science &Welfare ethics | K23: L | L23: 0 - Active | M23: 30/01/2028 | N23: 44564 | O23: Mrs. Woche, Fatuma Galgalo | P23: =SUBSTITUTE(TRIM( IF(COUNTIF(Q23:X23, "*Philosophy*"), "PhD ", "") & IF(COUNTIF(Q23:X23, "*Master*"), "MSc ", "") & IF(COUNTIF(Q23:X23, "*Bachelor*"), "Bachelors ", "") & IF(COUNTIF(Q23:X23, "*Diploma*"), "Dip ", "") & IF(COUNTIF(Q23:X23, "*KCSE*"), "KCSE ", "") & IF(COUNTIF(Q23:X23, "*KCPE*"), "KCPE ", "") & IF(COUNTIF(Q23:X23, "*IHRM*"), "IHRM ", "") & IF(COUNTIF(Q23:X23, "*HRMPB*"), "HRMPB ", "") & IF(COUNTIF(Q23:X23, "*KISM*"), "KISM ", "") & IF(COUNTIF(Q23:X23, "*ICPAK*"), "ICPAK ", "") & IF(COUNTIF(Q23:X23, "*CPA*"), "CPA ", "") & IF(COUNTIF(Q23:X23, "*Strategic Leadership*"), "SLDP ", "") & IF(COUNTIF(Q23:X23, "*Senior Management*"), "SMC ", "") & IF(COUNTIF(Q23:X23, "*Nursing*"), "NCK ", "") & IF(COUNTIF(Q23:X23, "*KMLTTB*"), "KMLTTB ", "") & IF(COUNTIF(Q23:X23, "*Cstat*"), "Cstat ", "") & IF(SUMPRODUCT(LEN(Q23:X23)-LEN(SUBSTITUTE(UPPER(Q23:X23),"CERTIFICATE","")))/11>0, SUMPRODUCT(LEN(Q23:X23)-LEN(SUBSTITUTE(UPPER(Q23:X23),"CERTIFICATE","")))/11 & " Certificates ", "") ), " ", ", ") -> Bachelors, KCSE, KCPE | S23: Bachelor of Science in Animal Science | V23: KCSE | W23: KCPE | Y23: Local Contract | Z23: Burji
A24: 21 | B24: 21 | C24: 20089224039 | D24: Ms. Kimiti, Priscila Wangari | F24: 22245948 | G24: F | H24: 46 | I24: Senior Animal Health Assistant - EL - H03EJ | J24: Animal Science &Welfare ethics | K24: J | L24: 0 - Active | M24: 06/07/2038 | N24: 39479 | O24: Ms. Kimiti, Priscila Wangari | P24: =SUBSTITUTE(TRIM( IF(COUNTIF(Q24:X24, "*Philosophy*"), "PhD ", "") & IF(COUNTIF(Q24:X24, "*Master*"), "MSc ", "") & IF(COUNTIF(Q24:X24, "*Bachelor*"), "Bachelors ", "") & IF(COUNTIF(Q24:X24, "*Diploma*"), "Dip ", "") & IF(COUNTIF(Q24:X24, "*KCSE*"), "KCSE ", "") & IF(COUNTIF(Q24:X24, "*KCPE*"), "KCPE ", "") & IF(COUNTIF(Q24:X24, "*IHRM*"), "IHRM ", "") & IF(COUNTIF(Q24:X24, "*HRMPB*"), "HRMPB ", "") & IF(COUNTIF(Q24:X24, "*KISM*"), "KISM ", "") & IF(COUNTIF(Q24:X24, "*ICPAK*"), "ICPAK ", "") & IF(COUNTIF(Q24:X24, "*CPA*"), "CPA ", "") & IF(COUNTIF(Q24:X24, "*Strategic Leadership*"), "SLDP ", "") & IF(COUNTIF(Q24:X24, "*Senior Management*"), "SMC ", "") & IF(COUNTIF(Q24:X24, "*Nursing*"), "NCK ", "") & IF(COUNTIF(Q24:X24, "*KMLTTB*"), "KMLTTB ", "") & IF(COUNTIF(Q24:X24, "*Cstat*"), "Cstat ", "") & IF(SUMPRODUCT(LEN(Q24:X24)-LEN(SUBSTITUTE(UPPER(Q24:X24),"CERTIFICATE","")))/11>0, SUMPRODUCT(LEN(Q24:X24)-LEN(SUBSTITUTE(UPPER(Q24:X24),"CERTIFICATE","")))/11 & " Certificates ", "") ), " ", ", ") -> KCSE, KCPE, 2, Certificates | U24: Certificate in Animal Health | V24: KCSE | W24: KCPE | X24: Certificate in Baboon Insertable Cardiac Monitor Project | Y24: Permanent | Z24: Kikuyu
A25: 22 | B25: 22 | C25: 20114215537 | D25: Mr. Adino, Thomas Agutu | F25: 10344158 | G25: M | H25: 55 | I25: Senior Animal Health Assistant - EL - H03EJ | J25: Animal Science &Welfare ethics | K25: J | L25: 0 - Active | M25: 22/07/2029 | N25: 40549 | O25: Mr. Adino, Thomas Agutu | P25: =SUBSTITUTE(TRIM( IF(COUNTIF(Q25:X25, "*Philosophy*"), "PhD ", "") & IF(COUNTIF(Q25:X25, "*Master*"), "MSc ", "") & IF(COUNTIF(Q25:X25, "*Bachelor*"), "Bachelors ", "") & IF(COUNTIF(Q25:X25, "*Diploma*"), "Dip ", "") & IF(COUNTIF(Q25:X25, "*KCSE*"), "KCSE ", "") & IF(COUNTIF(Q25:X25, "*KCPE*"), "KCPE ", "") & IF(COUNTIF(Q25:X25, "*IHRM*"), "IHRM ", "") & IF(COUNTIF(Q25:X25, "*HRMPB*"), "HRMPB ", "") & IF(COUNTIF(Q25:X25, "*KISM*"), "KISM ", "") & IF(COUNTIF(Q25:X25, "*ICPAK*"), "ICPAK ", "") & IF(COUNTIF(Q25:X25, "*CPA*"), "CPA ", "") & IF(COUNTIF(Q25:X25, "*Strategic Leadership*"), "SLDP ", "") & IF(COUNTIF(Q25:X25, "*Senior Management*"), "SMC ", "") & IF(COUNTIF(Q25:X25, "*Nursing*"), "NCK ", "") & IF(COUNTIF(Q25:X25, "*KMLTTB*"), "KMLTTB ", "") & IF(COUNTIF(Q25:X25, "*Cstat*"), "Cstat ", "") & IF(SUMPRODUCT(LEN(Q25:X25)-LEN(SUBSTITUTE(UPPER(Q25:X25),"CERTIFICATE","")))/11>0, SUMPRODUCT(LEN(Q25:X25)-LEN(SUBSTITUTE(UPPER(Q25:X25),"CERTIFICATE","")))/11 & " Certificates ", "") ), " ", ", ") -> Bachelors, Dip, KCSE, KCPE, 1, Certificates | S25: Bachelor of Science of Technology and Applied Biology | T25: Diploma in Technology (INDUSTRIAL AND APPLIED BIOLOGY) | U25: Certificate in Medical Laboratory Science lab | V25: KCSE | W25: KCPE | Y25: Permanent | Z25: Luo
A26: 23 | B26: 23 | C26: 20142576250 | D26: Ms. Jerono, Caroline | F26: 26426983 | G26: F | H26: 36 | I26: Laboratory Technologist [3] - EL - L07CJ | J26: Animal Science &Welfare ethics | K26: J | L26: 0 - Active | M26: 09/05/2048 | N26: 41640 | O26: Ms. Jerono, Caroline | P26: =SUBSTITUTE(TRIM( IF(COUNTIF(Q26:X26, "*Philosophy*"), "PhD ", "") & IF(COUNTIF(Q26:X26, "*Master*"), "MSc ", "") & IF(COUNTIF(Q26:X26, "*Bachelor*"), "Bachelors ", "") & IF(COUNTIF(Q26:X26, "*Diploma*"), "Dip ", "") & IF(COUNTIF(Q26:X26, "*KCSE*"), "KCSE ", "") & IF(COUNTIF(Q26:X26, "*KCPE*"), "KCPE ", "") & IF(COUNTIF(Q26:X26, "*IHRM*"), "IHRM ", "") & IF(COUNTIF(Q26:X26, "*HRMPB*"), "HRMPB ", "") & IF(COUNTIF(Q26:X26, "*KISM*"), "KISM ", "") & IF(COUNTIF(Q26:X26, "*ICPAK*"), "ICPAK ", "") & IF(COUNTIF(Q26:X26, "*CPA*"), "CPA ", "") & IF(COUNTIF(Q26:X26, "*Strategic Leadership*"), "SLDP ", "") & IF(COUNTIF(Q26:X26, "*Senior Management*"), "SMC ", "") & IF(COUNTIF(Q26:X26, "*Nursing*"), "NCK ", "") & IF(COUNTIF(Q26:X26, "*KMLTTB*"), "KMLTTB ", "") & IF(COUNTIF(Q26:X26, "*Cstat*"), "Cstat ", "") & IF(SUMPRODUCT(LEN(Q26:X26)-LEN(SUBSTITUTE(UPPER(Q26:X26),"CERTIFICATE","")))/11>0, SUMPRODUCT(LEN(Q26:X26)-LEN(SUBSTITUTE(UPPER(Q26:X26),"CERTIFICATE","")))/11 & " Certificates ", "") ), " ", ", ") -> Bachelors, Dip, KCSE, KCPE | S26: Bachelor of Science of Technology in Biotechnology | T26: Diploma in Applied Biology | V26: KCSE | W26: KCPE | Y26: Permanent | Z26: Kalenjin
A27: 24 | B27: 24 | C27: 20152655226 | D27: Mr. Omondi, Hillary Ochieng | F27: 25584197 | G27: M | H27: 37 | I27: Senior Animal Health Assistant - EL - H03EJ | J27: Animal Science &Welfare ethics | K27: J | L27: 0 - Active | M27: 30/06/2025 | N27: 13/08/2015 | O27: Mr. Omondi, Hillary Ochieng | P27: =SUBSTITUTE(TRIM( IF(COUNTIF(Q27:X27, "*Philosophy*"), "PhD ", "") & IF(COUNTIF(Q27:X27, "*Master*"), "MSc ", "") & IF(COUNTIF(Q27:X27, "*Bachelor*"), "Bachelors ", "") & IF(COUNTIF(Q27:X27, "*Diploma*"), "Dip ", "") & IF(COUNTIF(Q27:X27, "*KCSE*"), "KCSE ", "") & IF(COUNTIF(Q27:X27, "*KCPE*"), "KCPE ", "") & IF(COUNTIF(Q27:X27, "*IHRM*"), "IHRM ", "") & IF(COUNTIF(Q27:X27, "*HRMPB*"), "HRMPB ", "") & IF(COUNTIF(Q27:X27, "*KISM*"), "KISM ", "") & IF(COUNTIF(Q27:X27, "*ICPAK*"), "ICPAK ", "") & IF(COUNTIF(Q27:X27, "*CPA*"), "CPA ", "") & IF(COUNTIF(Q27:X27, "*Strategic Leadership*"), "SLDP ", "") & IF(COUNTIF(Q27:X27, "*Senior Management*"), "SMC ", "") & IF(COUNTIF(Q27:X27, "*Nursing*"), "NCK ", "") & IF(COUNTIF(Q27:X27, "*KMLTTB*"), "KMLTTB ", "") & IF(COUNTIF(Q27:X27, "*Cstat*"), "Cstat ", "") & IF(SUMPRODUCT(LEN(Q27:X27)-LEN(SUBSTITUTE(UPPER(Q27:X27),"CERTIFICATE","")))/11>0, SUMPRODUCT(LEN(Q27:X27)-LEN(SUBSTITUTE(UPPER(Q27:X27),"CERTIFICATE","")))/11 & " Certificates ", "") ), " ", ", ") -> Dip, KCSE, KCPE | T27: Diploma in Technology (Industrial and Applied Biology | V27: KCSE | W27: KCPE | Y27: Local Contract | Z27: Luo
A28: 25 | B28: 25 | C28: 20178600980 | D28: Ms. Kigen, Daisy Jebet | F28: 22538194 | G28: F | H28: 44 | I28: Senior Animal Health Assistant - EL - H03EJ | J28: Animal Science &Welfare ethics | K28: J | L28: 0 - Active | M28: 01/05/2027 | N28: 42830 | O28: Ms. Kigen, Daisy Jebet | P28: =SUBSTITUTE(TRIM( IF(COUNTIF(Q28:X28, "*Philosophy*"), "PhD ", "") & IF(COUNTIF(Q28:X28, "*Master*"), "MSc ", "") & IF(COUNTIF(Q28:X28, "*Bachelor*"), "Bachelors ", "") & IF(COUNTIF(Q28:X28, "*Diploma*"), "Dip ", "") & IF(COUNTIF(Q28:X28, "*KCSE*"), "KCSE ", "") & IF(COUNTIF(Q28:X28, "*KCPE*"), "KCPE ", "") & IF(COUNTIF(Q28:X28, "*IHRM*"), "IHRM ", "") & IF(COUNTIF(Q28:X28, "*HRMPB*"), "HRMPB ", "") & IF(COUNTIF(Q28:X28, "*KISM*"), "KISM ", "") & IF(COUNTIF(Q28:X28, "*ICPAK*"), "ICPAK ", "") & IF(COUNTIF(Q28:X28, "*CPA*"), "CPA ", "") & IF(COUNTIF(Q28:X28, "*Strategic Leadership*"), "SLDP ", "") & IF(COUNTIF(Q28:X28, "*Senior Management*"), "SMC ", "") & IF(COUNTIF(Q28:X28, "*Nursing*"), "NCK ", "") & IF(COUNTIF(Q28:X28, "*KMLTTB*"), "KMLTTB ", "") & IF(COUNTIF(Q28:X28, "*Cstat*"), "Cstat ", "") & IF(SUMPRODUCT(LEN(Q28:X28)-LEN(SUBSTITUTE(UPPER(Q28:X28),"CERTIFICATE","")))/11>0, SUMPRODUCT(LEN(Q28:X28)-LEN(SUBSTITUTE(UPPER(Q28:X28),"CERTIFICATE","")))/11 & " Certificates ", "") ), " ", ", ") -> Dip, KCSE, KCPE | T28: Diploma in Community Nutrition | V28: KCSE | W28: KCPE | Y28: Local Contract | Z28: Kalenjin
A29: 26 | B29: 26 | C29: 19920654349 | D29: Mr. Githinji, James Ndungu | F29: 11652898 | G29: M | H29: 55 | I29: Animal Health Assistant [1] - EL - H03EH | J29: Animal Science &Welfare ethics | K29: H | L29: 0 - Active | M29: 05/11/2029 | N29: 33640 | O29: Mr. Githinji, James Ndungu | P29: =SUBSTITUTE(TRIM( IF(COUNTIF(Q29:X29, "*Philosophy*"), "PhD ", "") & IF(COUNTIF(Q29:X29, "*Master*"), "MSc ", "") & IF(COUNTIF(Q29:X29, "*Bachelor*"), "Bachelors ", "") & IF(COUNTIF(Q29:X29, "*Diploma*"), "Dip ", "") & IF(COUNTIF(Q29:X29, "*KCSE*"), "KCSE ", "") & IF(COUNTIF(Q29:X29, "*KCPE*"), "KCPE ", "") & IF(COUNTIF(Q29:X29, "*IHRM*"), "IHRM ", "") & IF(COUNTIF(Q29:X29, "*HRMPB*"), "HRMPB ", "") & IF(COUNTIF(Q29:X29, "*KISM*"), "KISM ", "") & IF(COUNTIF(Q29:X29, "*ICPAK*"), "ICPAK ", "") & IF(COUNTIF(Q29:X29, "*CPA*"), "CPA ", "") & IF(COUNTIF(Q29:X29, "*Strategic Leadership*"), "SLDP ", "") & IF(COUNTIF(Q29:X29, "*Senior Management*"), "SMC ", "") & IF(COUNTIF(Q29:X29, "*Nursing*"), "NCK ", "") & IF(COUNTIF(Q29:X29, "*KMLTTB*"), "KMLTTB ", "") & IF(COUNTIF(Q29:X29, "*Cstat*"), "Cstat ", "") & IF(SUMPRODUCT(LEN(Q29:X29)-LEN(SUBSTITUTE(UPPER(Q29:X29),"CERTIFICATE","")))/11>0, SUMPRODUCT(LEN(Q29:X29)-LEN(SUBSTITUTE(UPPER(Q29:X29),"CERTIFICATE","")))/11 & " Certificates ", "") ), " ", ", ") -> KCSE, KCPE, 1, Certificates | V29: KCSE | W29: KCPE | X29: Certificate in Baboon Insertable Cardiac Monitor Project | Y29: Permanent | Z29: Kikuyu
A30: 27 | B30: 27 | C30: 19980490640 | D30: Ms. Nzuve, Mary Ngusye | F30: 13706972 | G30: F | H30: 49 | I30: Laboratory Assistant [2] - EL - L07BH | J30: Animal Science &Welfare ethics | K30: H | L30: 0 - Active | M30: 25/05/2035 | N30: 36016 | O30: Ms. Nzuve, Mary Ngusye | P30: =SUBSTITUTE(TRIM( IF(COUNTIF(Q30:X30, "*Philosophy*"), "PhD ", "") & IF(COUNTIF(Q30:X30, "*Master*"), "MSc ", "") & IF(COUNTIF(Q30:X30, "*Bachelor*"), "Bachelors ", "") & IF(COUNTIF(Q30:X30, "*Diploma*"), "Dip ", "") & IF(COUNTIF(Q30:X30, "*KCSE*"), "KCSE ", "") & IF(COUNTIF(Q30:X30, "*KCPE*"), "KCPE ", "") & IF(COUNTIF(Q30:X30, "*IHRM*"), "IHRM ", "") & IF(COUNTIF(Q30:X30, "*HRMPB*"), "HRMPB ", "") & IF(COUNTIF(Q30:X30, "*KISM*"), "KISM ", "") & IF(COUNTIF(Q30:X30, "*ICPAK*"), "ICPAK ", "") & IF(COUNTIF(Q30:X30, "*CPA*"), "CPA ", "") & IF(COUNTIF(Q30:X30, "*Strategic Leadership*"), "SLDP ", "") & IF(COUNTIF(Q30:X30, "*Senior Management*"), "SMC ", "") & IF(COUNTIF(Q30:X30, "*Nursing*"), "NCK ", "") & IF(COUNTIF(Q30:X30, "*KMLTTB*"), "KMLTTB ", "") & IF(COUNTIF(Q30:X30, "*Cstat*"), "Cstat ", "") & IF(SUMPRODUCT(LEN(Q30:X30)-LEN(SUBSTITUTE(UPPER(Q30:X30),"CERTIFICATE","")))/11>0, SUMPRODUCT(LEN(Q30:X30)-LEN(SUBSTITUTE(UPPER(Q30:X30),"CERTIFICATE","")))/11 & " Certificates ", "") ), " ", ", ") -> KCSE, KCPE, 1, Certificates | U30: Certificate in Medical Laboratory Science | V30: KCSE | W30: KCPE | Y30: Permanent | Z30: Kamba
A31: 28 | B31: 28 | C31: 20060933768 | D31: Mr. Alembi, Jason Emmanuel | F31: 13501715 | G31: M | H31: 50 | I31: Animal Health Assistant [1] - EL - H03EH | J31: Animal Science &Welfare ethics | K31: H | L31: 0 - Active | M31: 04/08/2034 | N31: 38907 | O31: Mr. Alembi, Jason Emmanuel | P31: =SUBSTITUTE(TRIM( IF(COUNTIF(Q31:X31, "*Philosophy*"), "PhD ", "") & IF(COUNTIF(Q31:X31, "*Master*"), "MSc ", "") & IF(COUNTIF(Q31:X31, "*Bachelor*"), "Bachelors ", "") & IF(COUNTIF(Q31:X31, "*Diploma*"), "Dip ", "") & IF(COUNTIF(Q31:X31, "*KCSE*"), "KCSE ", "") & IF(COUNTIF(Q31:X31, "*KCPE*"), "KCPE ", "") & IF(COUNTIF(Q31:X31, "*IHRM*"), "IHRM ", "") & IF(COUNTIF(Q31:X31, "*HRMPB*"), "HRMPB ", "") & IF(COUNTIF(Q31:X31, "*KISM*"), "KISM ", "") & IF(COUNTIF(Q31:X31, "*ICPAK*"), "ICPAK ", "") & IF(COUNTIF(Q31:X31, "*CPA*"), "CPA ", "") & IF(COUNTIF(Q31:X31, "*Strategic Leadership*"), "SLDP ", "") & IF(COUNTIF(Q31:X31, "*Senior Management*"), "SMC ", "") & IF(COUNTIF(Q31:X31, "*Nursing*"), "NCK ", "") & IF(COUNTIF(Q31:X31, "*KMLTTB*"), "KMLTTB ", "") & IF(COUNTIF(Q31:X31, "*Cstat*"), "Cstat ", "") & IF(SUMPRODUCT(LEN(Q31:X31)-LEN(SUBSTITUTE(UPPER(Q31:X31),"CERTIFICATE","")))/11>0, SUMPRODUCT(LEN(Q31:X31)-LEN(SUBSTITUTE(UPPER(Q31:X31),"CERTIFICATE","")))/11 & " Certificates ", "") ), " ", ", ") -> KCSE, KCPE, 1, Certificates | U31: Certificate in Store Keeping | V31: KCSE | W31: KCPE | Y31: Permanent | Z31: Luhya
A32: 29 | B32: 29 | C32: 20077018155 | D32: Mr. Ngacha, James Gichuru | F32: 14705584 | G32: M | H32: 48 | I32: Curatorial Assistant [2] - EL - M16BH | J32: Animal Science &Welfare ethics | K32: H | L32: 0 - Active | M32: 14/09/2036 | N32: 39084 | O32: Mr. Ngacha, James Gichuru | P32: =SUBSTITUTE(TRIM( IF(COUNTIF(Q32:X32, "*Philosophy*"), "PhD ", "") & IF(COUNTIF(Q32:X32, "*Master*"), "MSc ", "") & IF(COUNTIF(Q32:X32, "*Bachelor*"), "Bachelors ", "") & IF(COUNTIF(Q32:X32, "*Diploma*"), "Dip ", "") & IF(COUNTIF(Q32:X32, "*KCSE*"), "KCSE ", "") & IF(COUNTIF(Q32:X32, "*KCPE*"), "KCPE ", "") & IF(COUNTIF(Q32:X32, "*IHRM*"), "IHRM ", "") & IF(COUNTIF(Q32:X32, "*HRMPB*"), "HRMPB ", "") & IF(COUNTIF(Q32:X32, "*KISM*"), "KISM ", "") & IF(COUNTIF(Q32:X32, "*ICPAK*"), "ICPAK ", "") & IF(COUNTIF(Q32:X32, "*CPA*"), "CPA ", "") & IF(COUNTIF(Q32:X32, "*Strategic Leadership*"), "SLDP ", "") & IF(COUNTIF(Q32:X32, "*Senior Management*"), "SMC ", "") & IF(COUNTIF(Q32:X32, "*Nursing*"), "NCK ", "") & IF(COUNTIF(Q32:X32, "*KMLTTB*"), "KMLTTB ", "") & IF(COUNTIF(Q32:X32, "*Cstat*"), "Cstat ", "") & IF(SUMPRODUCT(LEN(Q32:X32)-LEN(SUBSTITUTE(UPPER(Q32:X32),"CERTIFICATE","")))/11>0, SUMPRODUCT(LEN(Q32:X32)-LEN(SUBSTITUTE(UPPER(Q32:X32),"CERTIFICATE","")))/11 & " Certificates ", "") ), " ", ", ") -> KCSE, KCPE | V32: KCSE | W32: KCPE | Y32: Permanent | Z32: Kikuyu
A33: 30 | B33: 30 | C33: 20077018309 | D33: Mr. Nayok, Collins Melubo | F33: 22657472 | G33: M | H33: 47 | I33: Office Assistant [2] - EL - T04DH | J33: Animal Science &Welfare ethics | K33: H | L33: 0 - Active | M33: 07/02/2038 | N33: 39083 | O33: Mr. Nayok, Collins Melubo | P33: =SUBSTITUTE(TRIM( IF(COUNTIF(Q33:X33, "*Philosophy*"), "PhD ", "") & IF(COUNTIF(Q33:X33, "*Master*"), "MSc ", "") & IF(COUNTIF(Q33:X33, "*Bachelor*"), "Bachelors ", "") & IF(COUNTIF(Q33:X33, "*Diploma*"), "Dip ", "") & IF(COUNTIF(Q33:X33, "*KCSE*"), "KCSE ", "") & IF(COUNTIF(Q33:X33, "*KCPE*"), "KCPE ", "") & IF(COUNTIF(Q33:X33, "*IHRM*"), "IHRM ", "") & IF(COUNTIF(Q33:X33, "*HRMPB*"), "HRMPB ", "") & IF(COUNTIF(Q33:X33, "*KISM*"), "KISM ", "") & IF(COUNTIF(Q33:X33, "*ICPAK*"), "ICPAK ", "") & IF(COUNTIF(Q33:X33, "*CPA*"), "CPA ", "") & IF(COUNTIF(Q33:X33, "*Strategic Leadership*"), "SLDP ", "") & IF(COUNTIF(Q33:X33, "*Senior Management*"), "SMC ", "") & IF(COUNTIF(Q33:X33, "*Nursing*"), "NCK ", "") & IF(COUNTIF(Q33:X33, "*KMLTTB*"), "KMLTTB ", "") & IF(COUNTIF(Q33:X33, "*Cstat*"), "Cstat ", "") & IF(SUMPRODUCT(LEN(Q33:X33)-LEN(SUBSTITUTE(UPPER(Q33:X33),"CERTIFICATE","")))/11>0, SUMPRODUCT(LEN(Q33:X33)-LEN(SUBSTITUTE(UPPER(Q33:X33),"CERTIFICATE","")))/11 & " Certificates ", "") ), " ", ", ") -> KCSE, KCPE, 1, Certificates | U33: Certificate in Library Studies | V33: KCSE | W33: KCPE | Y33: Permanent | Z33: Maasai
A34: 31 | B34: 31 | C34: 20089223821 | D34: Mr. Kiage, Walter Omaribah | F34: 22145871 | G34: M | H34: 44 | I34: Animal Health Assistant [1] - EL - H03EH | J34: Animal Science &Welfare ethics | K34: H | L34: 0 - Active | M34: 03/10/2040 | N34: 39454 | O34: Mr. Kiage, Walter Omaribah | P34: =SUBSTITUTE(TRIM( IF(COUNTIF(Q34:X34, "*Philosophy*"), "PhD ", "") & IF(COUNTIF(Q34:X34, "*Master*"), "MSc ", "") & IF(COUNTIF(Q34:X34, "*Bachelor*"), "Bachelors ", "") & IF(COUNTIF(Q34:X34, "*Diploma*"), "Dip ", "") & IF(COUNTIF(Q34:X34, "*KCSE*"), "KCSE ", "") & IF(COUNTIF(Q34:X34, "*KCPE*"), "KCPE ", "") & IF(COUNTIF(Q34:X34, "*IHRM*"), "IHRM ", "") & IF(COUNTIF(Q34:X34, "*HRMPB*"), "HRMPB ", "") & IF(COUNTIF(Q34:X34, "*KISM*"), "KISM ", "") & IF(COUNTIF(Q34:X34, "*ICPAK*"), "ICPAK ", "") & IF(COUNTIF(Q34:X34, "*CPA*"), "CPA ", "") & IF(COUNTIF(Q34:X34, "*Strategic Leadership*"), "SLDP ", "") & IF(COUNTIF(Q34:X34, "*Senior Management*"), "SMC ", "") & IF(COUNTIF(Q34:X34, "*Nursing*"), "NCK ", "") & IF(COUNTIF(Q34:X34, "*KMLTTB*"), "KMLTTB ", "") & IF(COUNTIF(Q34:X34, "*Cstat*"), "Cstat ", "") & IF(SUMPRODUCT(LEN(Q34:X34)-LEN(SUBSTITUTE(UPPER(Q34:X34),"CERTIFICATE","")))/11>0, SUMPRODUCT(LEN(Q34:X34)-LEN(SUBSTITUTE(UPPER(Q34:X34),"CERTIFICATE","")))/11 & " Certificates ", "") ), " ", ", ") -> KCSE, KCPE, 1, Certificates | U34: Certificate in Technical Education | V34: KCSE | W34: KCPE | Y34: Permanent | Z34: Kisii
A35: 32 | B35: 32 | C35: 20210646208 | D35: Mr. Gahoyo, Furaha Ali | F35: 14620321 | G35: M | H35: 49 | I35: Animal Health Assistant [1] - EL - H03EH | J35: Animal Science &Welfare ethics | K35: H | L35: 0 - Active | M35: 31/08/2027 | N35: 44197 | O35: Mr. Gahoyo, Furaha Ali | P35: =SUBSTITUTE(TRIM( IF(COUNTIF(Q35:X35, "*Philosophy*"), "PhD ", "") & IF(COUNTIF(Q35:X35, "*Master*"), "MSc ", "") & IF(COUNTIF(Q35:X35, "*Bachelor*"), "Bachelors ", "") & IF(COUNTIF(Q35:X35, "*Diploma*"), "Dip ", "") & IF(COUNTIF(Q35:X35, "*KCSE*"), "KCSE ", "") & IF(COUNTIF(Q35:X35, "*KCPE*"), "KCPE ", "") & IF(COUNTIF(Q35:X35, "*IHRM*"), "IHRM ", "") & IF(COUNTIF(Q35:X35, "*HRMPB*"), "HRMPB ", "") & IF(COUNTIF(Q35:X35, "*KISM*"), "KISM ", "") & IF(COUNTIF(Q35:X35, "*ICPAK*"), "ICPAK ", "") & IF(COUNTIF(Q35:X35, "*CPA*"), "CPA ", "") & IF(COUNTIF(Q35:X35, "*Strategic Leadership*"), "SLDP ", "") & IF(COUNTIF(Q35:X35, "*Senior Management*"), "SMC ", "") & IF(COUNTIF(Q35:X35, "*Nursing*"), "NCK ", "") & IF(COUNTIF(Q35:X35, "*KMLTTB*"), "KMLTTB ", "") & IF(COUNTIF(Q35:X35, "*Cstat*"), "Cstat ", "") & IF(SUMPRODUCT(LEN(Q35:X35)-LEN(SUBSTITUTE(UPPER(Q35:X35),"CERTIFICATE","")))/11>0, SUMPRODUCT(LEN(Q35:X35)-LEN(SUBSTITUTE(UPPER(Q35:X35),"CERTIFICATE","")))/11 & " Certificates ", "") ), " ", ", ") -> Dip, KCSE, KCPE | T35: Ordinary Diploma in Clearing,Forwarding and Shipping Procedure. | V35: KCSE | W35: KCPE | Y35: Local Contract | Z35: Mijikenda
A36: 33 | B36: 33 | C36: 20000078914 | D36: Mr. Karongo, Stephen Kinyanjui | F36: 10141052 | G36: M | H36: 56 | I36: Animal Health Assistant [2] - EL - H03EG | J36: Animal Science &Welfare ethics | K36: G | L36: 0 - Active | M36: 16/04/2029 | N36: 36532 | O36: Mr. Karongo, Stephen Kinyanjui | P36: =SUBSTITUTE(TRIM( IF(COUNTIF(Q36:X36, "*Philosophy*"), "PhD ", "") & IF(COUNTIF(Q36:X36, "*Master*"), "MSc ", "") & IF(COUNTIF(Q36:X36, "*Bachelor*"), "Bachelors ", "") & IF(COUNTIF(Q36:X36, "*Diploma*"), "Dip ", "") & IF(COUNTIF(Q36:X36, "*KCSE*"), "KCSE ", "") & IF(COUNTIF(Q36:X36, "*KCPE*"), "KCPE ", "") & IF(COUNTIF(Q36:X36, "*IHRM*"), "IHRM ", "") & IF(COUNTIF(Q36:X36, "*HRMPB*"), "HRMPB ", "") & IF(COUNTIF(Q36:X36, "*KISM*"), "KISM ", "") & IF(COUNTIF(Q36:X36, "*ICPAK*"), "ICPAK ", "") & IF(COUNTIF(Q36:X36, "*CPA*"), "CPA ", "") & IF(COUNTIF(Q36:X36, "*Strategic Leadership*"), "SLDP ", "") & IF(COUNTIF(Q36:X36, "*Senior Management*"), "SMC ", "") & IF(COUNTIF(Q36:X36, "*Nursing*"), "NCK ", "") & IF(COUNTIF(Q36:X36, "*KMLTTB*"), "KMLTTB ", "") & IF(COUNTIF(Q36:X36, "*Cstat*"), "Cstat ", "") & IF(SUMPRODUCT(LEN(Q36:X36)-LEN(SUBSTITUTE(UPPER(Q36:X36),"CERTIFICATE","")))/11>0, SUMPRODUCT(LEN(Q36:X36)-LEN(SUBSTITUTE(UPPER(Q36:X36),"CERTIFICATE","")))/11 & " Certificates ", "") ), " ", ", ") -> KCPE | W36: KCPE | Y36: Permanent | Z36: Kikuyu
A37: 34 | B37: 34 | C37: 20178600786 | D37: Mr. Loitareng, Sammy Poghon | F37: 35374930 | G37: M | H37: 32 | I37: Senior Auxiliary staff - EL - T04CG | J37: Animal Science &Welfare ethics | K37: G | L37: 0 - Active | M37: 30/11/2027 | N37: 42898 | O37: Mr. Loitareng, Sammy Poghon | P37: =SUBSTITUTE(TRIM( IF(COUNTIF(Q37:X37, "*Philosophy*"), "PhD ", "") & IF(COUNTIF(Q37:X37, "*Master*"), "MSc ", "") & IF(COUNTIF(Q37:X37, "*Bachelor*"), "Bachelors ", "") & IF(COUNTIF(Q37:X37, "*Diploma*"), "Dip ", "") & IF(COUNTIF(Q37:X37, "*KCSE*"), "KCSE ", "") & IF(COUNTIF(Q37:X37, "*KCPE*"), "KCPE ", "") & IF(COUNTIF(Q37:X37, "*IHRM*"), "IHRM ", "") & IF(COUNTIF(Q37:X37, "*HRMPB*"), "HRMPB ", "") & IF(COUNTIF(Q37:X37, "*KISM*"), "KISM ", "") & IF(COUNTIF(Q37:X37, "*ICPAK*"), "ICPAK ", "") & IF(COUNTIF(Q37:X37, "*CPA*"), "CPA ", "") & IF(COUNTIF(Q37:X37, "*Strategic Leadership*"), "SLDP ", "") & IF(COUNTIF(Q37:X37, "*Senior Management*"), "SMC ", "") & IF(COUNTIF(Q37:X37, "*Nursing*"), "NCK ", "") & IF(COUNTIF(Q37:X37, "*KMLTTB*"), "KMLTTB ", "") & IF(COUNTIF(Q37:X37, "*Cstat*"), "Cstat ", "") & IF(SUMPRODUCT(LEN(Q37:X37)-LEN(SUBSTITUTE(UPPER(Q37:X37),"CERTIFICATE","")))/11>0, SUMPRODUCT(LEN(Q37:X37)-LEN(SUBSTITUTE(UPPER(Q37:X37),"CERTIFICATE","")))/11 & " Certificates ", "") ), " ", ", ") -> KCSE, KCPE | V37: KCSE | W37: KCPE | Y37: Local Contract | Z37: Maasai
A38: 35 | B38: 35 | C38: 20250007973 | D38: Dr. Mwongela, Benjamin Muuo | F38: 33556049 | G38: M | H38: 29 | I38: Fellowship - EL - M16XG | J38: Animal Science &Welfare ethics | K38: G | L38: 0 - Active | M38: 31/01/2026 | N38: 45659 | O38: Dr. Mwongela, Benjamin Muuo | P38: =SUBSTITUTE(TRIM( IF(COUNTIF(Q38:X38, "*Philosophy*"), "PhD ", "") & IF(COUNTIF(Q38:X38, "*Master*"), "MSc ", "") & IF(COUNTIF(Q38:X38, "*Bachelor*"), "Bachelors ", "") & IF(COUNTIF(Q38:X38, "*Diploma*"), "Dip ", "") & IF(COUNTIF(Q38:X38, "*KCSE*"), "KCSE ", "") & IF(COUNTIF(Q38:X38, "*KCPE*"), "KCPE ", "") & IF(COUNTIF(Q38:X38, "*IHRM*"), "IHRM ", "") & IF(COUNTIF(Q38:X38, "*HRMPB*"), "HRMPB ", "") & IF(COUNTIF(Q38:X38, "*KISM*"), "KISM ", "") & IF(COUNTIF(Q38:X38, "*ICPAK*"), "ICPAK ", "") & IF(COUNTIF(Q38:X38, "*CPA*"), "CPA ", "") & IF(COUNTIF(Q38:X38, "*Strategic Leadership*"), "SLDP ", "") & IF(COUNTIF(Q38:X38, "*Senior Management*"), "SMC ", "") & IF(COUNTIF(Q38:X38, "*Nursing*"), "NCK ", "") & IF(COUNTIF(Q38:X38, "*KMLTTB*"), "KMLTTB ", "") & IF(COUNTIF(Q38:X38, "*Cstat*"), "Cstat ", "") & IF(SUMPRODUCT(LEN(Q38:X38)-LEN(SUBSTITUTE(UPPER(Q38:X38),"CERTIFICATE","")))/11>0, SUMPRODUCT(LEN(Q38:X38)-LEN(SUBSTITUTE(UPPER(Q38:X38),"CERTIFICATE","")))/11 & " Certificates ", "") ), " ", ", ") -> Bachelors, KCSE, KCPE, 1, Certificates | S38: Bachelor of Veterinary Medicine | V38: KCSE | W38: KCPE | X38: Certificate of Registration of a Veterinary Surgeon | Y38: Part Time Contract | Z38: Kamba
A39: 36 | B39: 36 | C39: 20250011100 | D39: Mr. Momanyi, Sam Ocharo | F39: 32277442 | G39: M | H39: 31 | I39: Fellowship - EL - M16XG | J39: Animal Science &Welfare ethics | K39: G | L39: 0 - Active | M39: 28/02/2026 | N39: 45660 | O39: Mr. Momanyi, Sam Ocharo | P39: =SUBSTITUTE(TRIM( IF(COUNTIF(Q39:X39, "*Philosophy*"), "PhD ", "") & IF(COUNTIF(Q39:X39, "*Master*"), "MSc ", "") & IF(COUNTIF(Q39:X39, "*Bachelor*"), "Bachelors ", "") & IF(COUNTIF(Q39:X39, "*Diploma*"), "Dip ", "") & IF(COUNTIF(Q39:X39, "*KCSE*"), "KCSE ", "") & IF(COUNTIF(Q39:X39, "*KCPE*"), "KCPE ", "") & IF(COUNTIF(Q39:X39, "*IHRM*"), "IHRM ", "") & IF(COUNTIF(Q39:X39, "*HRMPB*"), "HRMPB ", "") & IF(COUNTIF(Q39:X39, "*KISM*"), "KISM ", "") & IF(COUNTIF(Q39:X39, "*ICPAK*"), "ICPAK ", "") & IF(COUNTIF(Q39:X39, "*CPA*"), "CPA ", "") & IF(COUNTIF(Q39:X39, "*Strategic Leadership*"), "SLDP ", "") & IF(COUNTIF(Q39:X39, "*Senior Management*"), "SMC ", "") & IF(COUNTIF(Q39:X39, "*Nursing*"), "NCK ", "") & IF(COUNTIF(Q39:X39, "*KMLTTB*"), "KMLTTB ", "") & IF(COUNTIF(Q39:X39, "*Cstat*"), "Cstat ", "") & IF(SUMPRODUCT(LEN(Q39:X39)-LEN(SUBSTITUTE(UPPER(Q39:X39),"CERTIFICATE","")))/11>0, SUMPRODUCT(LEN(Q39:X39)-LEN(SUBSTITUTE(UPPER(Q39:X39),"CERTIFICATE","")))/11 & " Certificates ", "") ), " ", ", ") -> Bachelors, KCSE, KCPE | S39: Bachelor of Science in Medical Microbiology | V39: KCSE | W39: KCPE | Y39: Part Time Contract | Z39: Kisii
A40: 37 | B40: 37 | C40: 20250067282 | D40: Hannah Ndiko Waweru | F40: 12925801 | G40: F | I40: Animal Health Assistant 11 | J40: Animal Science &Welfare ethics | K40: G | L40: 0 - Active | M40: 46757 | N40: 45693 | O40: Hannah Ndiko Waweru | P40: =SUBSTITUTE(TRIM( IF(COUNTIF(Q40:X40, "*Philosophy*"), "PhD ", "") & IF(COUNTIF(Q40:X40, "*Master*"), "MSc ", "") & IF(COUNTIF(Q40:X40, "*Bachelor*"), "Bachelors ", "") & IF(COUNTIF(Q40:X40, "*Diploma*"), "Dip ", "") & IF(COUNTIF(Q40:X40, "*KCSE*"), "KCSE ", "") & IF(COUNTIF(Q40:X40, "*KCPE*"), "KCPE ", "") & IF(COUNTIF(Q40:X40, "*IHRM*"), "IHRM ", "") & IF(COUNTIF(Q40:X40, "*HRMPB*"), "HRMPB ", "") & IF(COUNTIF(Q40:X40, "*KISM*"), "KISM ", "") & IF(COUNTIF(Q40:X40, "*ICPAK*"), "ICPAK ", "") & IF(COUNTIF(Q40:X40, "*CPA*"), "CPA ", "") & IF(COUNTIF(Q40:X40, "*Strategic Leadership*"), "SLDP ", "") & IF(COUNTIF(Q40:X40, "*Senior Management*"), "SMC ", "") & IF(COUNTIF(Q40:X40, "*Nursing*"), "NCK ", "") & IF(COUNTIF(Q40:X40, "*KMLTTB*"), "KMLTTB ", "") & IF(COUNTIF(Q40:X40, "*Cstat*"), "Cstat ", "") & IF(SUMPRODUCT(LEN(Q40:X40)-LEN(SUBSTITUTE(UPPER(Q40:X40),"CERTIFICATE","")))/11>0, SUMPRODUCT(LEN(Q40:X40)-LEN(SUBSTITUTE(UPPER(Q40:X40),"CERTIFICATE","")))/11 & " Certificates ", "") ), " ", ", ") -> KCSE, KCPE | V40: KCSE | W40: KCPE | Y40: Local Contract | Z40: Kikuyu
A41: 38 | B41: 38 | C41: 20250089145 | D41: Collins Kivuva Kioko | F41: 37906155 | G41: M | I41: Animal Health Assistant 11 | J41: Animal Science &Welfare ethics | K41: G | L41: 0 - Active | M41: 46757 | N41: 45693 | O41: Collins Kivuva Kioko | P41: =SUBSTITUTE(TRIM( IF(COUNTIF(Q41:X41, "*Philosophy*"), "PhD ", "") & IF(COUNTIF(Q41:X41, "*Master*"), "MSc ", "") & IF(COUNTIF(Q41:X41, "*Bachelor*"), "Bachelors ", "") & IF(COUNTIF(Q41:X41, "*Diploma*"), "Dip ", "") & IF(COUNTIF(Q41:X41, "*KCSE*"), "KCSE ", "") & IF(COUNTIF(Q41:X41, "*KCPE*"), "KCPE ", "") & IF(COUNTIF(Q41:X41, "*IHRM*"), "IHRM ", "") & IF(COUNTIF(Q41:X41, "*HRMPB*"), "HRMPB ", "") & IF(COUNTIF(Q41:X41, "*KISM*"), "KISM ", "") & IF(COUNTIF(Q41:X41, "*ICPAK*"), "ICPAK ", "") & IF(COUNTIF(Q41:X41, "*CPA*"), "CPA ", "") & IF(COUNTIF(Q41:X41, "*Strategic Leadership*"), "SLDP ", "") & IF(COUNTIF(Q41:X41, "*Senior Management*"), "SMC ", "") & IF(COUNTIF(Q41:X41, "*Nursing*"), "NCK ", "") & IF(COUNTIF(Q41:X41, "*KMLTTB*"), "KMLTTB ", "") & IF(COUNTIF(Q41:X41, "*Cstat*"), "Cstat ", "") & IF(SUMPRODUCT(LEN(Q41:X41)-LEN(SUBSTITUTE(UPPER(Q41:X41),"CERTIFICATE","")))/11>0, SUMPRODUCT(LEN(Q41:X41)-LEN(SUBSTITUTE(UPPER(Q41:X41),"CERTIFICATE","")))/11 & " Certificates ", "") ), " ", ", ") -> KCSE, KCPE | V41: KCSE | W41: KCPE | Y41: Local Contract | Z41: Kamba
A42: 39 | B42: 39 | C42: 20250067266 | D42: Daniel Obondi Morara | F42: 40223884 | G42: M | I42: Animal Health Assistant 11 | J42: Animal Science &Welfare ethics | K42: G | L42: 0 - Active | M42: 46757 | N42: 45693 | O42: Daniel Obondi Morara | P42: =SUBSTITUTE(TRIM( IF(COUNTIF(Q42:X42, "*Philosophy*"), "PhD ", "") & IF(COUNTIF(Q42:X42, "*Master*"), "MSc ", "") & IF(COUNTIF(Q42:X42, "*Bachelor*"), "Bachelors ", "") & IF(COUNTIF(Q42:X42, "*Diploma*"), "Dip ", "") & IF(COUNTIF(Q42:X42, "*KCSE*"), "KCSE ", "") & IF(COUNTIF(Q42:X42, "*KCPE*"), "KCPE ", "") & IF(COUNTIF(Q42:X42, "*IHRM*"), "IHRM ", "") & IF(COUNTIF(Q42:X42, "*HRMPB*"), "HRMPB ", "") & IF(COUNTIF(Q42:X42, "*KISM*"), "KISM ", "") & IF(COUNTIF(Q42:X42, "*ICPAK*"), "ICPAK ", "") & IF(COUNTIF(Q42:X42, "*CPA*"), "CPA ", "") & IF(COUNTIF(Q42:X42, "*Strategic Leadership*"), "SLDP ", "") & IF(COUNTIF(Q42:X42, "*Senior Management*"), "SMC ", "") & IF(COUNTIF(Q42:X42, "*Nursing*"), "NCK ", "") & IF(COUNTIF(Q42:X42, "*KMLTTB*"), "KMLTTB ", "") & IF(COUNTIF(Q42:X42, "*Cstat*"), "Cstat ", "") & IF(SUMPRODUCT(LEN(Q42:X42)-LEN(SUBSTITUTE(UPPER(Q42:X42),"CERTIFICATE","")))/11>0, SUMPRODUCT(LEN(Q42:X42)-LEN(SUBSTITUTE(UPPER(Q42:X42),"CERTIFICATE","")))/11 & " Certificates ", "") ), " ", ", ") -> KCSE, KCPE | V42: KCSE | W42: KCPE | Y42: Local Contract | Z42: Kisii
A43: 40 | B43: 40 | C43: 20060933849 | D43: Mr. Gichuhi, Jaffer Ibrahim | F43: 21717357 | G43: M | H43: 46 | I43: Auxiliary staff [1] - EL - T04CF | J43: Animal Science &Welfare ethics | K43: F | L43: 0 - Active | M43: 06/07/2038 | N43: 38725 | O43: Mr. Gichuhi, Jaffer Ibrahim | P43: =SUBSTITUTE(TRIM( IF(COUNTIF(Q43:X43, "*Philosophy*"), "PhD ", "") & IF(COUNTIF(Q43:X43, "*Master*"), "MSc ", "") & IF(COUNTIF(Q43:X43, "*Bachelor*"), "Bachelors ", "") & IF(COUNTIF(Q43:X43, "*Diploma*"), "Dip ", "") & IF(COUNTIF(Q43:X43, "*KCSE*"), "KCSE ", "") & IF(COUNTIF(Q43:X43, "*KCPE*"), "KCPE ", "") & IF(COUNTIF(Q43:X43, "*IHRM*"), "IHRM ", "") & IF(COUNTIF(Q43:X43, "*HRMPB*"), "HRMPB ", "") & IF(COUNTIF(Q43:X43, "*KISM*"), "KISM ", "") & IF(COUNTIF(Q43:X43, "*ICPAK*"), "ICPAK ", "") & IF(COUNTIF(Q43:X43, "*CPA*"), "CPA ", "") & IF(COUNTIF(Q43:X43, "*Strategic Leadership*"), "SLDP ", "") & IF(COUNTIF(Q43:X43, "*Senior Management*"), "SMC ", "") & IF(COUNTIF(Q43:X43, "*Nursing*"), "NCK ", "") & IF(COUNTIF(Q43:X43, "*KMLTTB*"), "KMLTTB ", "") & IF(COUNTIF(Q43:X43, "*Cstat*"), "Cstat ", "") & IF(SUMPRODUCT(LEN(Q43:X43)-LEN(SUBSTITUTE(UPPER(Q43:X43),"CERTIFICATE","")))/11>0, SUMPRODUCT(LEN(Q43:X43)-LEN(SUBSTITUTE(UPPER(Q43:X43),"CERTIFICATE","")))/11 & " Certificates ", "") ), " ", ", ") | Y43: Permanent | Z43: Kikuyu
A44: 41 | B44: 41 | C44: 20121211057 | D44: Mr. Kengo, Isaac Nduka | F44: 10164110 | G44: M | H44: 56 | I44: Animal Health Assistant [3] - EL - H03EF | J44: Animal Science &Welfare ethics | K44: F | L44: 0 - Active | M44: 16/07/2028 | N44: 40915 | O44: Mr. Kengo, Isaac Nduka | P44: =SUBSTITUTE(TRIM( IF(COUNTIF(Q44:X44, "*Philosophy*"), "PhD ", "") & IF(COUNTIF(Q44:X44, "*Master*"), "MSc ", "") & IF(COUNTIF(Q44:X44, "*Bachelor*"), "Bachelors ", "") & IF(COUNTIF(Q44:X44, "*Diploma*"), "Dip ", "") & IF(COUNTIF(Q44:X44, "*KCSE*"), "KCSE ", "") & IF(COUNTIF(Q44:X44, "*KCPE*"), "KCPE ", "") & IF(COUNTIF(Q44:X44, "*IHRM*"), "IHRM ", "") & IF(COUNTIF(Q44:X44, "*HRMPB*"), "HRMPB ", "") & IF(COUNTIF(Q44:X44, "*KISM*"), "KISM ", "") & IF(COUNTIF(Q44:X44, "*ICPAK*"), "ICPAK ", "") & IF(COUNTIF(Q44:X44, "*CPA*"), "CPA ", "") & IF(COUNTIF(Q44:X44, "*Strategic Leadership*"), "SLDP ", "") & IF(COUNTIF(Q44:X44, "*Senior Management*"), "SMC ", "") & IF(COUNTIF(Q44:X44, "*Nursing*"), "NCK ", "") & IF(COUNTIF(Q44:X44, "*KMLTTB*"), "KMLTTB ", "") & IF(COUNTIF(Q44:X44, "*Cstat*"), "Cstat ", "") & IF(SUMPRODUCT(LEN(Q44:X44)-LEN(SUBSTITUTE(UPPER(Q44:X44),"CERTIFICATE","")))/11>0, SUMPRODUCT(LEN(Q44:X44)-LEN(SUBSTITUTE(UPPER(Q44:X44),"CERTIFICATE","")))/11 & " Certificates ", "") ), " ", ", ") | Y44: Permanent | Z44: Luhya
A45: 42 | B45: 42 | C45: 20142576234 | D45: Ms. Korir, Gladys Chepkemoi | F45: 26041520 | G45: F | H45: 36 | I45: Animal Health Assistant [3] - EL - H03EF | J45: Animal Science &Welfare ethics | K45: F | L45: 0 - Active | M45: 25/12/2048 | N45: 41640 | O45: Ms. Korir, Gladys Chepkemoi | P45: =SUBSTITUTE(TRIM( IF(COUNTIF(Q45:X45, "*Philosophy*"), "PhD ", "") & IF(COUNTIF(Q45:X45, "*Master*"), "MSc ", "") & IF(COUNTIF(Q45:X45, "*Bachelor*"), "Bachelors ", "") & IF(COUNTIF(Q45:X45, "*Diploma*"), "Dip ", "") & IF(COUNTIF(Q45:X45, "*KCSE*"), "KCSE ", "") & IF(COUNTIF(Q45:X45, "*KCPE*"), "KCPE ", "") & IF(COUNTIF(Q45:X45, "*IHRM*"), "IHRM ", "") & IF(COUNTIF(Q45:X45, "*HRMPB*"), "HRMPB ", "") & IF(COUNTIF(Q45:X45, "*KISM*"), "KISM ", "") & IF(COUNTIF(Q45:X45, "*ICPAK*"), "ICPAK ", "") & IF(COUNTIF(Q45:X45, "*CPA*"), "CPA ", "") & IF(COUNTIF(Q45:X45, "*Strategic Leadership*"), "SLDP ", "") & IF(COUNTIF(Q45:X45, "*Senior Management*"), "SMC ", "") & IF(COUNTIF(Q45:X45, "*Nursing*"), "NCK ", "") & IF(COUNTIF(Q45:X45, "*KMLTTB*"), "KMLTTB ", "") & IF(COUNTIF(Q45:X45, "*Cstat*"), "Cstat ", "") & IF(SUMPRODUCT(LEN(Q45:X45)-LEN(SUBSTITUTE(UPPER(Q45:X45),"CERTIFICATE","")))/11>0, SUMPRODUCT(LEN(Q45:X45)-LEN(SUBSTITUTE(UPPER(Q45:X45),"CERTIFICATE","")))/11 & " Certificates ", "") ), " ", ", ") -> 2, Certificates | U45: Computer Packages Certificate,Craft in Science Laboratory Technology Certificate | Y45: Permanent | Z45: Kalenjin
A46: 43 | B46: 43 | C46: 20250067274 | D46: Hillary Kadende Masiva | F46: 39582151 | G46: M | I46: Animal Health Assistant 11 | J46: Reproductive Health & Biology | K46: G | L46: 0 - Active | M46: 46757 | N46: 45693 | O46: Hillary Kadende Masiva | P46: =SUBSTITUTE(TRIM( IF(COUNTIF(Q46:X46, "*Philosophy*"), "PhD ", "") & IF(COUNTIF(Q46:X46, "*Master*"), "MSc ", "") & IF(COUNTIF(Q46:X46, "*Bachelor*"), "Bachelors ", "") & IF(COUNTIF(Q46:X46, "*Diploma*"), "Dip ", "") & IF(COUNTIF(Q46:X46, "*KCSE*"), "KCSE ", "") & IF(COUNTIF(Q46:X46, "*KCPE*"), "KCPE ", "") & IF(COUNTIF(Q46:X46, "*IHRM*"), "IHRM ", "") & IF(COUNTIF(Q46:X46, "*HRMPB*"), "HRMPB ", "") & IF(COUNTIF(Q46:X46, "*KISM*"), "KISM ", "") & IF(COUNTIF(Q46:X46, "*ICPAK*"), "ICPAK ", "") & IF(COUNTIF(Q46:X46, "*CPA*"), "CPA ", "") & IF(COUNTIF(Q46:X46, "*Strategic Leadership*"), "SLDP ", "") & IF(COUNTIF(Q46:X46, "*Senior Management*"), "SMC ", "") & IF(COUNTIF(Q46:X46, "*Nursing*"), "NCK ", "") & IF(COUNTIF(Q46:X46, "*KMLTTB*"), "KMLTTB ", "") & IF(COUNTIF(Q46:X46, "*Cstat*"), "Cstat ", "") & IF(SUMPRODUCT(LEN(Q46:X46)-LEN(SUBSTITUTE(UPPER(Q46:X46),"CERTIFICATE","")))/11>0, SUMPRODUCT(LEN(Q46:X46)-LEN(SUBSTITUTE(UPPER(Q46:X46),"CERTIFICATE","")))/11 & " Certificates ", "") ), " ", ", ") -> KCSE, KCPE | V46: KCSE | W46: KCPE | Y46: Local Contract | Z46: Luhya
A47: 44 | B47: 44 | C47: 20250089137 | D47: Kennedy Mwangi Kamande | F47: 29388325 | G47: M | I47: Animal Health Assistant 11 | J47: Reproductive Health & Biology | K47: G | L47: 0 - Active | M47: 46757 | N47: 45693 | O47: Kennedy Mwangi Kamande | P47: =SUBSTITUTE(TRIM( IF(COUNTIF(Q47:X47, "*Philosophy*"), "PhD ", "") & IF(COUNTIF(Q47:X47, "*Master*"), "MSc ", "") & IF(COUNTIF(Q47:X47, "*Bachelor*"), "Bachelors ", "") & IF(COUNTIF(Q47:X47, "*Diploma*"), "Dip ", "") & IF(COUNTIF(Q47:X47, "*KCSE*"), "KCSE ", "") & IF(COUNTIF(Q47:X47, "*KCPE*"), "KCPE ", "") & IF(COUNTIF(Q47:X47, "*IHRM*"), "IHRM ", "") & IF(COUNTIF(Q47:X47, "*HRMPB*"), "HRMPB ", "") & IF(COUNTIF(Q47:X47, "*KISM*"), "KISM ", "") & IF(COUNTIF(Q47:X47, "*ICPAK*"), "ICPAK ", "") & IF(COUNTIF(Q47:X47, "*CPA*"), "CPA ", "") & IF(COUNTIF(Q47:X47, "*Strategic Leadership*"), "SLDP ", "") & IF(COUNTIF(Q47:X47, "*Senior Management*"), "SMC ", "") & IF(COUNTIF(Q47:X47, "*Nursing*"), "NCK ", "") & IF(COUNTIF(Q47:X47, "*KMLTTB*"), "KMLTTB ", "") & IF(COUNTIF(Q47:X47, "*Cstat*"), "Cstat ", "") & IF(SUMPRODUCT(LEN(Q47:X47)-LEN(SUBSTITUTE(UPPER(Q47:X47),"CERTIFICATE","")))/11>0, SUMPRODUCT(LEN(Q47:X47)-LEN(SUBSTITUTE(UPPER(Q47:X47),"CERTIFICATE","")))/11 & " Certificates ", "") ), " ", ", ") -> KCSE, KCPE | V47: KCSE | W47: KCPE | Y47: Local Contract | Z47: Kikuyu
F48: CONSERVATION & ECOLOGY | P48: =SUBSTITUTE(TRIM( IF(COUNTIF(Q48:X48, "*Philosophy*"), "PhD ", "") & IF(COUNTIF(Q48:X48, "*Master*"), "MSc ", "") & IF(COUNTIF(Q48:X48, "*Bachelor*"), "Bachelors ", "") & IF(COUNTIF(Q48:X48, "*Diploma*"), "Dip ", "") & IF(COUNTIF(Q48:X48, "*KCSE*"), "KCSE ", "") & IF(COUNTIF(Q48:X48, "*KCPE*"), "KCPE ", "") & IF(COUNTIF(Q48:X48, "*IHRM*"), "IHRM ", "") & IF(COUNTIF(Q48:X48, "*HRMPB*"), "HRMPB ", "") & IF(COUNTIF(Q48:X48, "*KISM*"), "KISM ", "") & IF(COUNTIF(Q48:X48, "*ICPAK*"), "ICPAK ", "") & IF(COUNTIF(Q48:X48, "*CPA*"), "CPA ", "") & IF(COUNTIF(Q48:X48, "*Strategic Leadership*"), "SLDP ", "") & IF(COUNTIF(Q48:X48, "*Senior Management*"), "SMC ", "") & IF(COUNTIF(Q48:X48, "*Nursing*"), "NCK ", "") & IF(COUNTIF(Q48:X48, "*KMLTTB*"), "KMLTTB ", "") & IF(COUNTIF(Q48:X48, "*Cstat*"), "Cstat ", "") & IF(SUMPRODUCT(LEN(Q48:X48)-LEN(SUBSTITUTE(UPPER(Q48:X48),"CERTIFICATE","")))/11>0, SUMPRODUCT(LEN(Q48:X48)-LEN(SUBSTITUTE(UPPER(Q48:X48),"CERTIFICATE","")))/11 & " Certificates ", "") ), " ", ", ")
A49: 45 | B49: 45 | C49: 20020838693 | D49: Dr. Mwangi, Danson Kareri | F49: 21301415 | G49: M | H49: 48 | I49: Senior Research Scientist [2] - ET - R01AP | J49: Conservation & Ecology | K49: P | L49: 0 - Active | M49: 28/03/2047 | N49: 37469 | O49: Dr. Mwangi, Danson Kareri | P49: =SUBSTITUTE(TRIM( IF(COUNTIF(Q49:X49, "*Philosophy*"), "PhD ", "") & IF(COUNTIF(Q49:X49, "*Master*"), "MSc ", "") & IF(COUNTIF(Q49:X49, "*Bachelor*"), "Bachelors ", "") & IF(COUNTIF(Q49:X49, "*Diploma*"), "Dip ", "") & IF(COUNTIF(Q49:X49, "*KCSE*"), "KCSE ", "") & IF(COUNTIF(Q49:X49, "*KCPE*"), "KCPE ", "") & IF(COUNTIF(Q49:X49, "*IHRM*"), "IHRM ", "") & IF(COUNTIF(Q49:X49, "*HRMPB*"), "HRMPB ", "") & IF(COUNTIF(Q49:X49, "*KISM*"), "KISM ", "") & IF(COUNTIF(Q49:X49, "*ICPAK*"), "ICPAK ", "") & IF(COUNTIF(Q49:X49, "*CPA*"), "CPA ", "") & IF(COUNTIF(Q49:X49, "*Strategic Leadership*"), "SLDP ", "") & IF(COUNTIF(Q49:X49, "*Senior Management*"), "SMC ", "") & IF(COUNTIF(Q49:X49, "*Nursing*"), "NCK ", "") & IF(COUNTIF(Q49:X49, "*KMLTTB*"), "KMLTTB ", "") & IF(COUNTIF(Q49:X49, "*Cstat*"), "Cstat ", "") & IF(SUMPRODUCT(LEN(Q49:X49)-LEN(SUBSTITUTE(UPPER(Q49:X49),"CERTIFICATE","")))/11>0, SUMPRODUCT(LEN(Q49:X49)-LEN(SUBSTITUTE(UPPER(Q49:X49),"CERTIFICATE","")))/11 & " Certificates ", "") ), " ", ", ") -> PhD, MSc, Bachelors, Dip, KCSE, KCPE | Q49: Doctor of Philosophy | R49: Masters of Arts (Heath Social Science) | S49: Bachelor of Science (Enviromental Heath) | T49: Diploma in Enviromental Studies | V49: KCSE | W49: KCPE | Y49: Permanent | Z49: Kikuyu
A50: 46 | B50: 46 | C50: 20077018228 | D50: Dr. Kivai, Stanslaus Mulu | F50: 20503322 | G50: M | H50: 48 | I50: Senior Research Scientist [1] - ET - R01AQ | J50: Conservation & Ecology | K50: Q | L50: 0 - Active | M50: 06/11/2046 | N50: 39264 | O50: Dr. Kivai, Stanslaus Mulu | P50: =SUBSTITUTE(TRIM( IF(COUNTIF(Q50:X50, "*Philosophy*"), "PhD ", "") & IF(COUNTIF(Q50:X50, "*Master*"), "MSc ", "") & IF(COUNTIF(Q50:X50, "*Bachelor*"), "Bachelors ", "") & IF(COUNTIF(Q50:X50, "*Diploma*"), "Dip ", "") & IF(COUNTIF(Q50:X50, "*KCSE*"), "KCSE ", "") & IF(COUNTIF(Q50:X50, "*KCPE*"), "KCPE ", "") & IF(COUNTIF(Q50:X50, "*IHRM*"), "IHRM ", "") & IF(COUNTIF(Q50:X50, "*HRMPB*"), "HRMPB ", "") & IF(COUNTIF(Q50:X50, "*KISM*"), "KISM ", "") & IF(COUNTIF(Q50:X50, "*ICPAK*"), "ICPAK ", "") & IF(COUNTIF(Q50:X50, "*CPA*"), "CPA ", "") & IF(COUNTIF(Q50:X50, "*Strategic Leadership*"), "SLDP ", "") & IF(COUNTIF(Q50:X50, "*Senior Management*"), "SMC ", "") & IF(COUNTIF(Q50:X50, "*Nursing*"), "NCK ", "") & IF(COUNTIF(Q50:X50, "*KMLTTB*"), "KMLTTB ", "") & IF(COUNTIF(Q50:X50, "*Cstat*"), "Cstat ", "") & IF(SUMPRODUCT(LEN(Q50:X50)-LEN(SUBSTITUTE(UPPER(Q50:X50),"CERTIFICATE","")))/11>0, SUMPRODUCT(LEN(Q50:X50)-LEN(SUBSTITUTE(UPPER(Q50:X50),"CERTIFICATE","")))/11 & " Certificates ", "") ), " ", ", ") -> PhD, MSc, Bachelors, KCSE, KCPE | Q50: Doctor of Philosophy | R50: Masters of Science in Biology, Dryland Biodiversity | S50: Bachelor of Science in Nutural Resources Management | V50: KCSE | W50: KCPE | Y50: Permanent | Z50: Kamba
A51: 47 | B51: 47 | C51: 20190119450 | D51: Ms. Otoli, Pauline Muranditsi | F51: 28782265 | G51: F | H51: 33 | I51: Assistant Research Scientist - EL - R01BL | J51: Conservation & Ecology | K51: L | L51: 0 - Active | M51: 31/12/2027 | N51: 44621 | O51: Ms. Otoli, Pauline Muranditsi | P51: =SUBSTITUTE(TRIM( IF(COUNTIF(Q51:X51, "*Philosophy*"), "PhD ", "") & IF(COUNTIF(Q51:X51, "*Master*"), "MSc ", "") & IF(COUNTIF(Q51:X51, "*Bachelor*"), "Bachelors ", "") & IF(COUNTIF(Q51:X51, "*Diploma*"), "Dip ", "") & IF(COUNTIF(Q51:X51, "*KCSE*"), "KCSE ", "") & IF(COUNTIF(Q51:X51, "*KCPE*"), "KCPE ", "") & IF(COUNTIF(Q51:X51, "*IHRM*"), "IHRM ", "") & IF(COUNTIF(Q51:X51, "*HRMPB*"), "HRMPB ", "") & IF(COUNTIF(Q51:X51, "*KISM*"), "KISM ", "") & IF(COUNTIF(Q51:X51, "*ICPAK*"), "ICPAK ", "") & IF(COUNTIF(Q51:X51, "*CPA*"), "CPA ", "") & IF(COUNTIF(Q51:X51, "*Strategic Leadership*"), "SLDP ", "") & IF(COUNTIF(Q51:X51, "*Senior Management*"), "SMC ", "") & IF(COUNTIF(Q51:X51, "*Nursing*"), "NCK ", "") & IF(COUNTIF(Q51:X51, "*KMLTTB*"), "KMLTTB ", "") & IF(COUNTIF(Q51:X51, "*Cstat*"), "Cstat ", "") & IF(SUMPRODUCT(LEN(Q51:X51)-LEN(SUBSTITUTE(UPPER(Q51:X51),"CERTIFICATE","")))/11>0, SUMPRODUCT(LEN(Q51:X51)-LEN(SUBSTITUTE(UPPER(Q51:X51),"CERTIFICATE","")))/11 & " Certificates ", "") ), " ", ", ") -> Bachelors, KCSE, KCPE | S51: Bachelor of Science in Natural Resources (Wildlife management option) | V51: KCSE | W51: KCPE | Y51: Local Contract | Z51: Luhya
A52: 48 | B52: 48 | C52: 20152655365 | D52: Ms. Okero, Caroline Achieng' | F52: 25138933 | G52: F | H52: 39 | I52: Human Resource Assistant [2] - EL - C04BJ | J52: Conservation & Ecology | K52: J | L52: 0 - Active | M52: 30/06/2025 | N52: 42011 | O52: Ms. Okero, Caroline Achieng' | P52: =SUBSTITUTE(TRIM( IF(COUNTIF(Q52:X52, "*Philosophy*"), "PhD ", "") & IF(COUNTIF(Q52:X52, "*Master*"), "MSc ", "") & IF(COUNTIF(Q52:X52, "*Bachelor*"), "Bachelors ", "") & IF(COUNTIF(Q52:X52, "*Diploma*"), "Dip ", "") & IF(COUNTIF(Q52:X52, "*KCSE*"), "KCSE ", "") & IF(COUNTIF(Q52:X52, "*KCPE*"), "KCPE ", "") & IF(COUNTIF(Q52:X52, "*IHRM*"), "IHRM ", "") & IF(COUNTIF(Q52:X52, "*HRMPB*"), "HRMPB ", "") & IF(COUNTIF(Q52:X52, "*KISM*"), "KISM ", "") & IF(COUNTIF(Q52:X52, "*ICPAK*"), "ICPAK ", "") & IF(COUNTIF(Q52:X52, "*CPA*"), "CPA ", "") & IF(COUNTIF(Q52:X52, "*Strategic Leadership*"), "SLDP ", "") & IF(COUNTIF(Q52:X52, "*Senior Management*"), "SMC ", "") & IF(COUNTIF(Q52:X52, "*Nursing*"), "NCK ", "") & IF(COUNTIF(Q52:X52, "*KMLTTB*"), "KMLTTB ", "") & IF(COUNTIF(Q52:X52, "*Cstat*"), "Cstat ", "") & IF(SUMPRODUCT(LEN(Q52:X52)-LEN(SUBSTITUTE(UPPER(Q52:X52),"CERTIFICATE","")))/11>0, SUMPRODUCT(LEN(Q52:X52)-LEN(SUBSTITUTE(UPPER(Q52:X52),"CERTIFICATE","")))/11 & " Certificates ", "") ), " ", ", ") -> Dip, KCSE, KCPE | T52: Diploma in Business Administration | V52: KCSE | W52: KCPE | Y52: Local Contract | Z52: Luo
A53: 49 | B53: 49 | C53: 19920654357 | D53: Mr. Nguli, Jonathan Ngalatu | F53: 9225573 | G53: M | H53: 57 | I53: Animal Health Assistant [1] - EL - H03EH | J53: Conservation & Ecology | K53: H | L53: 0 - Active | M53: 31/12/2027 | N53: 20/05/1992 | O53: Mr. Nguli, Jonathan Ngalatu | P53: =SUBSTITUTE(TRIM( IF(COUNTIF(Q53:X53, "*Philosophy*"), "PhD ", "") & IF(COUNTIF(Q53:X53, "*Master*"), "MSc ", "") & IF(COUNTIF(Q53:X53, "*Bachelor*"), "Bachelors ", "") & IF(COUNTIF(Q53:X53, "*Diploma*"), "Dip ", "") & IF(COUNTIF(Q53:X53, "*KCSE*"), "KCSE ", "") & IF(COUNTIF(Q53:X53, "*KCPE*"), "KCPE ", "") & IF(COUNTIF(Q53:X53, "*IHRM*"), "IHRM ", "") & IF(COUNTIF(Q53:X53, "*HRMPB*"), "HRMPB ", "") & IF(COUNTIF(Q53:X53, "*KISM*"), "KISM ", "") & IF(COUNTIF(Q53:X53, "*ICPAK*"), "ICPAK ", "") & IF(COUNTIF(Q53:X53, "*CPA*"), "CPA ", "") & IF(COUNTIF(Q53:X53, "*Strategic Leadership*"), "SLDP ", "") & IF(COUNTIF(Q53:X53, "*Senior Management*"), "SMC ", "") & IF(COUNTIF(Q53:X53, "*Nursing*"), "NCK ", "") & IF(COUNTIF(Q53:X53, "*KMLTTB*"), "KMLTTB ", "") & IF(COUNTIF(Q53:X53, "*Cstat*"), "Cstat ", "") & IF(SUMPRODUCT(LEN(Q53:X53)-LEN(SUBSTITUTE(UPPER(Q53:X53),"CERTIFICATE","")))/11>0, SUMPRODUCT(LEN(Q53:X53)-LEN(SUBSTITUTE(UPPER(Q53:X53),"CERTIFICATE","")))/11 & " Certificates ", "") ), " ", ", ") -> Dip, KCSE, KCPE | T53: Diploma Wildlife /Forestry Conservation | V53: KCSE | W53: KCPE | Y53: Permanent | Z53: kamba
A54: 50 | B54: 50 | C54: 20250007868 | D54: Mr. Maingi, Charles Kivasu | F54: 26449205 | G54: M | H54: 37 | I54: Fellowship - EL - M16XG | J54: Conservation & Ecology | K54: G | L54: 0 - Active | M54: 31/12/2025 | N54: 45658 | O54: Mr. Maingi, Charles Kivasu | P54: =SUBSTITUTE(TRIM( IF(COUNTIF(Q54:X54, "*Philosophy*"), "PhD ", "") & IF(COUNTIF(Q54:X54, "*Master*"), "MSc ", "") & IF(COUNTIF(Q54:X54, "*Bachelor*"), "Bachelors ", "") & IF(COUNTIF(Q54:X54, "*Diploma*"), "Dip ", "") & IF(COUNTIF(Q54:X54, "*KCSE*"), "KCSE ", "") & IF(COUNTIF(Q54:X54, "*KCPE*"), "KCPE ", "") & IF(COUNTIF(Q54:X54, "*IHRM*"), "IHRM ", "") & IF(COUNTIF(Q54:X54, "*HRMPB*"), "HRMPB ", "") & IF(COUNTIF(Q54:X54, "*KISM*"), "KISM ", "") & IF(COUNTIF(Q54:X54, "*ICPAK*"), "ICPAK ", "") & IF(COUNTIF(Q54:X54, "*CPA*"), "CPA ", "") & IF(COUNTIF(Q54:X54, "*Strategic Leadership*"), "SLDP ", "") & IF(COUNTIF(Q54:X54, "*Senior Management*"), "SMC ", "") & IF(COUNTIF(Q54:X54, "*Nursing*"), "NCK ", "") & IF(COUNTIF(Q54:X54, "*KMLTTB*"), "KMLTTB ", "") & IF(COUNTIF(Q54:X54, "*Cstat*"), "Cstat ", "") & IF(SUMPRODUCT(LEN(Q54:X54)-LEN(SUBSTITUTE(UPPER(Q54:X54),"CERTIFICATE","")))/11>0, SUMPRODUCT(LEN(Q54:X54)-LEN(SUBSTITUTE(UPPER(Q54:X54),"CERTIFICATE","")))/11 & " Certificates ", "") ), " ", ", ") -> MSc, Bachelors, KCSE, KCPE | R54: Master of Science in Biology of Conservation | S54: Bachelor of Science( in Environmental Conservation & Natural Resource Management) | V54: KCSE | W54: KCPE | Y54: Part Time Contract | Z54: kamba
A55: 51 | B55: 51 | C55: 20250007931 | D55: Mr. Wambua, Tony Muisyo | F55: 33308998 | G55: M | H55: 29 | I55: Fellowship - EL - M16XG | J55: Conservation & Ecology | K55: G | L55: 0 - Active | M55: 28/02/2026 | N55: 45660 | O55: Mr. Wambua, Tony Muisyo | P55: =SUBSTITUTE(TRIM( IF(COUNTIF(Q55:X55, "*Philosophy*"), "PhD ", "") & IF(COUNTIF(Q55:X55, "*Master*"), "MSc ", "") & IF(COUNTIF(Q55:X55, "*Bachelor*"), "Bachelors ", "") & IF(COUNTIF(Q55:X55, "*Diploma*"), "Dip ", "") & IF(COUNTIF(Q55:X55, "*KCSE*"), "KCSE ", "") & IF(COUNTIF(Q55:X55, "*KCPE*"), "KCPE ", "") & IF(COUNTIF(Q55:X55, "*IHRM*"), "IHRM ", "") & IF(COUNTIF(Q55:X55, "*HRMPB*"), "HRMPB ", "") & IF(COUNTIF(Q55:X55, "*KISM*"), "KISM ", "") & IF(COUNTIF(Q55:X55, "*ICPAK*"), "ICPAK ", "") & IF(COUNTIF(Q55:X55, "*CPA*"), "CPA ", "") & IF(COUNTIF(Q55:X55, "*Strategic Leadership*"), "SLDP ", "") & IF(COUNTIF(Q55:X55, "*Senior Management*"), "SMC ", "") & IF(COUNTIF(Q55:X55, "*Nursing*"), "NCK ", "") & IF(COUNTIF(Q55:X55, "*KMLTTB*"), "KMLTTB ", "") & IF(COUNTIF(Q55:X55, "*Cstat*"), "Cstat ", "") & IF(SUMPRODUCT(LEN(Q55:X55)-LEN(SUBSTITUTE(UPPER(Q55:X55),"CERTIFICATE","")))/11>0, SUMPRODUCT(LEN(Q55:X55)-LEN(SUBSTITUTE(UPPER(Q55:X55),"CERTIFICATE","")))/11 & " Certificates ", "") ), " ", ", ") -> Bachelors, KCSE, KCPE | S55: Bachelor Of Science | V55: KCSE | W55: KCPE | Y55: Part Time Contract | Z55: Kamba
A56: 52 | B56: 52 | C56: 20250011215 | D56: Ms. Mbugua, Joyce Wairimu | F56: 31592937 | G56: F | H56: 30 | I56: Fellowship - EL - M16XG | J56: Conservation & Ecology | K56: G | L56: 0 - Active | M56: 31/12/2025 | N56: 45658 | O56: Ms. Mbugua, Joyce Wairimu | P56: =SUBSTITUTE(TRIM( IF(COUNTIF(Q56:X56, "*Philosophy*"), "PhD ", "") & IF(COUNTIF(Q56:X56, "*Master*"), "MSc ", "") & IF(COUNTIF(Q56:X56, "*Bachelor*"), "Bachelors ", "") & IF(COUNTIF(Q56:X56, "*Diploma*"), "Dip ", "") & IF(COUNTIF(Q56:X56, "*KCSE*"), "KCSE ", "") & IF(COUNTIF(Q56:X56, "*KCPE*"), "KCPE ", "") & IF(COUNTIF(Q56:X56, "*IHRM*"), "IHRM ", "") & IF(COUNTIF(Q56:X56, "*HRMPB*"), "HRMPB ", "") & IF(COUNTIF(Q56:X56, "*KISM*"), "KISM ", "") & IF(COUNTIF(Q56:X56, "*ICPAK*"), "ICPAK ", "") & IF(COUNTIF(Q56:X56, "*CPA*"), "CPA ", "") & IF(COUNTIF(Q56:X56, "*Strategic Leadership*"), "SLDP ", "") & IF(COUNTIF(Q56:X56, "*Senior Management*"), "SMC ", "") & IF(COUNTIF(Q56:X56, "*Nursing*"), "NCK ", "") & IF(COUNTIF(Q56:X56, "*KMLTTB*"), "KMLTTB ", "") & IF(COUNTIF(Q56:X56, "*Cstat*"), "Cstat ", "") & IF(SUMPRODUCT(LEN(Q56:X56)-LEN(SUBSTITUTE(UPPER(Q56:X56),"CERTIFICATE","")))/11>0, SUMPRODUCT(LEN(Q56:X56)-LEN(SUBSTITUTE(UPPER(Q56:X56),"CERTIFICATE","")))/11 & " Certificates ", "") ), " ", ", ") -> Bachelors, KCSE, KCPE | S56: Bachelor of Science in Environmental Studies(Planning&Management | V56: KCSE | W56: KCPE | Y56: Part Time Contract | Z56: Kikuyu
A57: 53 | B57: 53 | D57: Miss. Ruth Wambui Mburu | F57: 39029408 | G57: F | I57: Fellowship - EL - M16XG | J57: Conservation & Ecology | K57: G | L57: 0 - Active | M57: 30/04/2026 | O57: Miss. Ruth Wambui Mburu | P57: =SUBSTITUTE(TRIM( IF(COUNTIF(Q57:X57, "*Philosophy*"), "PhD ", "") & IF(COUNTIF(Q57:X57, "*Master*"), "MSc ", "") & IF(COUNTIF(Q57:X57, "*Bachelor*"), "Bachelors ", "") & IF(COUNTIF(Q57:X57, "*Diploma*"), "Dip ", "") & IF(COUNTIF(Q57:X57, "*KCSE*"), "KCSE ", "") & IF(COUNTIF(Q57:X57, "*KCPE*"), "KCPE ", "") & IF(COUNTIF(Q57:X57, "*IHRM*"), "IHRM ", "") & IF(COUNTIF(Q57:X57, "*HRMPB*"), "HRMPB ", "") & IF(COUNTIF(Q57:X57, "*KISM*"), "KISM ", "") & IF(COUNTIF(Q57:X57, "*ICPAK*"), "ICPAK ", "") & IF(COUNTIF(Q57:X57, "*CPA*"), "CPA ", "") & IF(COUNTIF(Q57:X57, "*Strategic Leadership*"), "SLDP ", "") & IF(COUNTIF(Q57:X57, "*Senior Management*"), "SMC ", "") & IF(COUNTIF(Q57:X57, "*Nursing*"), "NCK ", "") & IF(COUNTIF(Q57:X57, "*KMLTTB*"), "KMLTTB ", "") & IF(COUNTIF(Q57:X57, "*Cstat*"), "Cstat ", "") & IF(SUMPRODUCT(LEN(Q57:X57)-LEN(SUBSTITUTE(UPPER(Q57:X57),"CERTIFICATE","")))/11>0, SUMPRODUCT(LEN(Q57:X57)-LEN(SUBSTITUTE(UPPER(Q57:X57),"CERTIFICATE","")))/11 & " Certificates ", "") ), " ", ", ") -> Bachelors, KCSE, KCPE | S57: Bachelor of Science in Wildlife Enterprise& Management | V57: KCSE | W57: KCPE | Y57: Part Time Contract | Z57: Kikuyu
A58: 54 | B58: 54 | D58: Balozi Lekaso | F58: 36558749 | G58: M | I58: Fellowship - EL - M16XG | J58: Conservation & Ecology | K58: G | L58: 0 - Active | M58: 30/04/2026 | O58: Balozi Lekaso | P58: =SUBSTITUTE(TRIM( IF(COUNTIF(Q58:X58, "*Philosophy*"), "PhD ", "") & IF(COUNTIF(Q58:X58, "*Master*"), "MSc ", "") & IF(COUNTIF(Q58:X58, "*Bachelor*"), "Bachelors ", "") & IF(COUNTIF(Q58:X58, "*Diploma*"), "Dip ", "") & IF(COUNTIF(Q58:X58, "*KCSE*"), "KCSE ", "") & IF(COUNTIF(Q58:X58, "*KCPE*"), "KCPE ", "") & IF(COUNTIF(Q58:X58, "*IHRM*"), "IHRM ", "") & IF(COUNTIF(Q58:X58, "*HRMPB*"), "HRMPB ", "") & IF(COUNTIF(Q58:X58, "*KISM*"), "KISM ", "") & IF(COUNTIF(Q58:X58, "*ICPAK*"), "ICPAK ", "") & IF(COUNTIF(Q58:X58, "*CPA*"), "CPA ", "") & IF(COUNTIF(Q58:X58, "*Strategic Leadership*"), "SLDP ", "") & IF(COUNTIF(Q58:X58, "*Senior Management*"), "SMC ", "") & IF(COUNTIF(Q58:X58, "*Nursing*"), "NCK ", "") & IF(COUNTIF(Q58:X58, "*KMLTTB*"), "KMLTTB ", "") & IF(COUNTIF(Q58:X58, "*Cstat*"), "Cstat ", "") & IF(SUMPRODUCT(LEN(Q58:X58)-LEN(SUBSTITUTE(UPPER(Q58:X58),"CERTIFICATE","")))/11>0, SUMPRODUCT(LEN(Q58:X58)-LEN(SUBSTITUTE(UPPER(Q58:X58),"CERTIFICATE","")))/11 & " Certificates ", "") ), " ", ", ") -> Bachelors, KCSE, KCPE | S58: Bachelor of Environmental Studies-Science(Enviromental Biology& Health) | V58: KCSE | W58: KCPE | Y58: Part Time Contract | Z58: Samburu
A59: 55 | B59: 55 | D59: Paxton Kabasa Mugamangi | F59: 30101934 | G59: M | H59: 31 | I59: Fellowship - EL - M16XG | J59: Conservation & Ecology | K59: G | L59: 0 - Active | M59: 31/12/2025 | O59: Paxton Kabasa Mugamangi | P59: =SUBSTITUTE(TRIM( IF(COUNTIF(Q59:X59, "*Philosophy*"), "PhD ", "") & IF(COUNTIF(Q59:X59, "*Master*"), "MSc ", "") & IF(COUNTIF(Q59:X59, "*Bachelor*"), "Bachelors ", "") & IF(COUNTIF(Q59:X59, "*Diploma*"), "Dip ", "") & IF(COUNTIF(Q59:X59, "*KCSE*"), "KCSE ", "") & IF(COUNTIF(Q59:X59, "*KCPE*"), "KCPE ", "") & IF(COUNTIF(Q59:X59, "*IHRM*"), "IHRM ", "") & IF(COUNTIF(Q59:X59, "*HRMPB*"), "HRMPB ", "") & IF(COUNTIF(Q59:X59, "*KISM*"), "KISM ", "") & IF(COUNTIF(Q59:X59, "*ICPAK*"), "ICPAK ", "") & IF(COUNTIF(Q59:X59, "*CPA*"), "CPA ", "") & IF(COUNTIF(Q59:X59, "*Strategic Leadership*"), "SLDP ", "") & IF(COUNTIF(Q59:X59, "*Senior Management*"), "SMC ", "") & IF(COUNTIF(Q59:X59, "*Nursing*"), "NCK ", "") & IF(COUNTIF(Q59:X59, "*KMLTTB*"), "KMLTTB ", "") & IF(COUNTIF(Q59:X59, "*Cstat*"), "Cstat ", "") & IF(SUMPRODUCT(LEN(Q59:X59)-LEN(SUBSTITUTE(UPPER(Q59:X59),"CERTIFICATE","")))/11>0, SUMPRODUCT(LEN(Q59:X59)-LEN(SUBSTITUTE(UPPER(Q59:X59),"CERTIFICATE","")))/11 & " Certificates ", "") ), " ", ", ") -> Bachelors, KCSE, KCPE | S59: Bachelor of Science (Conservation Biology) | V59: KCSE | W59: KCPE | Y59: Part Time Contract | Z59: Luhya
A60: 89 | B60: 56 | C60: 20250011207 | D60: Mr. Hiribae, Said Rhova | F60: 25880958 | G60: M | H60: 39 | I60: Fellowship - EL - M16XG | J60: Conservation & Ecology | K60: G | L60: 0 - Active | M60: 31/12/2025 | N60: 45658 | O60: Mr. Hiribae, Said Rhova | P60: =SUBSTITUTE(TRIM( IF(COUNTIF(Q60:X60, "*Philosophy*"), "PhD ", "") & IF(COUNTIF(Q60:X60, "*Master*"), "MSc ", "") & IF(COUNTIF(Q60:X60, "*Bachelor*"), "Bachelors ", "") & IF(COUNTIF(Q60:X60, "*Diploma*"), "Dip ", "") & IF(COUNTIF(Q60:X60, "*KCSE*"), "KCSE ", "") & IF(COUNTIF(Q60:X60, "*KCPE*"), "KCPE ", "") & IF(COUNTIF(Q60:X60, "*IHRM*"), "IHRM ", "") & IF(COUNTIF(Q60:X60, "*HRMPB*"), "HRMPB ", "") & IF(COUNTIF(Q60:X60, "*KISM*"), "KISM ", "") & IF(COUNTIF(Q60:X60, "*ICPAK*"), "ICPAK ", "") & IF(COUNTIF(Q60:X60, "*CPA*"), "CPA ", "") & IF(COUNTIF(Q60:X60, "*Strategic Leadership*"), "SLDP ", "") & IF(COUNTIF(Q60:X60, "*Senior Management*"), "SMC ", "") & IF(COUNTIF(Q60:X60, "*Nursing*"), "NCK ", "") & IF(COUNTIF(Q60:X60, "*KMLTTB*"), "KMLTTB ", "") & IF(COUNTIF(Q60:X60, "*Cstat*"), "Cstat ", "") & IF(SUMPRODUCT(LEN(Q60:X60)-LEN(SUBSTITUTE(UPPER(Q60:X60),"CERTIFICATE","")))/11>0, SUMPRODUCT(LEN(Q60:X60)-LEN(SUBSTITUTE(UPPER(Q60:X60),"CERTIFICATE","")))/11 & " Certificates ", "") ), " ", ", ") -> KCSE, KCPE | V60: KCSE | W60: KCPE | Y60: Part Time Contract | Z60: Mijikenda
F61: FINANCE & ACCOUNTING | P61: =SUBSTITUTE(TRIM( IF(COUNTIF(Q61:X61, "*Philosophy*"), "PhD ", "") & IF(COUNTIF(Q61:X61, "*Master*"), "MSc ", "") & IF(COUNTIF(Q61:X61, "*Bachelor*"), "Bachelors ", "") & IF(COUNTIF(Q61:X61, "*Diploma*"), "Dip ", "") & IF(COUNTIF(Q61:X61, "*KCSE*"), "KCSE ", "") & IF(COUNTIF(Q61:X61, "*KCPE*"), "KCPE ", "") & IF(COUNTIF(Q61:X61, "*IHRM*"), "IHRM ", "") & IF(COUNTIF(Q61:X61, "*HRMPB*"), "HRMPB ", "") & IF(COUNTIF(Q61:X61, "*KISM*"), "KISM ", "") & IF(COUNTIF(Q61:X61, "*ICPAK*"), "ICPAK ", "") & IF(COUNTIF(Q61:X61, "*CPA*"), "CPA ", "") & IF(COUNTIF(Q61:X61, "*Strategic Leadership*"), "SLDP ", "") & IF(COUNTIF(Q61:X61, "*Senior Management*"), "SMC ", "") & IF(COUNTIF(Q61:X61, "*Nursing*"), "NCK ", "") & IF(COUNTIF(Q61:X61, "*KMLTTB*"), "KMLTTB ", "") & IF(COUNTIF(Q61:X61, "*Cstat*"), "Cstat ", "") & IF(SUMPRODUCT(LEN(Q61:X61)-LEN(SUBSTITUTE(UPPER(Q61:X61),"CERTIFICATE","")))/11>0, SUMPRODUCT(LEN(Q61:X61)-LEN(SUBSTITUTE(UPPER(Q61:X61),"CERTIFICATE","")))/11 & " Certificates ", "") ), " ", ", ")
A62: 56 | B62: 57 | C62: 19920654373 | D62: Mr. Mohamed, Salla Daudi | F62: 8735350 | G62: M | H62: 58 | I62: Principal Accountant - EL - D01AP | J62: Finance & Accounting | K62: P | L62: 0 - Active | M62: 06/09/2026 | N62: 26/02/1992 | O62: Mr. Mohamed, Salla Daudi | P62: =SUBSTITUTE(TRIM( IF(COUNTIF(Q62:X62, "*Philosophy*"), "PhD ", "") & IF(COUNTIF(Q62:X62, "*Master*"), "MSc ", "") & IF(COUNTIF(Q62:X62, "*Bachelor*"), "Bachelors ", "") & IF(COUNTIF(Q62:X62, "*Diploma*"), "Dip ", "") & IF(COUNTIF(Q62:X62, "*KCSE*"), "KCSE ", "") & IF(COUNTIF(Q62:X62, "*KCPE*"), "KCPE ", "") & IF(COUNTIF(Q62:X62, "*IHRM*"), "IHRM ", "") & IF(COUNTIF(Q62:X62, "*HRMPB*"), "HRMPB ", "") & IF(COUNTIF(Q62:X62, "*KISM*"), "KISM ", "") & IF(COUNTIF(Q62:X62, "*ICPAK*"), "ICPAK ", "") & IF(COUNTIF(Q62:X62, "*CPA*"), "CPA ", "") & IF(COUNTIF(Q62:X62, "*Strategic Leadership*"), "SLDP ", "") & IF(COUNTIF(Q62:X62, "*Senior Management*"), "SMC ", "") & IF(COUNTIF(Q62:X62, "*Nursing*"), "NCK ", "") & IF(COUNTIF(Q62:X62, "*KMLTTB*"), "KMLTTB ", "") & IF(COUNTIF(Q62:X62, "*Cstat*"), "Cstat ", "") & IF(SUMPRODUCT(LEN(Q62:X62)-LEN(SUBSTITUTE(UPPER(Q62:X62),"CERTIFICATE","")))/11>0, SUMPRODUCT(LEN(Q62:X62)-LEN(SUBSTITUTE(UPPER(Q62:X62),"CERTIFICATE","")))/11 & " Certificates ", "") ), " ", ", ") -> Bachelors, Dip, KCSE, KCPE, CPA | S62: Bachelor of Business Management (Accounting) | T62: Diploma in Human Resource Management | V62: KCSE | W62: KCPE | X62: CPAK | Y62: Permanent | Z62: Burji
A63: 57 | B63: 58 | C63: 20095593234 | D63: Mrs. Njogu, Esther Mukami | F63: 25394414 | G63: F | H63: 36 | I63: Principal Accountant - EL - D01AP | J63: Finance & Accounting | K63: P | L63: 0 - Active | M63: 27/05/2048 | N63: 16/06/2009 | O63: Mrs. Njogu, Esther Mukami | P63: =SUBSTITUTE(TRIM( IF(COUNTIF(Q63:X63, "*Philosophy*"), "PhD ", "") & IF(COUNTIF(Q63:X63, "*Master*"), "MSc ", "") & IF(COUNTIF(Q63:X63, "*Bachelor*"), "Bachelors ", "") & IF(COUNTIF(Q63:X63, "*Diploma*"), "Dip ", "") & IF(COUNTIF(Q63:X63, "*KCSE*"), "KCSE ", "") & IF(COUNTIF(Q63:X63, "*KCPE*"), "KCPE ", "") & IF(COUNTIF(Q63:X63, "*IHRM*"), "IHRM ", "") & IF(COUNTIF(Q63:X63, "*HRMPB*"), "HRMPB ", "") & IF(COUNTIF(Q63:X63, "*KISM*"), "KISM ", "") & IF(COUNTIF(Q63:X63, "*ICPAK*"), "ICPAK ", "") & IF(COUNTIF(Q63:X63, "*CPA*"), "CPA ", "") & IF(COUNTIF(Q63:X63, "*Strategic Leadership*"), "SLDP ", "") & IF(COUNTIF(Q63:X63, "*Senior Management*"), "SMC ", "") & IF(COUNTIF(Q63:X63, "*Nursing*"), "NCK ", "") & IF(COUNTIF(Q63:X63, "*KMLTTB*"), "KMLTTB ", "") & IF(COUNTIF(Q63:X63, "*Cstat*"), "Cstat ", "") & IF(SUMPRODUCT(LEN(Q63:X63)-LEN(SUBSTITUTE(UPPER(Q63:X63),"CERTIFICATE","")))/11>0, SUMPRODUCT(LEN(Q63:X63)-LEN(SUBSTITUTE(UPPER(Q63:X63),"CERTIFICATE","")))/11 & " Certificates ", "") ), " ", ", ") -> MSc, Bachelors, KCSE, KCPE | R63: Master of Arts in Finance | S63: Bachelor of Arts in Commerce | V63: KCSE | W63: KCPE | Y63: Permanent | Z63: Kikuyu
A64: 58 | B64: 59 | C64: 19930980988 | D64: Mr. Kahethu, Francis Kariuki | F64: 8107003 | G64: M | H64: 58 | I64: Accountant [1] - EL - D01AM | J64: Finance & Accounting | K64: M | L64: 0 - Active | M64: 01/12/2026 | N64: 33976 | O64: Mr. Kahethu, Francis Kariuki | P64: =SUBSTITUTE(TRIM( IF(COUNTIF(Q64:X64, "*Philosophy*"), "PhD ", "") & IF(COUNTIF(Q64:X64, "*Master*"), "MSc ", "") & IF(COUNTIF(Q64:X64, "*Bachelor*"), "Bachelors ", "") & IF(COUNTIF(Q64:X64, "*Diploma*"), "Dip ", "") & IF(COUNTIF(Q64:X64, "*KCSE*"), "KCSE ", "") & IF(COUNTIF(Q64:X64, "*KCPE*"), "KCPE ", "") & IF(COUNTIF(Q64:X64, "*IHRM*"), "IHRM ", "") & IF(COUNTIF(Q64:X64, "*HRMPB*"), "HRMPB ", "") & IF(COUNTIF(Q64:X64, "*KISM*"), "KISM ", "") & IF(COUNTIF(Q64:X64, "*ICPAK*"), "ICPAK ", "") & IF(COUNTIF(Q64:X64, "*CPA*"), "CPA ", "") & IF(COUNTIF(Q64:X64, "*Strategic Leadership*"), "SLDP ", "") & IF(COUNTIF(Q64:X64, "*Senior Management*"), "SMC ", "") & IF(COUNTIF(Q64:X64, "*Nursing*"), "NCK ", "") & IF(COUNTIF(Q64:X64, "*KMLTTB*"), "KMLTTB ", "") & IF(COUNTIF(Q64:X64, "*Cstat*"), "Cstat ", "") & IF(SUMPRODUCT(LEN(Q64:X64)-LEN(SUBSTITUTE(UPPER(Q64:X64),"CERTIFICATE","")))/11>0, SUMPRODUCT(LEN(Q64:X64)-LEN(SUBSTITUTE(UPPER(Q64:X64),"CERTIFICATE","")))/11 & " Certificates ", "") ), " ", ", ") -> KCSE, KCPE | U64: KATC | V64: KCSE | W64: KCPE | Y64: Permanent | Z64: kikuyu
A65: 59 | B65: 60 | C65: 20181472524 | D65: Ms. Musyoka, Cecilia Ndethya | F65: 24146874 | G65: F | H65: 40 | I65: Accountant [2] - EL - D01AL | J65: Finance & Accounting | K65: L | L65: 0 - Active | M65: 31/12/2027 | N65: 43101 | O65: Ms. Musyoka, Cecilia Ndethya | P65: =SUBSTITUTE(TRIM( IF(COUNTIF(Q65:X65, "*Philosophy*"), "PhD ", "") & IF(COUNTIF(Q65:X65, "*Master*"), "MSc ", "") & IF(COUNTIF(Q65:X65, "*Bachelor*"), "Bachelors ", "") & IF(COUNTIF(Q65:X65, "*Diploma*"), "Dip ", "") & IF(COUNTIF(Q65:X65, "*KCSE*"), "KCSE ", "") & IF(COUNTIF(Q65:X65, "*KCPE*"), "KCPE ", "") & IF(COUNTIF(Q65:X65, "*IHRM*"), "IHRM ", "") & IF(COUNTIF(Q65:X65, "*HRMPB*"), "HRMPB ", "") & IF(COUNTIF(Q65:X65, "*KISM*"), "KISM ", "") & IF(COUNTIF(Q65:X65, "*ICPAK*"), "ICPAK ", "") & IF(COUNTIF(Q65:X65, "*CPA*"), "CPA ", "") & IF(COUNTIF(Q65:X65, "*Strategic Leadership*"), "SLDP ", "") & IF(COUNTIF(Q65:X65, "*Senior Management*"), "SMC ", "") & IF(COUNTIF(Q65:X65, "*Nursing*"), "NCK ", "") & IF(COUNTIF(Q65:X65, "*KMLTTB*"), "KMLTTB ", "") & IF(COUNTIF(Q65:X65, "*Cstat*"), "Cstat ", "") & IF(SUMPRODUCT(LEN(Q65:X65)-LEN(SUBSTITUTE(UPPER(Q65:X65),"CERTIFICATE","")))/11>0, SUMPRODUCT(LEN(Q65:X65)-LEN(SUBSTITUTE(UPPER(Q65:X65),"CERTIFICATE","")))/11 & " Certificates ", "") ), " ", ", ") -> Bachelors, KCSE, KCPE | S65: Bachelor of Arts Commerce | V65: KCSE | W65: KCPE | Y65: Local Contract | Z65: Kamba
A66: 60 | B66: 61 | C66: 20240300890 | D66: Mr. Mwaniki, Samuel Macharia | F66: 37963481 | G66: M | H66: 25 | I66: Auditor [1] - EL - D07AL | J66: Finance & Accounting | K66: L | L66: 0 - Active | M66: 46883 | N66: 45301 | O66: Mr. Mwaniki, Samuel Macharia | P66: =SUBSTITUTE(TRIM( IF(COUNTIF(Q66:X66, "*Philosophy*"), "PhD ", "") & IF(COUNTIF(Q66:X66, "*Master*"), "MSc ", "") & IF(COUNTIF(Q66:X66, "*Bachelor*"), "Bachelors ", "") & IF(COUNTIF(Q66:X66, "*Diploma*"), "Dip ", "") & IF(COUNTIF(Q66:X66, "*KCSE*"), "KCSE ", "") & IF(COUNTIF(Q66:X66, "*KCPE*"), "KCPE ", "") & IF(COUNTIF(Q66:X66, "*IHRM*"), "IHRM ", "") & IF(COUNTIF(Q66:X66, "*HRMPB*"), "HRMPB ", "") & IF(COUNTIF(Q66:X66, "*KISM*"), "KISM ", "") & IF(COUNTIF(Q66:X66, "*ICPAK*"), "ICPAK ", "") & IF(COUNTIF(Q66:X66, "*CPA*"), "CPA ", "") & IF(COUNTIF(Q66:X66, "*Strategic Leadership*"), "SLDP ", "") & IF(COUNTIF(Q66:X66, "*Senior Management*"), "SMC ", "") & IF(COUNTIF(Q66:X66, "*Nursing*"), "NCK ", "") & IF(COUNTIF(Q66:X66, "*KMLTTB*"), "KMLTTB ", "") & IF(COUNTIF(Q66:X66, "*Cstat*"), "Cstat ", "") & IF(SUMPRODUCT(LEN(Q66:X66)-LEN(SUBSTITUTE(UPPER(Q66:X66),"CERTIFICATE","")))/11>0, SUMPRODUCT(LEN(Q66:X66)-LEN(SUBSTITUTE(UPPER(Q66:X66),"CERTIFICATE","")))/11 & " Certificates ", "") ), " ", ", ") -> Bachelors, KCSE, KCPE | S66: Bachelor of Commerce (Accounting) | V66: KCSE | W66: KCPE | Y66: Local Contract | Z66: Kikuyu
A67: 61 | B67: 62 | C67: 20250067240 | D67: Sylvia mercy Abere | F67: 36697114 | G67: F | I67: Accountant 11 | J67: Finance & Accounting | K67: L | L67: 0 - Active | M67: 46757 | N67: 45693 | O67: Sylvia mercy Abere | P67: =SUBSTITUTE(TRIM( IF(COUNTIF(Q67:X67, "*Philosophy*"), "PhD ", "") & IF(COUNTIF(Q67:X67, "*Master*"), "MSc ", "") & IF(COUNTIF(Q67:X67, "*Bachelor*"), "Bachelors ", "") & IF(COUNTIF(Q67:X67, "*Diploma*"), "Dip ", "") & IF(COUNTIF(Q67:X67, "*KCSE*"), "KCSE ", "") & IF(COUNTIF(Q67:X67, "*KCPE*"), "KCPE ", "") & IF(COUNTIF(Q67:X67, "*IHRM*"), "IHRM ", "") & IF(COUNTIF(Q67:X67, "*HRMPB*"), "HRMPB ", "") & IF(COUNTIF(Q67:X67, "*KISM*"), "KISM ", "") & IF(COUNTIF(Q67:X67, "*ICPAK*"), "ICPAK ", "") & IF(COUNTIF(Q67:X67, "*CPA*"), "CPA ", "") & IF(COUNTIF(Q67:X67, "*Strategic Leadership*"), "SLDP ", "") & IF(COUNTIF(Q67:X67, "*Senior Management*"), "SMC ", "") & IF(COUNTIF(Q67:X67, "*Nursing*"), "NCK ", "") & IF(COUNTIF(Q67:X67, "*KMLTTB*"), "KMLTTB ", "") & IF(COUNTIF(Q67:X67, "*Cstat*"), "Cstat ", "") & IF(SUMPRODUCT(LEN(Q67:X67)-LEN(SUBSTITUTE(UPPER(Q67:X67),"CERTIFICATE","")))/11>0, SUMPRODUCT(LEN(Q67:X67)-LEN(SUBSTITUTE(UPPER(Q67:X67),"CERTIFICATE","")))/11 & " Certificates ", "") ), " ", ", ") -> Bachelors, KCSE, KCPE | S67: Bachelor of Commerce (Finance) | V67: KCSE | W67: KCPE | Y67: Local Contract | Z67: Kisii
A68: 62 | B68: 63 | C68: 20250067232 | D68: Lewis Gitonga Nyaga | F68: 33381959 | G68: M | I68: Accountant 11 | J68: Finance & Accounting | K68: L | L68: 0 - Active | M68: 46757 | N68: 45693 | O68: Lewis Gitonga Nyaga | P68: =SUBSTITUTE(TRIM( IF(COUNTIF(Q68:X68, "*Philosophy*"), "PhD ", "") & IF(COUNTIF(Q68:X68, "*Master*"), "MSc ", "") & IF(COUNTIF(Q68:X68, "*Bachelor*"), "Bachelors ", "") & IF(COUNTIF(Q68:X68, "*Diploma*"), "Dip ", "") & IF(COUNTIF(Q68:X68, "*KCSE*"), "KCSE ", "") & IF(COUNTIF(Q68:X68, "*KCPE*"), "KCPE ", "") & IF(COUNTIF(Q68:X68, "*IHRM*"), "IHRM ", "") & IF(COUNTIF(Q68:X68, "*HRMPB*"), "HRMPB ", "") & IF(COUNTIF(Q68:X68, "*KISM*"), "KISM ", "") & IF(COUNTIF(Q68:X68, "*ICPAK*"), "ICPAK ", "") & IF(COUNTIF(Q68:X68, "*CPA*"), "CPA ", "") & IF(COUNTIF(Q68:X68, "*Strategic Leadership*"), "SLDP ", "") & IF(COUNTIF(Q68:X68, "*Senior Management*"), "SMC ", "") & IF(COUNTIF(Q68:X68, "*Nursing*"), "NCK ", "") & IF(COUNTIF(Q68:X68, "*KMLTTB*"), "KMLTTB ", "") & IF(COUNTIF(Q68:X68, "*Cstat*"), "Cstat ", "") & IF(SUMPRODUCT(LEN(Q68:X68)-LEN(SUBSTITUTE(UPPER(Q68:X68),"CERTIFICATE","")))/11>0, SUMPRODUCT(LEN(Q68:X68)-LEN(SUBSTITUTE(UPPER(Q68:X68),"CERTIFICATE","")))/11 & " Certificates ", "") ), " ", ", ") -> Bachelors, KCSE, KCPE | S68: Bachelor of Commerce (Accounting) | V68: KCSE | W68: KCPE | Y68: Local Contract | Z68: Embu
A69: 63 | B69: 64 | C69: 20250067258 | D69: Janet Wanjui Kinyua | F69: 39000494 | G69: F | I69: Accountant 11 | J69: Finance & Accounting | K69: L | L69: 0 - Active | M69: 46757 | N69: 45693 | O69: Janet Wanjui Kinyua | P69: =SUBSTITUTE(TRIM( IF(COUNTIF(Q69:X69, "*Philosophy*"), "PhD ", "") & IF(COUNTIF(Q69:X69, "*Master*"), "MSc ", "") & IF(COUNTIF(Q69:X69, "*Bachelor*"), "Bachelors ", "") & IF(COUNTIF(Q69:X69, "*Diploma*"), "Dip ", "") & IF(COUNTIF(Q69:X69, "*KCSE*"), "KCSE ", "") & IF(COUNTIF(Q69:X69, "*KCPE*"), "KCPE ", "") & IF(COUNTIF(Q69:X69, "*IHRM*"), "IHRM ", "") & IF(COUNTIF(Q69:X69, "*HRMPB*"), "HRMPB ", "") & IF(COUNTIF(Q69:X69, "*KISM*"), "KISM ", "") & IF(COUNTIF(Q69:X69, "*ICPAK*"), "ICPAK ", "") & IF(COUNTIF(Q69:X69, "*CPA*"), "CPA ", "") & IF(COUNTIF(Q69:X69, "*Strategic Leadership*"), "SLDP ", "") & IF(COUNTIF(Q69:X69, "*Senior Management*"), "SMC ", "") & IF(COUNTIF(Q69:X69, "*Nursing*"), "NCK ", "") & IF(COUNTIF(Q69:X69, "*KMLTTB*"), "KMLTTB ", "") & IF(COUNTIF(Q69:X69, "*Cstat*"), "Cstat ", "") & IF(SUMPRODUCT(LEN(Q69:X69)-LEN(SUBSTITUTE(UPPER(Q69:X69),"CERTIFICATE","")))/11>0, SUMPRODUCT(LEN(Q69:X69)-LEN(SUBSTITUTE(UPPER(Q69:X69),"CERTIFICATE","")))/11 & " Certificates ", "") ), " ", ", ") -> Bachelors, KCSE, KCPE | S69: Bachelor of Commerce (Finance) | V69: KCSE | W69: KCPE | Y69: Local Contract | Z69: Kikuyu
A70: 64 | B70: 65 | C70: 20220598342 | D70: Mr. Nkarero, Antony Ntiita | F70: 31621426 | G70: M | H70: 30 | I70: Clerical Officer - EL - T03AG | J70: Finance & Accounting | K70: G | L70: 0 - Active | M70: 31/01/2028 | N70: 20/01/2022 | O70: Mr. Nkarero, Antony Ntiita | P70: =SUBSTITUTE(TRIM( IF(COUNTIF(Q70:X70, "*Philosophy*"), "PhD ", "") & IF(COUNTIF(Q70:X70, "*Master*"), "MSc ", "") & IF(COUNTIF(Q70:X70, "*Bachelor*"), "Bachelors ", "") & IF(COUNTIF(Q70:X70, "*Diploma*"), "Dip ", "") & IF(COUNTIF(Q70:X70, "*KCSE*"), "KCSE ", "") & IF(COUNTIF(Q70:X70, "*KCPE*"), "KCPE ", "") & IF(COUNTIF(Q70:X70, "*IHRM*"), "IHRM ", "") & IF(COUNTIF(Q70:X70, "*HRMPB*"), "HRMPB ", "") & IF(COUNTIF(Q70:X70, "*KISM*"), "KISM ", "") & IF(COUNTIF(Q70:X70, "*ICPAK*"), "ICPAK ", "") & IF(COUNTIF(Q70:X70, "*CPA*"), "CPA ", "") & IF(COUNTIF(Q70:X70, "*Strategic Leadership*"), "SLDP ", "") & IF(COUNTIF(Q70:X70, "*Senior Management*"), "SMC ", "") & IF(COUNTIF(Q70:X70, "*Nursing*"), "NCK ", "") & IF(COUNTIF(Q70:X70, "*KMLTTB*"), "KMLTTB ", "") & IF(COUNTIF(Q70:X70, "*Cstat*"), "Cstat ", "") & IF(SUMPRODUCT(LEN(Q70:X70)-LEN(SUBSTITUTE(UPPER(Q70:X70),"CERTIFICATE","")))/11>0, SUMPRODUCT(LEN(Q70:X70)-LEN(SUBSTITUTE(UPPER(Q70:X70),"CERTIFICATE","")))/11 & " Certificates ", "") ), " ", ", ") -> KCSE, KCPE, 1, Certificates | U70: Certificate in Early Childhood Development | V70: KCSE | W70: KCPE | Y70: Local Contract | Z70: Maasai
F71: INFORMATION COMMUNICATION & TECHNOLOGY | P71: =SUBSTITUTE(TRIM( IF(COUNTIF(Q71:X71, "*Philosophy*"), "PhD ", "") & IF(COUNTIF(Q71:X71, "*Master*"), "MSc ", "") & IF(COUNTIF(Q71:X71, "*Bachelor*"), "Bachelors ", "") & IF(COUNTIF(Q71:X71, "*Diploma*"), "Dip ", "") & IF(COUNTIF(Q71:X71, "*KCSE*"), "KCSE ", "") & IF(COUNTIF(Q71:X71, "*KCPE*"), "KCPE ", "") & IF(COUNTIF(Q71:X71, "*IHRM*"), "IHRM ", "") & IF(COUNTIF(Q71:X71, "*HRMPB*"), "HRMPB ", "") & IF(COUNTIF(Q71:X71, "*KISM*"), "KISM ", "") & IF(COUNTIF(Q71:X71, "*ICPAK*"), "ICPAK ", "") & IF(COUNTIF(Q71:X71, "*CPA*"), "CPA ", "") & IF(COUNTIF(Q71:X71, "*Strategic Leadership*"), "SLDP ", "") & IF(COUNTIF(Q71:X71, "*Senior Management*"), "SMC ", "") & IF(COUNTIF(Q71:X71, "*Nursing*"), "NCK ", "") & IF(COUNTIF(Q71:X71, "*KMLTTB*"), "KMLTTB ", "") & IF(COUNTIF(Q71:X71, "*Cstat*"), "Cstat ", "") & IF(SUMPRODUCT(LEN(Q71:X71)-LEN(SUBSTITUTE(UPPER(Q71:X71),"CERTIFICATE","")))/11>0, SUMPRODUCT(LEN(Q71:X71)-LEN(SUBSTITUTE(UPPER(Q71:X71),"CERTIFICATE","")))/11 & " Certificates ", "") ), " ", ", ")
A72: 65 | B72: 66 | C72: 20200484002 | D72: Mr. Charles, Akama Okioma | F72: 33171966 | G72: M | H72: 29 | I72: Information Communication Technology Officer [1] - EL - M11AM | J72: ICT | K72: M | L72: 0 - Active | M72: 31/12/2027 | N72: 15/07/2020 | O72: Mr. Charles, Akama Okioma | P72: =SUBSTITUTE(TRIM( IF(COUNTIF(Q72:X72, "*Philosophy*"), "PhD ", "") & IF(COUNTIF(Q72:X72, "*Master*"), "MSc ", "") & IF(COUNTIF(Q72:X72, "*Bachelor*"), "Bachelors ", "") & IF(COUNTIF(Q72:X72, "*Diploma*"), "Dip ", "") & IF(COUNTIF(Q72:X72, "*KCSE*"), "KCSE ", "") & IF(COUNTIF(Q72:X72, "*KCPE*"), "KCPE ", "") & IF(COUNTIF(Q72:X72, "*IHRM*"), "IHRM ", "") & IF(COUNTIF(Q72:X72, "*HRMPB*"), "HRMPB ", "") & IF(COUNTIF(Q72:X72, "*KISM*"), "KISM ", "") & IF(COUNTIF(Q72:X72, "*ICPAK*"), "ICPAK ", "") & IF(COUNTIF(Q72:X72, "*CPA*"), "CPA ", "") & IF(COUNTIF(Q72:X72, "*Strategic Leadership*"), "SLDP ", "") & IF(COUNTIF(Q72:X72, "*Senior Management*"), "SMC ", "") & IF(COUNTIF(Q72:X72, "*Nursing*"), "NCK ", "") & IF(COUNTIF(Q72:X72, "*KMLTTB*"), "KMLTTB ", "") & IF(COUNTIF(Q72:X72, "*Cstat*"), "Cstat ", "") & IF(SUMPRODUCT(LEN(Q72:X72)-LEN(SUBSTITUTE(UPPER(Q72:X72),"CERTIFICATE","")))/11>0, SUMPRODUCT(LEN(Q72:X72)-LEN(SUBSTITUTE(UPPER(Q72:X72),"CERTIFICATE","")))/11 & " Certificates ", "") ), " ", ", ") -> Bachelors, KCSE, KCPE | S72: Bachelor of Science in Statistics and Programming | V72: KCSE | W72: KCPE | Y72: Local Contract | Z72: Kisii
A73: 66 | B73: 67 | C73: 20200484010 | D73: Mr. Kirima, Vincent Mwenda | F73: 30408351 | G73: M | H73: 32 | I73: Information Communication Technology Officer [2] - EL - M11AL | J73: ICT | K73: L | L73: 0 - Active | M73: 30/06/2026 | N73: 43837 | O73: Mr. Kirima, Vincent Mwenda | P73: =SUBSTITUTE(TRIM( IF(COUNTIF(Q73:X73, "*Philosophy*"), "PhD ", "") & IF(COUNTIF(Q73:X73, "*Master*"), "MSc ", "") & IF(COUNTIF(Q73:X73, "*Bachelor*"), "Bachelors ", "") & IF(COUNTIF(Q73:X73, "*Diploma*"), "Dip ", "") & IF(COUNTIF(Q73:X73, "*KCSE*"), "KCSE ", "") & IF(COUNTIF(Q73:X73, "*KCPE*"), "KCPE ", "") & IF(COUNTIF(Q73:X73, "*IHRM*"), "IHRM ", "") & IF(COUNTIF(Q73:X73, "*HRMPB*"), "HRMPB ", "") & IF(COUNTIF(Q73:X73, "*KISM*"), "KISM ", "") & IF(COUNTIF(Q73:X73, "*ICPAK*"), "ICPAK ", "") & IF(COUNTIF(Q73:X73, "*CPA*"), "CPA ", "") & IF(COUNTIF(Q73:X73, "*Strategic Leadership*"), "SLDP ", "") & IF(COUNTIF(Q73:X73, "*Senior Management*"), "SMC ", "") & IF(COUNTIF(Q73:X73, "*Nursing*"), "NCK ", "") & IF(COUNTIF(Q73:X73, "*KMLTTB*"), "KMLTTB ", "") & IF(COUNTIF(Q73:X73, "*Cstat*"), "Cstat ", "") & IF(SUMPRODUCT(LEN(Q73:X73)-LEN(SUBSTITUTE(UPPER(Q73:X73),"CERTIFICATE","")))/11>0, SUMPRODUCT(LEN(Q73:X73)-LEN(SUBSTITUTE(UPPER(Q73:X73),"CERTIFICATE","")))/11 & " Certificates ", "") ), " ", ", ") -> Bachelors, Dip, KCSE, KCPE | S73: Bachelor of Arts in IT | T73: Diploma In IT | V73: KCSE | W73: KCPE | Y73: Local Contract | Z73: Meru
A74: 67 | B74: 68 | C74: 20220597964 | D74: Mr. Sing'oei, Johnson Kiplangat | F74: 35685292 | G74: M | H74: 26 | I74: Information Communication Technology Officer [2] - EL - M11AL | J74: ICT | K74: L | L74: 0 - Active | M74: 31/01/2028 | N74: 44806 | O74: Mr. Sing'oei, Johnson Kiplangat | P74: =SUBSTITUTE(TRIM( IF(COUNTIF(Q74:X74, "*Philosophy*"), "PhD ", "") & IF(COUNTIF(Q74:X74, "*Master*"), "MSc ", "") & IF(COUNTIF(Q74:X74, "*Bachelor*"), "Bachelors ", "") & IF(COUNTIF(Q74:X74, "*Diploma*"), "Dip ", "") & IF(COUNTIF(Q74:X74, "*KCSE*"), "KCSE ", "") & IF(COUNTIF(Q74:X74, "*KCPE*"), "KCPE ", "") & IF(COUNTIF(Q74:X74, "*IHRM*"), "IHRM ", "") & IF(COUNTIF(Q74:X74, "*HRMPB*"), "HRMPB ", "") & IF(COUNTIF(Q74:X74, "*KISM*"), "KISM ", "") & IF(COUNTIF(Q74:X74, "*ICPAK*"), "ICPAK ", "") & IF(COUNTIF(Q74:X74, "*CPA*"), "CPA ", "") & IF(COUNTIF(Q74:X74, "*Strategic Leadership*"), "SLDP ", "") & IF(COUNTIF(Q74:X74, "*Senior Management*"), "SMC ", "") & IF(COUNTIF(Q74:X74, "*Nursing*"), "NCK ", "") & IF(COUNTIF(Q74:X74, "*KMLTTB*"), "KMLTTB ", "") & IF(COUNTIF(Q74:X74, "*Cstat*"), "Cstat ", "") & IF(SUMPRODUCT(LEN(Q74:X74)-LEN(SUBSTITUTE(UPPER(Q74:X74),"CERTIFICATE","")))/11>0, SUMPRODUCT(LEN(Q74:X74)-LEN(SUBSTITUTE(UPPER(Q74:X74),"CERTIFICATE","")))/11 & " Certificates ", "") ), " ", ", ") -> Bachelors, KCSE, KCPE | S74: Bachelor of Arts in IT | V74: KCSE | W74: KCPE | Y74: Local Contract | Z74: Kalenjin
A75: 68 | B75: 69 | C75: 20220597906 | D75: Mr. Chai, David Chivatsi | F75: 30050596 | G75: M | H75: 32 | I75: Information Communication Technology Assistant [2] - EL - M11BJ | J75: ICT | K75: J | L75: 0 - Active | M75: 31/01/2028 | N75: 21/02/2022 | O75: Mr. Chai, David Chivatsi | P75: =SUBSTITUTE(TRIM( IF(COUNTIF(Q75:X75, "*Philosophy*"), "PhD ", "") & IF(COUNTIF(Q75:X75, "*Master*"), "MSc ", "") & IF(COUNTIF(Q75:X75, "*Bachelor*"), "Bachelors ", "") & IF(COUNTIF(Q75:X75, "*Diploma*"), "Dip ", "") & IF(COUNTIF(Q75:X75, "*KCSE*"), "KCSE ", "") & IF(COUNTIF(Q75:X75, "*KCPE*"), "KCPE ", "") & IF(COUNTIF(Q75:X75, "*IHRM*"), "IHRM ", "") & IF(COUNTIF(Q75:X75, "*HRMPB*"), "HRMPB ", "") & IF(COUNTIF(Q75:X75, "*KISM*"), "KISM ", "") & IF(COUNTIF(Q75:X75, "*ICPAK*"), "ICPAK ", "") & IF(COUNTIF(Q75:X75, "*CPA*"), "CPA ", "") & IF(COUNTIF(Q75:X75, "*Strategic Leadership*"), "SLDP ", "") & IF(COUNTIF(Q75:X75, "*Senior Management*"), "SMC ", "") & IF(COUNTIF(Q75:X75, "*Nursing*"), "NCK ", "") & IF(COUNTIF(Q75:X75, "*KMLTTB*"), "KMLTTB ", "") & IF(COUNTIF(Q75:X75, "*Cstat*"), "Cstat ", "") & IF(SUMPRODUCT(LEN(Q75:X75)-LEN(SUBSTITUTE(UPPER(Q75:X75),"CERTIFICATE","")))/11>0, SUMPRODUCT(LEN(Q75:X75)-LEN(SUBSTITUTE(UPPER(Q75:X75),"CERTIFICATE","")))/11 & " Certificates ", "") ), " ", ", ") -> Dip, KCSE, KCPE | T75: Diploma in Health Records and Informatiom Technology | V75: KCSE | W75: KCPE | Y75: Local Contract | Z75: Mijikenda
F76: KSRIC | P76: =SUBSTITUTE(TRIM( IF(COUNTIF(Q76:X76, "*Philosophy*"), "PhD ", "") & IF(COUNTIF(Q76:X76, "*Master*"), "MSc ", "") & IF(COUNTIF(Q76:X76, "*Bachelor*"), "Bachelors ", "") & IF(COUNTIF(Q76:X76, "*Diploma*"), "Dip ", "") & IF(COUNTIF(Q76:X76, "*KCSE*"), "KCSE ", "") & IF(COUNTIF(Q76:X76, "*KCPE*"), "KCPE ", "") & IF(COUNTIF(Q76:X76, "*IHRM*"), "IHRM ", "") & IF(COUNTIF(Q76:X76, "*HRMPB*"), "HRMPB ", "") & IF(COUNTIF(Q76:X76, "*KISM*"), "KISM ", "") & IF(COUNTIF(Q76:X76, "*ICPAK*"), "ICPAK ", "") & IF(COUNTIF(Q76:X76, "*CPA*"), "CPA ", "") & IF(COUNTIF(Q76:X76, "*Strategic Leadership*"), "SLDP ", "") & IF(COUNTIF(Q76:X76, "*Senior Management*"), "SMC ", "") & IF(COUNTIF(Q76:X76, "*Nursing*"), "NCK ", "") & IF(COUNTIF(Q76:X76, "*KMLTTB*"), "KMLTTB ", "") & IF(COUNTIF(Q76:X76, "*Cstat*"), "Cstat ", "") & IF(SUMPRODUCT(LEN(Q76:X76)-LEN(SUBSTITUTE(UPPER(Q76:X76),"CERTIFICATE","")))/11>0, SUMPRODUCT(LEN(Q76:X76)-LEN(SUBSTITUTE(UPPER(Q76:X76),"CERTIFICATE","")))/11 & " Certificates ", "") ), " ", ", ")
A77: 69 | B77: 70 | C77: 20121210938 | D77: Dr. Oluoch, George Omondi | F77: 24416334 | G77: M | H77: 39 | I77: Senior Veterinary Officer - EL - H04AP | J77: KSRIC | K77: P | L77: 0 - Active | M77: 16/09/2045 | N77: 40916 | O77: Dr. Oluoch, George Omondi | P77: =SUBSTITUTE(TRIM( IF(COUNTIF(Q77:X77, "*Philosophy*"), "PhD ", "") & IF(COUNTIF(Q77:X77, "*Master*"), "MSc ", "") & IF(COUNTIF(Q77:X77, "*Bachelor*"), "Bachelors ", "") & IF(COUNTIF(Q77:X77, "*Diploma*"), "Dip ", "") & IF(COUNTIF(Q77:X77, "*KCSE*"), "KCSE ", "") & IF(COUNTIF(Q77:X77, "*KCPE*"), "KCPE ", "") & IF(COUNTIF(Q77:X77, "*IHRM*"), "IHRM ", "") & IF(COUNTIF(Q77:X77, "*HRMPB*"), "HRMPB ", "") & IF(COUNTIF(Q77:X77, "*KISM*"), "KISM ", "") & IF(COUNTIF(Q77:X77, "*ICPAK*"), "ICPAK ", "") & IF(COUNTIF(Q77:X77, "*CPA*"), "CPA ", "") & IF(COUNTIF(Q77:X77, "*Strategic Leadership*"), "SLDP ", "") & IF(COUNTIF(Q77:X77, "*Senior Management*"), "SMC ", "") & IF(COUNTIF(Q77:X77, "*Nursing*"), "NCK ", "") & IF(COUNTIF(Q77:X77, "*KMLTTB*"), "KMLTTB ", "") & IF(COUNTIF(Q77:X77, "*Cstat*"), "Cstat ", "") & IF(SUMPRODUCT(LEN(Q77:X77)-LEN(SUBSTITUTE(UPPER(Q77:X77),"CERTIFICATE","")))/11>0, SUMPRODUCT(LEN(Q77:X77)-LEN(SUBSTITUTE(UPPER(Q77:X77),"CERTIFICATE","")))/11 & " Certificates ", "") ), " ", ", ") -> MSc, Bachelors, KCSE, KCPE, 1, Certificates | R77: Master of Science in Tropical and Infectious Diseases | S77: Bachelor of Veterinary Medicine | V77: KCSE | W77: KCPE | X77: Certificate of Registration of A Veterinary Surgeon | Y77: Permanent | Z77: Luo
A78: 70 | B78: 71 | C78: 2013091337 | D78: Ms. Ngari, Cecilia Wairimu | F78: 27494151 | G78: F | H78: 35 | I78: Assistant Research Scientist - EL - R01BL | J78: KSRIC | K78: L | L78: 0 - Active | M78: 31/12/2027 | N78: 44621 | O78: Ms. Ngari, Cecilia Wairimu | P78: =SUBSTITUTE(TRIM( IF(COUNTIF(Q78:X78, "*Philosophy*"), "PhD ", "") & IF(COUNTIF(Q78:X78, "*Master*"), "MSc ", "") & IF(COUNTIF(Q78:X78, "*Bachelor*"), "Bachelors ", "") & IF(COUNTIF(Q78:X78, "*Diploma*"), "Dip ", "") & IF(COUNTIF(Q78:X78, "*KCSE*"), "KCSE ", "") & IF(COUNTIF(Q78:X78, "*KCPE*"), "KCPE ", "") & IF(COUNTIF(Q78:X78, "*IHRM*"), "IHRM ", "") & IF(COUNTIF(Q78:X78, "*HRMPB*"), "HRMPB ", "") & IF(COUNTIF(Q78:X78, "*KISM*"), "KISM ", "") & IF(COUNTIF(Q78:X78, "*ICPAK*"), "ICPAK ", "") & IF(COUNTIF(Q78:X78, "*CPA*"), "CPA ", "") & IF(COUNTIF(Q78:X78, "*Strategic Leadership*"), "SLDP ", "") & IF(COUNTIF(Q78:X78, "*Senior Management*"), "SMC ", "") & IF(COUNTIF(Q78:X78, "*Nursing*"), "NCK ", "") & IF(COUNTIF(Q78:X78, "*KMLTTB*"), "KMLTTB ", "") & IF(COUNTIF(Q78:X78, "*Cstat*"), "Cstat ", "") & IF(SUMPRODUCT(LEN(Q78:X78)-LEN(SUBSTITUTE(UPPER(Q78:X78),"CERTIFICATE","")))/11>0, SUMPRODUCT(LEN(Q78:X78)-LEN(SUBSTITUTE(UPPER(Q78:X78),"CERTIFICATE","")))/11 & " Certificates ", "") ), " ", ", ") -> Bachelors, KCSE, KCPE, NCK | S78: Bachelor of Science in Nursing | V78: KCSE | W78: KCPE | X78: Nursing Council Of Kenya | Y78: Local Contract | Z78: Kikuyu
A79: 71 | B79: 72 | C79: 20220598960 | D79: Ms. Asila, Loreta Anyanje | F79: 27895831 | G79: F | H79: 35 | I79: Assistant Research Scientist - EL - R01BL | J79: KSRIC | K79: L | L79: 0 - Active | M79: 30/11/2027 | N79: 44621 | O79: Ms. Asila, Loreta Anyanje | P79: =SUBSTITUTE(TRIM( IF(COUNTIF(Q79:X79, "*Philosophy*"), "PhD ", "") & IF(COUNTIF(Q79:X79, "*Master*"), "MSc ", "") & IF(COUNTIF(Q79:X79, "*Bachelor*"), "Bachelors ", "") & IF(COUNTIF(Q79:X79, "*Diploma*"), "Dip ", "") & IF(COUNTIF(Q79:X79, "*KCSE*"), "KCSE ", "") & IF(COUNTIF(Q79:X79, "*KCPE*"), "KCPE ", "") & IF(COUNTIF(Q79:X79, "*IHRM*"), "IHRM ", "") & IF(COUNTIF(Q79:X79, "*HRMPB*"), "HRMPB ", "") & IF(COUNTIF(Q79:X79, "*KISM*"), "KISM ", "") & IF(COUNTIF(Q79:X79, "*ICPAK*"), "ICPAK ", "") & IF(COUNTIF(Q79:X79, "*CPA*"), "CPA ", "") & IF(COUNTIF(Q79:X79, "*Strategic Leadership*"), "SLDP ", "") & IF(COUNTIF(Q79:X79, "*Senior Management*"), "SMC ", "") & IF(COUNTIF(Q79:X79, "*Nursing*"), "NCK ", "") & IF(COUNTIF(Q79:X79, "*KMLTTB*"), "KMLTTB ", "") & IF(COUNTIF(Q79:X79, "*Cstat*"), "Cstat ", "") & IF(SUMPRODUCT(LEN(Q79:X79)-LEN(SUBSTITUTE(UPPER(Q79:X79),"CERTIFICATE","")))/11>0, SUMPRODUCT(LEN(Q79:X79)-LEN(SUBSTITUTE(UPPER(Q79:X79),"CERTIFICATE","")))/11 & " Certificates ", "") ), " ", ", ") -> Bachelors, KCSE, KCPE | S79: Bachelor of Science in Biostatistics | V79: KCSE | W79: KCPE | Y79: Local Contract | Z79: Luhya
A80: 72 | B80: 73 | C80: 2012024370 | D80: Ms. Antar, Munira Said A | F80: 23875841 | G80: F | H80: 40 | I80: Fellowship - EL - M16XG | J80: KSRIC | K80: G | L80: 0 - Active | M80: 02/01/2026 | N80: 44621 | O80: Ms. Antar, Munira Said A | P80: =SUBSTITUTE(TRIM( IF(COUNTIF(Q80:X80, "*Philosophy*"), "PhD ", "") & IF(COUNTIF(Q80:X80, "*Master*"), "MSc ", "") & IF(COUNTIF(Q80:X80, "*Bachelor*"), "Bachelors ", "") & IF(COUNTIF(Q80:X80, "*Diploma*"), "Dip ", "") & IF(COUNTIF(Q80:X80, "*KCSE*"), "KCSE ", "") & IF(COUNTIF(Q80:X80, "*KCPE*"), "KCPE ", "") & IF(COUNTIF(Q80:X80, "*IHRM*"), "IHRM ", "") & IF(COUNTIF(Q80:X80, "*HRMPB*"), "HRMPB ", "") & IF(COUNTIF(Q80:X80, "*KISM*"), "KISM ", "") & IF(COUNTIF(Q80:X80, "*ICPAK*"), "ICPAK ", "") & IF(COUNTIF(Q80:X80, "*CPA*"), "CPA ", "") & IF(COUNTIF(Q80:X80, "*Strategic Leadership*"), "SLDP ", "") & IF(COUNTIF(Q80:X80, "*Senior Management*"), "SMC ", "") & IF(COUNTIF(Q80:X80, "*Nursing*"), "NCK ", "") & IF(COUNTIF(Q80:X80, "*KMLTTB*"), "KMLTTB ", "") & IF(COUNTIF(Q80:X80, "*Cstat*"), "Cstat ", "") & IF(SUMPRODUCT(LEN(Q80:X80)-LEN(SUBSTITUTE(UPPER(Q80:X80),"CERTIFICATE","")))/11>0, SUMPRODUCT(LEN(Q80:X80)-LEN(SUBSTITUTE(UPPER(Q80:X80),"CERTIFICATE","")))/11 & " Certificates ", "") ), " ", ", ") -> MSc, Bachelors, KCSE, KCPE | R80: Master of Science in Medical Microbiology | S80: Bachelor of Science in Microbiology | V80: KCSE | W80: KCPE | Y80: Part Time Contract | Z80: Kenyan Arab
A81: 73 | B81: 74 | C81: 20181472223 | D81: Mr. Abisai, Fredrick Angote | F81: 33852077 | G81: M | H81: 27 | I81: Fellowship - EL - M16XG | J81: KSRIC | K81: G | L81: 0 - Active | M81: 14/07/2025 | N81: 43284 | O81: Mr. Abisai, Fredrick Angote | P81: =SUBSTITUTE(TRIM( IF(COUNTIF(Q81:X81, "*Philosophy*"), "PhD ", "") & IF(COUNTIF(Q81:X81, "*Master*"), "MSc ", "") & IF(COUNTIF(Q81:X81, "*Bachelor*"), "Bachelors ", "") & IF(COUNTIF(Q81:X81, "*Diploma*"), "Dip ", "") & IF(COUNTIF(Q81:X81, "*KCSE*"), "KCSE ", "") & IF(COUNTIF(Q81:X81, "*KCPE*"), "KCPE ", "") & IF(COUNTIF(Q81:X81, "*IHRM*"), "IHRM ", "") & IF(COUNTIF(Q81:X81, "*HRMPB*"), "HRMPB ", "") & IF(COUNTIF(Q81:X81, "*KISM*"), "KISM ", "") & IF(COUNTIF(Q81:X81, "*ICPAK*"), "ICPAK ", "") & IF(COUNTIF(Q81:X81, "*CPA*"), "CPA ", "") & IF(COUNTIF(Q81:X81, "*Strategic Leadership*"), "SLDP ", "") & IF(COUNTIF(Q81:X81, "*Senior Management*"), "SMC ", "") & IF(COUNTIF(Q81:X81, "*Nursing*"), "NCK ", "") & IF(COUNTIF(Q81:X81, "*KMLTTB*"), "KMLTTB ", "") & IF(COUNTIF(Q81:X81, "*Cstat*"), "Cstat ", "") & IF(SUMPRODUCT(LEN(Q81:X81)-LEN(SUBSTITUTE(UPPER(Q81:X81),"CERTIFICATE","")))/11>0, SUMPRODUCT(LEN(Q81:X81)-LEN(SUBSTITUTE(UPPER(Q81:X81),"CERTIFICATE","")))/11 & " Certificates ", "") ), " ", ", ") -> KCSE, KCPE | V81: KCSE | W81: KCPE | Y81: Part Time Contract | Z81: Luhya
A82: 74 | B82: 75 | C82: 20190119343 | D82: Mr. Musau, Brian Mukeli | F82: 32487813 | G82: M | H82: 30 | I82: Fellowship - EL - M16XG | J82: KSRIC | K82: G | L82: 0 - Active | M82: 31/07/2025 | N82: 44205 | O82: Mr. Musau, Brian Mukeli | P82: =SUBSTITUTE(TRIM( IF(COUNTIF(Q82:X82, "*Philosophy*"), "PhD ", "") & IF(COUNTIF(Q82:X82, "*Master*"), "MSc ", "") & IF(COUNTIF(Q82:X82, "*Bachelor*"), "Bachelors ", "") & IF(COUNTIF(Q82:X82, "*Diploma*"), "Dip ", "") & IF(COUNTIF(Q82:X82, "*KCSE*"), "KCSE ", "") & IF(COUNTIF(Q82:X82, "*KCPE*"), "KCPE ", "") & IF(COUNTIF(Q82:X82, "*IHRM*"), "IHRM ", "") & IF(COUNTIF(Q82:X82, "*HRMPB*"), "HRMPB ", "") & IF(COUNTIF(Q82:X82, "*KISM*"), "KISM ", "") & IF(COUNTIF(Q82:X82, "*ICPAK*"), "ICPAK ", "") & IF(COUNTIF(Q82:X82, "*CPA*"), "CPA ", "") & IF(COUNTIF(Q82:X82, "*Strategic Leadership*"), "SLDP ", "") & IF(COUNTIF(Q82:X82, "*Senior Management*"), "SMC ", "") & IF(COUNTIF(Q82:X82, "*Nursing*"), "NCK ", "") & IF(COUNTIF(Q82:X82, "*KMLTTB*"), "KMLTTB ", "") & IF(COUNTIF(Q82:X82, "*Cstat*"), "Cstat ", "") & IF(SUMPRODUCT(LEN(Q82:X82)-LEN(SUBSTITUTE(UPPER(Q82:X82),"CERTIFICATE","")))/11>0, SUMPRODUCT(LEN(Q82:X82)-LEN(SUBSTITUTE(UPPER(Q82:X82),"CERTIFICATE","")))/11 & " Certificates ", "") ), " ", ", ") -> Bachelors, KCSE, KCPE, 1, Certificates | S82: Bachelor of Science Microbiology | U82: certificate in intoduction to biology | V82: KCSE | W82: KCPE | Y82: Part Time Contract | Z82: Kamba
A83: 75 | B83: 76 | C83: 20190641465 | D83: Mr. Musalia, Miheso Hannington | F83: 22231664 | G83: M | H83: 44 | I83: Fellowship - EL - M16XG | J83: KSRIC | K83: G | L83: 0 - Active | M83: 14/07/2025 | N83: 43471 | O83: Mr. Musalia, Miheso Hannington | P83: =SUBSTITUTE(TRIM( IF(COUNTIF(Q83:X83, "*Philosophy*"), "PhD ", "") & IF(COUNTIF(Q83:X83, "*Master*"), "MSc ", "") & IF(COUNTIF(Q83:X83, "*Bachelor*"), "Bachelors ", "") & IF(COUNTIF(Q83:X83, "*Diploma*"), "Dip ", "") & IF(COUNTIF(Q83:X83, "*KCSE*"), "KCSE ", "") & IF(COUNTIF(Q83:X83, "*KCPE*"), "KCPE ", "") & IF(COUNTIF(Q83:X83, "*IHRM*"), "IHRM ", "") & IF(COUNTIF(Q83:X83, "*HRMPB*"), "HRMPB ", "") & IF(COUNTIF(Q83:X83, "*KISM*"), "KISM ", "") & IF(COUNTIF(Q83:X83, "*ICPAK*"), "ICPAK ", "") & IF(COUNTIF(Q83:X83, "*CPA*"), "CPA ", "") & IF(COUNTIF(Q83:X83, "*Strategic Leadership*"), "SLDP ", "") & IF(COUNTIF(Q83:X83, "*Senior Management*"), "SMC ", "") & IF(COUNTIF(Q83:X83, "*Nursing*"), "NCK ", "") & IF(COUNTIF(Q83:X83, "*KMLTTB*"), "KMLTTB ", "") & IF(COUNTIF(Q83:X83, "*Cstat*"), "Cstat ", "") & IF(SUMPRODUCT(LEN(Q83:X83)-LEN(SUBSTITUTE(UPPER(Q83:X83),"CERTIFICATE","")))/11>0, SUMPRODUCT(LEN(Q83:X83)-LEN(SUBSTITUTE(UPPER(Q83:X83),"CERTIFICATE","")))/11 & " Certificates ", "") ), " ", ", ") -> Dip, KCSE, KCPE, 1, Certificates | T83: Diploma in Food Technology | U83: Certificate in Food Technology Processing and Preservation | V83: KCSE | W83: KCPE | Y83: Part Time Contract | Z83: Luhya
A84: 76 | B84: 77 | C84: 20210645977 | D84: Miss. Musabyimana, Valentine | F84: 782066 | G84: F | H84: 28 | I84: Fellowship - EL - M16XG | J84: KSRIC | K84: G | L84: 0 - Active | M84: 14/07/2025 | N84: 44205 | O84: Miss. Musabyimana, Valentine | P84: =SUBSTITUTE(TRIM( IF(COUNTIF(Q84:X84, "*Philosophy*"), "PhD ", "") & IF(COUNTIF(Q84:X84, "*Master*"), "MSc ", "") & IF(COUNTIF(Q84:X84, "*Bachelor*"), "Bachelors ", "") & IF(COUNTIF(Q84:X84, "*Diploma*"), "Dip ", "") & IF(COUNTIF(Q84:X84, "*KCSE*"), "KCSE ", "") & IF(COUNTIF(Q84:X84, "*KCPE*"), "KCPE ", "") & IF(COUNTIF(Q84:X84, "*IHRM*"), "IHRM ", "") & IF(COUNTIF(Q84:X84, "*HRMPB*"), "HRMPB ", "") & IF(COUNTIF(Q84:X84, "*KISM*"), "KISM ", "") & IF(COUNTIF(Q84:X84, "*ICPAK*"), "ICPAK ", "") & IF(COUNTIF(Q84:X84, "*CPA*"), "CPA ", "") & IF(COUNTIF(Q84:X84, "*Strategic Leadership*"), "SLDP ", "") & IF(COUNTIF(Q84:X84, "*Senior Management*"), "SMC ", "") & IF(COUNTIF(Q84:X84, "*Nursing*"), "NCK ", "") & IF(COUNTIF(Q84:X84, "*KMLTTB*"), "KMLTTB ", "") & IF(COUNTIF(Q84:X84, "*Cstat*"), "Cstat ", "") & IF(SUMPRODUCT(LEN(Q84:X84)-LEN(SUBSTITUTE(UPPER(Q84:X84),"CERTIFICATE","")))/11>0, SUMPRODUCT(LEN(Q84:X84)-LEN(SUBSTITUTE(UPPER(Q84:X84),"CERTIFICATE","")))/11 & " Certificates ", "") ), " ", ", ") -> Bachelors, Dip, KCSE, KCPE | S84: Bachelor of Science in Biology | T84: Diploma in Modern Humanities | V84: KCSE | W84: KCPE | Y84: Part Time Contract | Z84: other Kenyan
A85: 77 | B85: 78 | C85: 20210646046 | D85: Mr. Maalim, Hussein Abass | F85: 35337775 | G85: M | H85: 28 | I85: Fellowship - EL - M16XG | J85: KSRIC | K85: G | L85: 0 - Active | M85: 27/02/2026 | N85: 44355 | O85: Mr. Maalim, Hussein Abass | P85: =SUBSTITUTE(TRIM( IF(COUNTIF(Q85:X85, "*Philosophy*"), "PhD ", "") & IF(COUNTIF(Q85:X85, "*Master*"), "MSc ", "") & IF(COUNTIF(Q85:X85, "*Bachelor*"), "Bachelors ", "") & IF(COUNTIF(Q85:X85, "*Diploma*"), "Dip ", "") & IF(COUNTIF(Q85:X85, "*KCSE*"), "KCSE ", "") & IF(COUNTIF(Q85:X85, "*KCPE*"), "KCPE ", "") & IF(COUNTIF(Q85:X85, "*IHRM*"), "IHRM ", "") & IF(COUNTIF(Q85:X85, "*HRMPB*"), "HRMPB ", "") & IF(COUNTIF(Q85:X85, "*KISM*"), "KISM ", "") & IF(COUNTIF(Q85:X85, "*ICPAK*"), "ICPAK ", "") & IF(COUNTIF(Q85:X85, "*CPA*"), "CPA ", "") & IF(COUNTIF(Q85:X85, "*Strategic Leadership*"), "SLDP ", "") & IF(COUNTIF(Q85:X85, "*Senior Management*"), "SMC ", "") & IF(COUNTIF(Q85:X85, "*Nursing*"), "NCK ", "") & IF(COUNTIF(Q85:X85, "*KMLTTB*"), "KMLTTB ", "") & IF(COUNTIF(Q85:X85, "*Cstat*"), "Cstat ", "") & IF(SUMPRODUCT(LEN(Q85:X85)-LEN(SUBSTITUTE(UPPER(Q85:X85),"CERTIFICATE","")))/11>0, SUMPRODUCT(LEN(Q85:X85)-LEN(SUBSTITUTE(UPPER(Q85:X85),"CERTIFICATE","")))/11 & " Certificates ", "") ), " ", ", ") -> KCSE | V85: KCSE | W85: None | Y85: Part Time Contract | Z85: Somali-So-State
A86: 78 | B86: 79 | C86: 20210646062 | D86: Mr. Tiyo, Lawi Totana | F86: 11710039 | G86: M | H86: 51 | I86: Fellowship - EL - M16XG | J86: KSRIC | K86: G | L86: 0 - Active | M86: 27/02/2026 | N86: 44355 | O86: Mr. Tiyo, Lawi Totana | P86: =SUBSTITUTE(TRIM( IF(COUNTIF(Q86:X86, "*Philosophy*"), "PhD ", "") & IF(COUNTIF(Q86:X86, "*Master*"), "MSc ", "") & IF(COUNTIF(Q86:X86, "*Bachelor*"), "Bachelors ", "") & IF(COUNTIF(Q86:X86, "*Diploma*"), "Dip ", "") & IF(COUNTIF(Q86:X86, "*KCSE*"), "KCSE ", "") & IF(COUNTIF(Q86:X86, "*KCPE*"), "KCPE ", "") & IF(COUNTIF(Q86:X86, "*IHRM*"), "IHRM ", "") & IF(COUNTIF(Q86:X86, "*HRMPB*"), "HRMPB ", "") & IF(COUNTIF(Q86:X86, "*KISM*"), "KISM ", "") & IF(COUNTIF(Q86:X86, "*ICPAK*"), "ICPAK ", "") & IF(COUNTIF(Q86:X86, "*CPA*"), "CPA ", "") & IF(COUNTIF(Q86:X86, "*Strategic Leadership*"), "SLDP ", "") & IF(COUNTIF(Q86:X86, "*Senior Management*"), "SMC ", "") & IF(COUNTIF(Q86:X86, "*Nursing*"), "NCK ", "") & IF(COUNTIF(Q86:X86, "*KMLTTB*"), "KMLTTB ", "") & IF(COUNTIF(Q86:X86, "*Cstat*"), "Cstat ", "") & IF(SUMPRODUCT(LEN(Q86:X86)-LEN(SUBSTITUTE(UPPER(Q86:X86),"CERTIFICATE","")))/11>0, SUMPRODUCT(LEN(Q86:X86)-LEN(SUBSTITUTE(UPPER(Q86:X86),"CERTIFICATE","")))/11 & " Certificates ", "") ), " ", ", ") -> KCSE | V86: KCSE | W86: None | Y86: Part Time Contract | Z86: Maasai
A87: 79 | B87: 80 | C87: 20220598512 | D87: Miss. Saitoti, Anne Sein | F87: 29443115 | G87: F | H87: 32 | I87: Fellowship - EL - M16XG | J87: KSRIC | K87: G | L87: 0 - Active | M87: 02/01/2026 | N87: 44621 | O87: Miss. Saitoti, Anne Sein | P87: =SUBSTITUTE(TRIM( IF(COUNTIF(Q87:X87, "*Philosophy*"), "PhD ", "") & IF(COUNTIF(Q87:X87, "*Master*"), "MSc ", "") & IF(COUNTIF(Q87:X87, "*Bachelor*"), "Bachelors ", "") & IF(COUNTIF(Q87:X87, "*Diploma*"), "Dip ", "") & IF(COUNTIF(Q87:X87, "*KCSE*"), "KCSE ", "") & IF(COUNTIF(Q87:X87, "*KCPE*"), "KCPE ", "") & IF(COUNTIF(Q87:X87, "*IHRM*"), "IHRM ", "") & IF(COUNTIF(Q87:X87, "*HRMPB*"), "HRMPB ", "") & IF(COUNTIF(Q87:X87, "*KISM*"), "KISM ", "") & IF(COUNTIF(Q87:X87, "*ICPAK*"), "ICPAK ", "") & IF(COUNTIF(Q87:X87, "*CPA*"), "CPA ", "") & IF(COUNTIF(Q87:X87, "*Strategic Leadership*"), "SLDP ", "") & IF(COUNTIF(Q87:X87, "*Senior Management*"), "SMC ", "") & IF(COUNTIF(Q87:X87, "*Nursing*"), "NCK ", "") & IF(COUNTIF(Q87:X87, "*KMLTTB*"), "KMLTTB ", "") & IF(COUNTIF(Q87:X87, "*Cstat*"), "Cstat ", "") & IF(SUMPRODUCT(LEN(Q87:X87)-LEN(SUBSTITUTE(UPPER(Q87:X87),"CERTIFICATE","")))/11>0, SUMPRODUCT(LEN(Q87:X87)-LEN(SUBSTITUTE(UPPER(Q87:X87),"CERTIFICATE","")))/11 & " Certificates ", "") ), " ", ", ") -> Bachelors, KCSE, KCPE | S87: Bachelor of Science in Medical Microbiology | V87: KCSE | W87: KCPE | Y87: Part Time Contract | Z87: Maasai
A88: 80 | B88: 81 | C88: 20220598546 | D88: Mr. Parkurito, Stanley Leteipan | F88: 28484103 | G88: M | H88: 33 | I88: Fellowship - EL - M16XG | J88: KSRIC | K88: G | L88: 0 - Active | M88: 30/09/2025 | N88: 44621 | O88: Mr. Parkurito, Stanley Leteipan | P88: =SUBSTITUTE(TRIM( IF(COUNTIF(Q88:X88, "*Philosophy*"), "PhD ", "") & IF(COUNTIF(Q88:X88, "*Master*"), "MSc ", "") & IF(COUNTIF(Q88:X88, "*Bachelor*"), "Bachelors ", "") & IF(COUNTIF(Q88:X88, "*Diploma*"), "Dip ", "") & IF(COUNTIF(Q88:X88, "*KCSE*"), "KCSE ", "") & IF(COUNTIF(Q88:X88, "*KCPE*"), "KCPE ", "") & IF(COUNTIF(Q88:X88, "*IHRM*"), "IHRM ", "") & IF(COUNTIF(Q88:X88, "*HRMPB*"), "HRMPB ", "") & IF(COUNTIF(Q88:X88, "*KISM*"), "KISM ", "") & IF(COUNTIF(Q88:X88, "*ICPAK*"), "ICPAK ", "") & IF(COUNTIF(Q88:X88, "*CPA*"), "CPA ", "") & IF(COUNTIF(Q88:X88, "*Strategic Leadership*"), "SLDP ", "") & IF(COUNTIF(Q88:X88, "*Senior Management*"), "SMC ", "") & IF(COUNTIF(Q88:X88, "*Nursing*"), "NCK ", "") & IF(COUNTIF(Q88:X88, "*KMLTTB*"), "KMLTTB ", "") & IF(COUNTIF(Q88:X88, "*Cstat*"), "Cstat ", "") & IF(SUMPRODUCT(LEN(Q88:X88)-LEN(SUBSTITUTE(UPPER(Q88:X88),"CERTIFICATE","")))/11>0, SUMPRODUCT(LEN(Q88:X88)-LEN(SUBSTITUTE(UPPER(Q88:X88),"CERTIFICATE","")))/11 & " Certificates ", "") ), " ", ", ") -> Dip, KCSE, KCPE, NCK | T88: Diploma in Community Health Nursing | V88: KCSE | W88: KCPE | X88: Nursing Council Of Kenya | Y88: Part Time Contract | Z88: Maasai
A89: 81 | B89: 82 | C89: 20220598740 | D89: Mr. Oluoch, Ezekiel Adino | F89: 30866902 | G89: M | H89: 32 | I89: Fellowship - EL - M16XG | J89: KSRIC | K89: G | L89: 0 - Active | M89: 02/01/2026 | N89: 44621 | O89: Mr. Oluoch, Ezekiel Adino | P89: =SUBSTITUTE(TRIM( IF(COUNTIF(Q89:X89, "*Philosophy*"), "PhD ", "") & IF(COUNTIF(Q89:X89, "*Master*"), "MSc ", "") & IF(COUNTIF(Q89:X89, "*Bachelor*"), "Bachelors ", "") & IF(COUNTIF(Q89:X89, "*Diploma*"), "Dip ", "") & IF(COUNTIF(Q89:X89, "*KCSE*"), "KCSE ", "") & IF(COUNTIF(Q89:X89, "*KCPE*"), "KCPE ", "") & IF(COUNTIF(Q89:X89, "*IHRM*"), "IHRM ", "") & IF(COUNTIF(Q89:X89, "*HRMPB*"), "HRMPB ", "") & IF(COUNTIF(Q89:X89, "*KISM*"), "KISM ", "") & IF(COUNTIF(Q89:X89, "*ICPAK*"), "ICPAK ", "") & IF(COUNTIF(Q89:X89, "*CPA*"), "CPA ", "") & IF(COUNTIF(Q89:X89, "*Strategic Leadership*"), "SLDP ", "") & IF(COUNTIF(Q89:X89, "*Senior Management*"), "SMC ", "") & IF(COUNTIF(Q89:X89, "*Nursing*"), "NCK ", "") & IF(COUNTIF(Q89:X89, "*KMLTTB*"), "KMLTTB ", "") & IF(COUNTIF(Q89:X89, "*Cstat*"), "Cstat ", "") & IF(SUMPRODUCT(LEN(Q89:X89)-LEN(SUBSTITUTE(UPPER(Q89:X89),"CERTIFICATE","")))/11>0, SUMPRODUCT(LEN(Q89:X89)-LEN(SUBSTITUTE(UPPER(Q89:X89),"CERTIFICATE","")))/11 & " Certificates ", "") ), " ", ", ") -> Bachelors, Dip, KCSE, KCPE, 1, Certificates | S89: Bachelor of Education in Early Childhood Education | T89: Diploma in Early Childhood Education | U89: Certificate in Early Childhood Education | V89: KCSE | W89: KCPE | Y89: Part Time Contract | Z89: Luo
A90: 82 | B90: 83 | C90: 20220598839 | D90: Mr. Kephah, Geofrey Maranga | F90: 23065759 | G90: M | H90: 42 | I90: Curatorial Assistant [3] - EL - M16BG | J90: KSRIC | K90: G | L90: 0 - Active | M90: 31/12/2027 | N90: 42379 | O90: Mr. Kephah, Geofrey Maranga | P90: =SUBSTITUTE(TRIM( IF(COUNTIF(Q90:X90, "*Philosophy*"), "PhD ", "") & IF(COUNTIF(Q90:X90, "*Master*"), "MSc ", "") & IF(COUNTIF(Q90:X90, "*Bachelor*"), "Bachelors ", "") & IF(COUNTIF(Q90:X90, "*Diploma*"), "Dip ", "") & IF(COUNTIF(Q90:X90, "*KCSE*"), "KCSE ", "") & IF(COUNTIF(Q90:X90, "*KCPE*"), "KCPE ", "") & IF(COUNTIF(Q90:X90, "*IHRM*"), "IHRM ", "") & IF(COUNTIF(Q90:X90, "*HRMPB*"), "HRMPB ", "") & IF(COUNTIF(Q90:X90, "*KISM*"), "KISM ", "") & IF(COUNTIF(Q90:X90, "*ICPAK*"), "ICPAK ", "") & IF(COUNTIF(Q90:X90, "*CPA*"), "CPA ", "") & IF(COUNTIF(Q90:X90, "*Strategic Leadership*"), "SLDP ", "") & IF(COUNTIF(Q90:X90, "*Senior Management*"), "SMC ", "") & IF(COUNTIF(Q90:X90, "*Nursing*"), "NCK ", "") & IF(COUNTIF(Q90:X90, "*KMLTTB*"), "KMLTTB ", "") & IF(COUNTIF(Q90:X90, "*Cstat*"), "Cstat ", "") & IF(SUMPRODUCT(LEN(Q90:X90)-LEN(SUBSTITUTE(UPPER(Q90:X90),"CERTIFICATE","")))/11>0, SUMPRODUCT(LEN(Q90:X90)-LEN(SUBSTITUTE(UPPER(Q90:X90),"CERTIFICATE","")))/11 & " Certificates ", "") ), " ", ", ") -> Dip, KCSE, KCPE, 1, Certificates | T90: Diploma in Tour Guide and Administration | U90: Certificate in Tour Guiding and Administration | V90: KCSE | W90: KCPE | Y90: Local Contract | Z90: Kisii
A91: 83 | B91: 84 | C91: 20220598889 | D91: Ms. Mukweyi, Pamela Khasandi | F91: 25037835 | G91: F | H91: 37 | I91: Fellowship - EL - M16XG | J91: KSRIC | K91: G | L91: 0 - Active | M91: 02/01/2026 | N91: 44621 | O91: Ms. Mukweyi, Pamela Khasandi | P91: =SUBSTITUTE(TRIM( IF(COUNTIF(Q91:X91, "*Philosophy*"), "PhD ", "") & IF(COUNTIF(Q91:X91, "*Master*"), "MSc ", "") & IF(COUNTIF(Q91:X91, "*Bachelor*"), "Bachelors ", "") & IF(COUNTIF(Q91:X91, "*Diploma*"), "Dip ", "") & IF(COUNTIF(Q91:X91, "*KCSE*"), "KCSE ", "") & IF(COUNTIF(Q91:X91, "*KCPE*"), "KCPE ", "") & IF(COUNTIF(Q91:X91, "*IHRM*"), "IHRM ", "") & IF(COUNTIF(Q91:X91, "*HRMPB*"), "HRMPB ", "") & IF(COUNTIF(Q91:X91, "*KISM*"), "KISM ", "") & IF(COUNTIF(Q91:X91, "*ICPAK*"), "ICPAK ", "") & IF(COUNTIF(Q91:X91, "*CPA*"), "CPA ", "") & IF(COUNTIF(Q91:X91, "*Strategic Leadership*"), "SLDP ", "") & IF(COUNTIF(Q91:X91, "*Senior Management*"), "SMC ", "") & IF(COUNTIF(Q91:X91, "*Nursing*"), "NCK ", "") & IF(COUNTIF(Q91:X91, "*KMLTTB*"), "KMLTTB ", "") & IF(COUNTIF(Q91:X91, "*Cstat*"), "Cstat ", "") & IF(SUMPRODUCT(LEN(Q91:X91)-LEN(SUBSTITUTE(UPPER(Q91:X91),"CERTIFICATE","")))/11>0, SUMPRODUCT(LEN(Q91:X91)-LEN(SUBSTITUTE(UPPER(Q91:X91),"CERTIFICATE","")))/11 & " Certificates ", "") ), " ", ", ") -> Bachelors, KCSE, KCPE | S91: Bachelor of Science in Biotechnology | V91: KCSE | W91: KCPE | Y91: Part Time Contract | Z91: Luhya
A92: 84 | B92: 85 | C92: 20240090217 | D92: Mr.. Makuani, Dennis Kotti | F92: 33133984 | G92: M | H92: 30 | I92: Fellowship - EL - M16XG | J92: KSRIC | K92: G | L92: 0 - Active | M92: 31/05/2026 | N92: 45294 | O92: Mr.. Makuani, Dennis Kotti | P92: =SUBSTITUTE(TRIM( IF(COUNTIF(Q92:X92, "*Philosophy*"), "PhD ", "") & IF(COUNTIF(Q92:X92, "*Master*"), "MSc ", "") & IF(COUNTIF(Q92:X92, "*Bachelor*"), "Bachelors ", "") & IF(COUNTIF(Q92:X92, "*Diploma*"), "Dip ", "") & IF(COUNTIF(Q92:X92, "*KCSE*"), "KCSE ", "") & IF(COUNTIF(Q92:X92, "*KCPE*"), "KCPE ", "") & IF(COUNTIF(Q92:X92, "*IHRM*"), "IHRM ", "") & IF(COUNTIF(Q92:X92, "*HRMPB*"), "HRMPB ", "") & IF(COUNTIF(Q92:X92, "*KISM*"), "KISM ", "") & IF(COUNTIF(Q92:X92, "*ICPAK*"), "ICPAK ", "") & IF(COUNTIF(Q92:X92, "*CPA*"), "CPA ", "") & IF(COUNTIF(Q92:X92, "*Strategic Leadership*"), "SLDP ", "") & IF(COUNTIF(Q92:X92, "*Senior Management*"), "SMC ", "") & IF(COUNTIF(Q92:X92, "*Nursing*"), "NCK ", "") & IF(COUNTIF(Q92:X92, "*KMLTTB*"), "KMLTTB ", "") & IF(COUNTIF(Q92:X92, "*Cstat*"), "Cstat ", "") & IF(SUMPRODUCT(LEN(Q92:X92)-LEN(SUBSTITUTE(UPPER(Q92:X92),"CERTIFICATE","")))/11>0, SUMPRODUCT(LEN(Q92:X92)-LEN(SUBSTITUTE(UPPER(Q92:X92),"CERTIFICATE","")))/11 & " Certificates ", "") ), " ", ", ") -> Bachelors, Dip, KCSE, KCPE | S92: Bachelor of Science ( major Biology ) Biomedical Option | T92: Diploma in Technology ( Biochemistry) | V92: KCSE | W92: KCPE | Y92: Part Time Contract | Z92: Kamba
A93: 85 | B93: 86 | C93: 20240300939 | D93: Mr. Ngage, Tonny Onyango Ouma | F93: 32424642 | G93: M | H93: 30 | I93: Fellowship - EL - M16XG | J93: KSRIC | K93: G | L93: 0 - Active | M93: 31/07/2025 | N93: 16/07/2024 | O93: Mr. Ngage, Tonny Onyango Ouma | P93: =SUBSTITUTE(TRIM( IF(COUNTIF(Q93:X93, "*Philosophy*"), "PhD ", "") & IF(COUNTIF(Q93:X93, "*Master*"), "MSc ", "") & IF(COUNTIF(Q93:X93, "*Bachelor*"), "Bachelors ", "") & IF(COUNTIF(Q93:X93, "*Diploma*"), "Dip ", "") & IF(COUNTIF(Q93:X93, "*KCSE*"), "KCSE ", "") & IF(COUNTIF(Q93:X93, "*KCPE*"), "KCPE ", "") & IF(COUNTIF(Q93:X93, "*IHRM*"), "IHRM ", "") & IF(COUNTIF(Q93:X93, "*HRMPB*"), "HRMPB ", "") & IF(COUNTIF(Q93:X93, "*KISM*"), "KISM ", "") & IF(COUNTIF(Q93:X93, "*ICPAK*"), "ICPAK ", "") & IF(COUNTIF(Q93:X93, "*CPA*"), "CPA ", "") & IF(COUNTIF(Q93:X93, "*Strategic Leadership*"), "SLDP ", "") & IF(COUNTIF(Q93:X93, "*Senior Management*"), "SMC ", "") & IF(COUNTIF(Q93:X93, "*Nursing*"), "NCK ", "") & IF(COUNTIF(Q93:X93, "*KMLTTB*"), "KMLTTB ", "") & IF(COUNTIF(Q93:X93, "*Cstat*"), "Cstat ", "") & IF(SUMPRODUCT(LEN(Q93:X93)-LEN(SUBSTITUTE(UPPER(Q93:X93),"CERTIFICATE","")))/11>0, SUMPRODUCT(LEN(Q93:X93)-LEN(SUBSTITUTE(UPPER(Q93:X93),"CERTIFICATE","")))/11 & " Certificates ", "") ), " ", ", ") -> Bachelors, KCSE, KCPE | S93: Bachelor Of Arts (Anthropology) | V93: KCSE | W93: KCPE | Y93: Part Time Contract | Z93: Luo
A94: 86 | B94: 87 | C94: 20240300955 | D94: Mr. Arwa, Steven Wasonga | F94: 37415502 | G94: M | H94: 25 | I94: Fellowship - EL - M16XG | J94: KSRIC | K94: G | L94: 0 - Active | M94: 31/07/2025 | N94: 16/07/2024 | O94: Mr. Arwa, Steven Wasonga | P94: =SUBSTITUTE(TRIM( IF(COUNTIF(Q94:X94, "*Philosophy*"), "PhD ", "") & IF(COUNTIF(Q94:X94, "*Master*"), "MSc ", "") & IF(COUNTIF(Q94:X94, "*Bachelor*"), "Bachelors ", "") & IF(COUNTIF(Q94:X94, "*Diploma*"), "Dip ", "") & IF(COUNTIF(Q94:X94, "*KCSE*"), "KCSE ", "") & IF(COUNTIF(Q94:X94, "*KCPE*"), "KCPE ", "") & IF(COUNTIF(Q94:X94, "*IHRM*"), "IHRM ", "") & IF(COUNTIF(Q94:X94, "*HRMPB*"), "HRMPB ", "") & IF(COUNTIF(Q94:X94, "*KISM*"), "KISM ", "") & IF(COUNTIF(Q94:X94, "*ICPAK*"), "ICPAK ", "") & IF(COUNTIF(Q94:X94, "*CPA*"), "CPA ", "") & IF(COUNTIF(Q94:X94, "*Strategic Leadership*"), "SLDP ", "") & IF(COUNTIF(Q94:X94, "*Senior Management*"), "SMC ", "") & IF(COUNTIF(Q94:X94, "*Nursing*"), "NCK ", "") & IF(COUNTIF(Q94:X94, "*KMLTTB*"), "KMLTTB ", "") & IF(COUNTIF(Q94:X94, "*Cstat*"), "Cstat ", "") & IF(SUMPRODUCT(LEN(Q94:X94)-LEN(SUBSTITUTE(UPPER(Q94:X94),"CERTIFICATE","")))/11>0, SUMPRODUCT(LEN(Q94:X94)-LEN(SUBSTITUTE(UPPER(Q94:X94),"CERTIFICATE","")))/11 & " Certificates ", "") ), " ", ", ") -> Bachelors, KCSE, KCPE | S94: Bachelor of Science in Statistics | V94: KCSE | W94: KCPE | Y94: Part Time Contract | Z94: Luo
A95: 87 | B95: 88 | C95: 20240300971 | D95: Mr. Micheal, Evans Kisilu | F95: 39383066 | G95: M | H95: 23 | I95: Fellowship - EL - M16XG | J95: KSRIC | K95: G | L95: 0 - Active | M95: 30/11/2025 | N95: 45302 | O95: Mr. Micheal, Evans Kisilu | P95: =SUBSTITUTE(TRIM( IF(COUNTIF(Q95:X95, "*Philosophy*"), "PhD ", "") & IF(COUNTIF(Q95:X95, "*Master*"), "MSc ", "") & IF(COUNTIF(Q95:X95, "*Bachelor*"), "Bachelors ", "") & IF(COUNTIF(Q95:X95, "*Diploma*"), "Dip ", "") & IF(COUNTIF(Q95:X95, "*KCSE*"), "KCSE ", "") & IF(COUNTIF(Q95:X95, "*KCPE*"), "KCPE ", "") & IF(COUNTIF(Q95:X95, "*IHRM*"), "IHRM ", "") & IF(COUNTIF(Q95:X95, "*HRMPB*"), "HRMPB ", "") & IF(COUNTIF(Q95:X95, "*KISM*"), "KISM ", "") & IF(COUNTIF(Q95:X95, "*ICPAK*"), "ICPAK ", "") & IF(COUNTIF(Q95:X95, "*CPA*"), "CPA ", "") & IF(COUNTIF(Q95:X95, "*Strategic Leadership*"), "SLDP ", "") & IF(COUNTIF(Q95:X95, "*Senior Management*"), "SMC ", "") & IF(COUNTIF(Q95:X95, "*Nursing*"), "NCK ", "") & IF(COUNTIF(Q95:X95, "*KMLTTB*"), "KMLTTB ", "") & IF(COUNTIF(Q95:X95, "*Cstat*"), "Cstat ", "") & IF(SUMPRODUCT(LEN(Q95:X95)-LEN(SUBSTITUTE(UPPER(Q95:X95),"CERTIFICATE","")))/11>0, SUMPRODUCT(LEN(Q95:X95)-LEN(SUBSTITUTE(UPPER(Q95:X95),"CERTIFICATE","")))/11 & " Certificates ", "") ), " ", ", ") -> Bachelors, KCSE, KCPE | S95: Bachelor of Veterinary Medicine | V95: KCSE | W95: KCPE | Y95: Part Time Contract | Z95: Kamba
A96: 88 | B96: 89 | C96: 20250008018 | D96: Mrs. Ngugi, Cecilia Wangui | F96: 38290848 | G96: F | H96: 23 | I96: Fellowship - EL - M16XG | J96: KSRIC | K96: G | L96: 0 - Active | M96: 31/01/2026 | N96: 45659 | O96: Mrs. Ngugi, Cecilia Wangui | P96: =SUBSTITUTE(TRIM( IF(COUNTIF(Q96:X96, "*Philosophy*"), "PhD ", "") & IF(COUNTIF(Q96:X96, "*Master*"), "MSc ", "") & IF(COUNTIF(Q96:X96, "*Bachelor*"), "Bachelors ", "") & IF(COUNTIF(Q96:X96, "*Diploma*"), "Dip ", "") & IF(COUNTIF(Q96:X96, "*KCSE*"), "KCSE ", "") & IF(COUNTIF(Q96:X96, "*KCPE*"), "KCPE ", "") & IF(COUNTIF(Q96:X96, "*IHRM*"), "IHRM ", "") & IF(COUNTIF(Q96:X96, "*HRMPB*"), "HRMPB ", "") & IF(COUNTIF(Q96:X96, "*KISM*"), "KISM ", "") & IF(COUNTIF(Q96:X96, "*ICPAK*"), "ICPAK ", "") & IF(COUNTIF(Q96:X96, "*CPA*"), "CPA ", "") & IF(COUNTIF(Q96:X96, "*Strategic Leadership*"), "SLDP ", "") & IF(COUNTIF(Q96:X96, "*Senior Management*"), "SMC ", "") & IF(COUNTIF(Q96:X96, "*Nursing*"), "NCK ", "") & IF(COUNTIF(Q96:X96, "*KMLTTB*"), "KMLTTB ", "") & IF(COUNTIF(Q96:X96, "*Cstat*"), "Cstat ", "") & IF(SUMPRODUCT(LEN(Q96:X96)-LEN(SUBSTITUTE(UPPER(Q96:X96),"CERTIFICATE","")))/11>0, SUMPRODUCT(LEN(Q96:X96)-LEN(SUBSTITUTE(UPPER(Q96:X96),"CERTIFICATE","")))/11 & " Certificates ", "") ), " ", ", ") -> Dip, KCSE, KCPE, NCK | T96: Diploma in Registered Nursing | V96: KCSE | W96: KCPE | X96: Nursing Council Of Kenya | Y96: Part Time Contract | Z96: Kikuyu
A97: 90 | B97: 90 | C97: 20250067339 | D97: Miss. Fiona Kanana Kimathi | F97: 40031044 | G97: F | I97: Fellowship - EL - M16XG | J97: KSRIC | K97: G | L97: 0 - Active | M97: 30/04/2026 | N97: 45693 | O97: Miss. Fiona Kanana Kimathi | P97: =SUBSTITUTE(TRIM( IF(COUNTIF(Q97:X97, "*Philosophy*"), "PhD ", "") & IF(COUNTIF(Q97:X97, "*Master*"), "MSc ", "") & IF(COUNTIF(Q97:X97, "*Bachelor*"), "Bachelors ", "") & IF(COUNTIF(Q97:X97, "*Diploma*"), "Dip ", "") & IF(COUNTIF(Q97:X97, "*KCSE*"), "KCSE ", "") & IF(COUNTIF(Q97:X97, "*KCPE*"), "KCPE ", "") & IF(COUNTIF(Q97:X97, "*IHRM*"), "IHRM ", "") & IF(COUNTIF(Q97:X97, "*HRMPB*"), "HRMPB ", "") & IF(COUNTIF(Q97:X97, "*KISM*"), "KISM ", "") & IF(COUNTIF(Q97:X97, "*ICPAK*"), "ICPAK ", "") & IF(COUNTIF(Q97:X97, "*CPA*"), "CPA ", "") & IF(COUNTIF(Q97:X97, "*Strategic Leadership*"), "SLDP ", "") & IF(COUNTIF(Q97:X97, "*Senior Management*"), "SMC ", "") & IF(COUNTIF(Q97:X97, "*Nursing*"), "NCK ", "") & IF(COUNTIF(Q97:X97, "*KMLTTB*"), "KMLTTB ", "") & IF(COUNTIF(Q97:X97, "*Cstat*"), "Cstat ", "") & IF(SUMPRODUCT(LEN(Q97:X97)-LEN(SUBSTITUTE(UPPER(Q97:X97),"CERTIFICATE","")))/11>0, SUMPRODUCT(LEN(Q97:X97)-LEN(SUBSTITUTE(UPPER(Q97:X97),"CERTIFICATE","")))/11 & " Certificates ", "") ), " ", ", ") -> Bachelors, KCSE, KCPE | S97: Bachelor of Science in Public Health | V97: KCSE | W97: KCPE | Y97: Part Time Contract | Z97: Meru
F98: LIBRARY | P98: =SUBSTITUTE(TRIM( IF(COUNTIF(Q98:X98, "*Philosophy*"), "PhD ", "") & IF(COUNTIF(Q98:X98, "*Master*"), "MSc ", "") & IF(COUNTIF(Q98:X98, "*Bachelor*"), "Bachelors ", "") & IF(COUNTIF(Q98:X98, "*Diploma*"), "Dip ", "") & IF(COUNTIF(Q98:X98, "*KCSE*"), "KCSE ", "") & IF(COUNTIF(Q98:X98, "*KCPE*"), "KCPE ", "") & IF(COUNTIF(Q98:X98, "*IHRM*"), "IHRM ", "") & IF(COUNTIF(Q98:X98, "*HRMPB*"), "HRMPB ", "") & IF(COUNTIF(Q98:X98, "*KISM*"), "KISM ", "") & IF(COUNTIF(Q98:X98, "*ICPAK*"), "ICPAK ", "") & IF(COUNTIF(Q98:X98, "*CPA*"), "CPA ", "") & IF(COUNTIF(Q98:X98, "*Strategic Leadership*"), "SLDP ", "") & IF(COUNTIF(Q98:X98, "*Senior Management*"), "SMC ", "") & IF(COUNTIF(Q98:X98, "*Nursing*"), "NCK ", "") & IF(COUNTIF(Q98:X98, "*KMLTTB*"), "KMLTTB ", "") & IF(COUNTIF(Q98:X98, "*Cstat*"), "Cstat ", "") & IF(SUMPRODUCT(LEN(Q98:X98)-LEN(SUBSTITUTE(UPPER(Q98:X98),"CERTIFICATE","")))/11>0, SUMPRODUCT(LEN(Q98:X98)-LEN(SUBSTITUTE(UPPER(Q98:X98),"CERTIFICATE","")))/11 & " Certificates ", "") ), " ", ", ")
A99: 91 | B99: 91 | C99: 20152655585 | D99: Mrs. Wafula, Dinah Nanjala | F99: 26673037 | G99: F | H99: 36 | I99: Librarian [2] - EL - M05AK | J99: Library | K99: K | L99: 0 - Active | M99: 05/08/2048 | N99: 42221 | O99: Mrs. Wafula, Dinah Nanjala | P99: =SUBSTITUTE(TRIM( IF(COUNTIF(Q99:X99, "*Philosophy*"), "PhD ", "") & IF(COUNTIF(Q99:X99, "*Master*"), "MSc ", "") & IF(COUNTIF(Q99:X99, "*Bachelor*"), "Bachelors ", "") & IF(COUNTIF(Q99:X99, "*Diploma*"), "Dip ", "") & IF(COUNTIF(Q99:X99, "*KCSE*"), "KCSE ", "") & IF(COUNTIF(Q99:X99, "*KCPE*"), "KCPE ", "") & IF(COUNTIF(Q99:X99, "*IHRM*"), "IHRM ", "") & IF(COUNTIF(Q99:X99, "*HRMPB*"), "HRMPB ", "") & IF(COUNTIF(Q99:X99, "*KISM*"), "KISM ", "") & IF(COUNTIF(Q99:X99, "*ICPAK*"), "ICPAK ", "") & IF(COUNTIF(Q99:X99, "*CPA*"), "CPA ", "") & IF(COUNTIF(Q99:X99, "*Strategic Leadership*"), "SLDP ", "") & IF(COUNTIF(Q99:X99, "*Senior Management*"), "SMC ", "") & IF(COUNTIF(Q99:X99, "*Nursing*"), "NCK ", "") & IF(COUNTIF(Q99:X99, "*KMLTTB*"), "KMLTTB ", "") & IF(COUNTIF(Q99:X99, "*Cstat*"), "Cstat ", "") & IF(SUMPRODUCT(LEN(Q99:X99)-LEN(SUBSTITUTE(UPPER(Q99:X99),"CERTIFICATE","")))/11>0, SUMPRODUCT(LEN(Q99:X99)-LEN(SUBSTITUTE(UPPER(Q99:X99),"CERTIFICATE","")))/11 & " Certificates ", "") ), " ", ", ") -> Bachelors, KCSE, KCPE | S99: Bachelor of Arts in Information Studies | V99: KCSE | W99: KCPE | Y99: Permanent | Z99: Luhya
A100: 92 | B100: 92 | C100: 20160708685 | D100: Mr. Ongata, Evans NickOwuor | F100: 27758071 | G100: M | H100: 34 | I100: Clerical Officer - EL - T03AG | J100: Library | K100: G | L100: 0 - Active | M100: 30/09/2025 | N100: 42500 | O100: Mr. Ongata, Evans NickOwuor | P100: =SUBSTITUTE(TRIM( IF(COUNTIF(Q100:X100, "*Philosophy*"), "PhD ", "") & IF(COUNTIF(Q100:X100, "*Master*"), "MSc ", "") & IF(COUNTIF(Q100:X100, "*Bachelor*"), "Bachelors ", "") & IF(COUNTIF(Q100:X100, "*Diploma*"), "Dip ", "") & IF(COUNTIF(Q100:X100, "*KCSE*"), "KCSE ", "") & IF(COUNTIF(Q100:X100, "*KCPE*"), "KCPE ", "") & IF(COUNTIF(Q100:X100, "*IHRM*"), "IHRM ", "") & IF(COUNTIF(Q100:X100, "*HRMPB*"), "HRMPB ", "") & IF(COUNTIF(Q100:X100, "*KISM*"), "KISM ", "") & IF(COUNTIF(Q100:X100, "*ICPAK*"), "ICPAK ", "") & IF(COUNTIF(Q100:X100, "*CPA*"), "CPA ", "") & IF(COUNTIF(Q100:X100, "*Strategic Leadership*"), "SLDP ", "") & IF(COUNTIF(Q100:X100, "*Senior Management*"), "SMC ", "") & IF(COUNTIF(Q100:X100, "*Nursing*"), "NCK ", "") & IF(COUNTIF(Q100:X100, "*KMLTTB*"), "KMLTTB ", "") & IF(COUNTIF(Q100:X100, "*Cstat*"), "Cstat ", "") & IF(SUMPRODUCT(LEN(Q100:X100)-LEN(SUBSTITUTE(UPPER(Q100:X100),"CERTIFICATE","")))/11>0, SUMPRODUCT(LEN(Q100:X100)-LEN(SUBSTITUTE(UPPER(Q100:X100),"CERTIFICATE","")))/11 & " Certificates ", "") ), " ", ", ") -> KCSE, KCPE | V100: KCSE | W100: KCPE | Y100: Local Contract | Z100: Luo
...

Sheet Sheet2
A1: S/No. | B1: #NAME? | C1: Payroll Number | D1: Full Name | E1: ID Number | F1: Gender | G1: Age | H1: Designation | I1: Department | J1: Job Group | K1: Employment Status | L1: ROD | M1: Qualification | N1: Terms of Employment | O1: Ethnicity
D2: ADMINISTRATION & HUMAN RESOURCE
A3: 1 | B3: 1 | C3: 19901899045 | D3: Dr. Mwethera, Peter Gichuhi | E3: 3731123 | F3: M | G3: 61 | H3: Director General - EL - C01AT | I3: Reproductive Health & Biology | J3: T | K3: 0 - Active | L3: 01/09/2029 | M3: PhD | N3: Local Contract | O3: Kikuyu
A4: 2 | B4: 2 | C4: 19990495773 | D4: Mrs. Hassan, Hamida Adam | E4: 12701644 | F4: F | G4: 50 | H4: Senior Personal Assistant - EL - T02AN | I4: Administration & HR | J4: N | K4: 0 - Active | L4: 14/08/2034 | M4: Higher Diploma | N4: Permanent | O4: Luhya
A5: 3 | B5: 3 | C5: 20114215626 | D5: Mr. Manene, Patrick Kimathi | E5: 13361887 | F5: M | G5: 53 | H5: Administrative Officer [1] - EL - C01AN | I5: Administration & HR | J5: N | K5: 0 - Active | L5: 05/04/2032 | M5: Masters | N5: Permanent | O5: Meru
A6: 4 | B6: 4 | C6: 19990495650 | D6: Ms. Ondiba, Stella Nyamorambo | E6: 13819220 | F6: F | G6: 49 | H6: Human Resource Officer [1] - EL - C04AN | I6: Planning & Strategy | J6: N | K6: 0 - Active | L6: 05/06/2035 | M6: Masters | N6: Permanent | O6: Kisii
A7: 5 | B7: 5 | C7: 20160708902 | D7: Mr. Ochien'g, Zaddock Ojall | E7: 24938714 | F7: M | G7: 38 | H7: Administrative Officer [3] - EL - C01AL | I7: Administration & HR | J7: L | K7: 0 - Active | L7: 31/07/2027 | M7: Degree | N7: Local Contract | O7: Luo
A8: 6 | B8: 6 | C8: 20220598180 | D8: Mr. Owuor, John Robert | E8: 31860798 | F8: M | G8: 30 | H8: Human Resource Officer [3] - EL - C04AL | I8: Administration & HR | J8: L | K8: 0 - Active | L8: 30/01/2028 | M8: Degree | N8: Local Contract | O8: Luo
A9: 7 | B9: 7 | C9: 19990495812 | D9: Ms. Rotich, Celestine Jepkoech | E9: 20257607 | F9: F | G9: 48 | H9: Librarian [2] - EL - M05AK | I9: Administration & HR | J9: K | K9: 0 - Active | L9: 27/11/2036 | M9: Diploma | N9: Permanent | O9: Kalenjin
A10: 8 | B10: 8 | C10: 20121211099 | D10: Mr. Kioko, Prester Kitonga | E10: 13783232 | F10: M | G10: 50 | H10: Higher Clerical Officer - EL - T03AH | I10: Public Relations & Marketing | J10: H | K10: 0 - Active | L10: 24/02/2035 | M10: O-Level | N10: Permanent | O10: Kamba
A11: 9 | B11: 9 | C11: 20077018333 | D11: Mrs. Muthoni, Elizabeth Ng'ang'a | E11: 10998397 | F11: F | G11: 53 | H11: Telephone Officer [1] - EL - M09AJ | I11: Administration & HR | J11: J | K11: 0 - Active | L11: 19/12/2031 | M11: A-Level | N11: Permanent | O11: Kikuyu
A12: 10 | B12: 10 | C12: 20077018202 | D12: Ms. Lithira, Sabina Nkoyai | E12: 13133273 | F12: F | G12: 51 | H12: Telephone Officer [2] - EL - M09AH | I12: Administration & HR | J12: H | K12: 0 - Active | L12: 27/08/2033 | M12: O-Level | N12: Permanent | O12: Meru
A13: 11 | B13: 11 | C13: 20220598130 | D13: Miss. Koech, Beatrice Chebet | E13: 35698228 | F13: F | G13: 27 | H13: Office Assistant [2] - EL - T04DH | I13: Administration & HR | J13: H | K13: 0 - Active | L13: 30/01/2028 | M13: Form iv | N13: Local Contract | O13: Kalenjin
A14: 12 | B14: 12 | C14: 20077018391 | D14: Mrs. Kassim, Kulthum Mohamed | E14: 11625899 | F14: F | G14: 52 | H14: Clerical Officer - EL - T03AG | I14: Administration & HR | J14: G | K14: 0 - Active | L14: 30/04/2032 | M14: Diploma | N14: Permanent | O14: Bajun
A15: 13 | B15: 13 | C15: 20240300989 | D15: Miss. Opanga, Brenda Kwamboka | E15: 36675697 | F15: F | G15: 26 | H15: Clerical Officer - EL - T03AG | I15: Administration & HR | J15: G | K15: 0 - Active | L15: 22/01/2028 | M15: O-Level | N15: Local Contract | O15: Kisii
E16: ANIMANL SCIENCE WELFARE & ETHICS
A17: 14 | B17: 14 | C17: 19871318408 | D17: Dr. Chivatsi, Chai Daniel | E17: 5336502 | F17: M | G17: 65 | H17: Chief Veterinary Officer - EL - H04AQ | I17: Animal Science &Welfare ethics | J17: Q | K17: 0 - Active | L17: 01/07/2025 | M17: PhD | N17: Permanent | O17: Mijikenda
A18: 15 | B18: 15 | C18: 20077017769 | D18: Mrs. Akinyi, Mercy Yvonne | E18: 21963939 | F18: F | G18: 44 | H18: Senior Research Scientist [2] - ET - R01AP | I18: Animal Science &Welfare ethics | J18: P | K18: 0 - Active | L18: 30/01/2051 | M18: PhD | N18: Permanent | O18: Luo
A19: 16 | B19: 16 | C19: 20030731445 | D19: Mr. Kariuki, Kenneth Waititu | E19: 20742989 | F19: M | G19: 47 | H19: Senior Laboratory Technologist - EL - L07CM | I19: Animal Science &Welfare ethics | J19: M | K19: 0 - Active | L19: 09/10/2037 | M19: Masters | N19: Permanent | O19: Kikuyu
A20: 17 | B20: 17 | C20: 20178600817 | D20: Mr. Nashon, Wanjala Wavumbah | E20: 28951215 | F20: M | G20: 33 | H20: Veterinary Officer - EL - H04AM | I20: Animal Science &Welfare ethics | J20: M | K20: 0 - Active | L20: 30/11/2027 | M20: Masters | N20: Local Contract | O20: Luhya
A21: 18 | B21: 18 | C21: 20178600833 | D21: Mrs. Mwadime, Janet Mghambi | E21: 28189079 | F21: F | G21: 34 | H21: Veterinary Officer - EL - H04AM | I21: Animal Science &Welfare ethics | J21: M | K21: 0 - Active | L21: 30/11/2027 | M21: Masters | N21: Local Contract | O21: Taita
A22: 19 | B22: 19 | C22: 20010746137 | D22: Mrs. Kavurani, Rose Owino | E22: 13634152 | F22: F | G22: 49 | H22: Animal Health Technologist [1] - EL - H03FL | I22: Animal Science &Welfare ethics | J22: L | K22: 0 - Active | L22: 20/12/2035 | M22: Degree | N22: Permanent | O22: Luhya
A23: 20 | B23: 20 | C23: 20220597833 | D23: Mrs. Woche, Fatuma Galgalo | E23: 34811881 | F23: F | G23: 28 | H23: Assistant Research Scientist - EL - R01BL | I23: Animal Science &Welfare ethics | J23: L | K23: 0 - Active | L23: 30/01/2028 | M23: Degree | N23: Local Contract | O23: Burji
A24: 21 | B24: 21 | C24: 20089224039 | D24: Ms. Kimiti, Priscila Wangari | E24: 22245948 | F24: F | G24: 46 | H24: Senior Animal Health Assistant - EL - H03EJ | I24: Animal Science &Welfare ethics | J24: J | K24: 0 - Active | L24: 06/07/2038 | M24: Diploma | N24: Permanent | O24: Kikuyu
A25: 22 | B25: 22 | C25: 20114215537 | D25: Mr. Adino, Thomas Agutu | E25: 10344158 | F25: M | G25: 55 | H25: Senior Animal Health Assistant - EL - H03EJ | I25: Animal Science &Welfare ethics | J25: J | K25: 0 - Active | L25: 22/07/2029 | M25: Degree | N25: Permanent | O25: Luo
A26: 23 | B26: 23 | C26: 20142576250 | D26: Ms. Jerono, Caroline | E26: 26426983 | F26: F | G26: 36 | H26: Laboratory Technologist [3] - EL - L07CJ | I26: Animal Science &Welfare ethics | J26: J | K26: 0 - Active | L26: 09/05/2048 | M26: Degree | N26: Permanent | O26: Kalenjin
A27: 24 | B27: 24 | C27: 20152655226 | D27: Mr. Omondi, Hillary Ochieng | E27: 25584197 | F27: M | G27: 37 | H27: Senior Animal Health Assistant - EL - H03EJ | I27: Animal Science &Welfare ethics | J27: J | K27: 0 - Active | L27: 30/06/2025 | M27: Diploma | N27: Local Contract | O27: Luo
A28: 25 | B28: 25 | C28: 20178600980 | D28: Ms. Kigen, Daisy Jebet | E28: 22538194 | F28: F | G28: 44 | H28: Senior Animal Health Assistant - EL - H03EJ | I28: Animal Science &Welfare ethics | J28: J | K28: 0 - Active | L28: 01/05/2027 | M28: Diploma | N28: Local Contract | O28: Kalenjin
... A39: 36 | B39: 36 | C39: 20250011100 | D39: Mr. Momanyi, Sam Ocharo | E39: 32277442 | F39: M | G39: 31 | H39: Fellowship - EL - M16XG | I39: Animal Science &Welfare ethics | J39: G | K39: 0 - Active | L39: 28/02/2026 | M39: Degree | N39: Part Time Contract | O39: Kisii
A40: 37 | B40: 37 | C40: 20250067282 | D40: Hannah Ndiko Waweru | E40: 12925801 | F40: F | G40: 49 | H40: Animal Health Assistant 11 | I40: Animal Science &Welfare ethics | J40: G | K40: 0 - Active | L40: 46757 | M40: O-Level | N40: Local Contract | O40: Kikuyu
A41: 38 | B41: 38 | C41: 20250089145 | D41: Collins Kivuva Kioko | E41: 37906155 | F41: M | G41: 25 | H41: Animal Health Assistant 11 | I41: Animal Science &Welfare ethics | J41: G | K41: 0 - Active | L41: 46757 | M41: O-Level | N41: Local Contract | O41: Kamba
A42: 39 | B42: 39 | C42: 20250067266 | D42: Daniel Obondi Morara | E42: 40223884 | F42: M | G42: 22 | H42: Animal Health Assistant 11 | I42: Animal Science &Welfare ethics | J42: G | K42: 0 - Active | L42: 46757 | M42: O-Level | N42: Local Contract | O42: Kisii
A43: 40 | B43: 40 | C43: 20060933849 | D43: Mr. Gichuhi, Jaffer Ibrahim | E43: 21717357 | F43: M | G43: 46 | H43: Auxiliary staff [1] - EL - T04CF | I43: Animal Science &Welfare ethics | J43: F | K43: 0 - Active | L43: 06/07/2038 | M43: O-Level | N43: Permanent | O43: Kikuyu
A44: 41 | B44: 41 | C44: 20121211057 | D44: Mr. Kengo, Isaac Nduka | E44: 10164110 | F44: M | G44: 56 | H44: Animal Health Assistant [3] - EL - H03EF | I44: Animal Science &Welfare ethics | J44: F | K44: 0 - Active | L44: 16/07/2028 | M44: O-Level | N44: Permanent | O44: Luhya
A45: 42 | B45: 42 | C45: 20142576234 | D45: Ms. Korir, Gladys Chepkemoi | E45: 26041520 | F45: F | G45: 36 | H45: Animal Health Assistant [3] - EL - H03EF | I45: Animal Science &Welfare ethics | J45: F | K45: 0 - Active | L45: 25/12/2048 | M45: O-Level | N45: Permanent | O45: Kalenjin
A46: 43 | B46: 43 | C46: 20250067274 | D46: Hillary Kadende Masiva | E46: 39582151 | F46: M | G46: 22 | H46: Animal Health Assistant 11 | I46: Reproductive Health & Biology | J46: G | K46: 0 - Active | L46: 46757 | M46: O-Level | N46: Local Contract | O46: Luhya
A47: 44 | B47: 44 | C47: 20250089137 | D47: Kennedy Mwangi Kamande | E47: 29388325 | F47: M | G47: 32 | H47: Animal Health Assistant 11 | I47: Reproductive Health & Biology | J47: G | K47: 0 - Active | L47: 46757 | M47: O-Level | N47: Local Contract | O47: Kikuyu
E48: CONSERVATION & ECOLOGY
A49: 45 | B49: 45 | C49: 20077018228 | D49: Mr. Kivai, Stanslaus Mulu | E49: 20503322 | F49: M | G49: 48 | H49: Senior Research Scientist [1] - ET - R01AQ | I49: Conservation & Ecology | J49: Q | K49: 0 - Active | L49: 06/11/2046 | M49: PhD | N49: Permanent | O49: Kamba
A50: 46 | B50: 46 | C50: 20190119450 | D50: Ms. Otoli, Pauline Muranditsi | E50: 28782265 | F50: F | G50: 33 | H50: Assistant Research Scientist - EL - R01BL | I50: Conservation & Ecology | J50: L | K50: 0 - Active | L50: 31/12/2027 | M50: Degree | N50: Local Contract | O50: Luhya
A51: 47 | B51: 47 | C51: 20152655365 | D51: Ms. Okero, Caroline Achieng' | E51: 25138933 | F51: F | G51: 39 | H51: Human Resource Assistant [2] - EL - C04BJ | I51: Conservation & Ecology | J51: J | K51: 0 - Active | L51: 30/06/2025 | M51: Diploma | N51: Local Contract | O51: Luo
A52: 48 | B52: 48 | C52: 19920654357 | D52: Mr. Nguli, Jonathan Ngalatu | E52: 9225573 | F52: M | G52: 57 | H52: Animal Health Assistant [1] - EL - H03EH | I52: Conservation & Ecology | J52: H | K52: 0 - Active | L52: 31/12/2027 | M52: A-Level | N52: Permanent | O52: kamba
A53: 49 | B53: 49 | C53: 20250007868 | D53: Mr. Maingi, Charles Kivasu | E53: 26449205 | F53: M | G53: 37 | H53: Fellowship - EL - M16XG | I53: Conservation & Ecology | J53: G | K53: 0 - Active | L53: 31/12/2025 | M53: Masters | N53: Part Time Contract | O53: kamba
A54: 50 | B54: 50 | C54: 20250007931 | D54: Mr. Wambua, Tony Muisyo | E54: 33308998 | F54: M | G54: 29 | H54: Fellowship - EL - M16XG | I54: Conservation & Ecology | J54: G | K54: 0 - Active | L54: 28/02/2026 | M54: Degree | N54: Part Time Contract | O54: Kamba
A55: 51 | B55: 51 | C55: 20250011215 | D55: Ms. Mbugua, Joyce Wairimu | E55: 31592937 | F55: F | G55: 30 | H55: Fellowship - EL - M16XG | I55: Conservation & Ecology | J55: G | K55: 0 - Active | L55: 31/12/2025 | M55: Degree | N55: Part Time Contract | O55: Kikuyu
A56: 52 | B56: 52 | C56: 20250118499 | D56: Miss. Ruth Wambui Mburu | E56: 39029408 | F56: F | G56: 24 | H56: Fellowship - EL - M16XG | I56: Conservation & Ecology | J56: G | K56: 0 - Active | L56: 30/04/2026 | M56: Degree | N56: Part Time Contract | O56: Kikuyu
A57: 53 | B57: 53 | C57: 20240036700 | D57: Balozi Lekaso | E57: 36558749 | F57: M | G57: 26 | H57: Fellowship - EL - M16XG | I57: Conservation & Ecology | J57: G | K57: 0 - Active | L57: 30/04/2026 | M57: Degree | N57: Part Time Contract | O57: Samburu
A58: 54 | B58: 54 | C58: 20190118631 | D58: Paxton Kabasa Mugamangi | E58: 30101934 | F58: M | G58: 31 | H58: Fellowship - EL - M16XG | I58: Conservation & Ecology | J58: G | K58: 0 - Active | L58: 31/12/2025 | M58: Degree | N58: Part Time Contract | O58: Luhya
E59: FINANCE & ACCOUNTING
A60: 55 | B60: 55 | C60: 19920654373 | D60: Mr. Mohamed, Salla Daudi | E60: 8735350 | F60: M | G60: 58 | H60: Principal Accountant - EL - D01AP | I60: Finance & Accounting | J60: P | K60: 0 - Active | L60: 06/09/2026 | M60: Masters/CPAK | N60: Permanent | O60: Burji
A61: 56 | B61: 56 | C61: 20095593234 | D61: Mrs. Njogu, Esther Mukami | E61: 25394414 | F61: F | G61: 36 | H61: Principal Accountant - EL - D01AP | I61: Finance & Accounting | J61: P | K61: 0 - Active | L61: 27/05/2048 | M61: Masters | N61: Permanent | O61: Kikuyu
A62: 57 | B62: 57 | C62: 19930980988 | D62: Mr. Kahethu, Francis Kariuki | E62: 8107003 | F62: M | G62: 58 | H62: Accountant [1] - EL - D01AM | I62: Finance & Accounting | J62: M | K62: 0 - Active | L62: 01/12/2026 | M62: A-Level | N62: Permanent | O62: kikuyu
A63: 58 | B63: 58 | C63: 20181472524 | D63: Ms. Musyoka, Cecilia Ndethya | E63: 24146874 | F63: F | G63: 40 | H63: Accountant [2] - EL - D01AL | I63: Finance & Accounting | J63: L | K63: 0 - Active | L63: 31/12/2027 | M63: Degree | N63: Local Contract | O63: Kamba
A64: 59 | B64: 59 | C64: 20240300890 | D64: Mr. Mwaniki, Samuel Macharia | E64: 37963481 | F64: M | G64: 25 | H64: Auditor [1] - EL - D07AL | I64: Finance & Accounting | J64: L | K64: 0 - Active | L64: 46883 | M64: Degree | N64: Local Contract | O64: Kikuyu
A65: 60 | B65: 60 | C65: 20250067240 | D65: Sylvia mercy Abere | E65: 36697114 | F65: F | G65: 26 | H65: Accountant 11 | I65: Finance & Accounting | J65: L | K65: 0 - Active | L65: 46757 | M65: Degree | N65: Local Contract | O65: Kisii
A66: 61 | B66: 61 | C66: 20250067232 | D66: Lewis Gitonga Nyaga | E66: 33381959 | F66: M | G66: 29 | H66: Accountant 11 | I66: Finance & Accounting | J66: L | K66: 0 - Active | L66: 46757 | M66: Degree | N66: Local Contract | O66: Embu
A67: 62 | B67: 62 | C67: 20250067258 | D67: Janet Wanjui Kinyua | E67: 39000494 | F67: F | G67: 23 | H67: Accountant 11 | I67: Finance & Accounting | J67: L | K67: 0 - Active | L67: 46757 | M67: Degree | N67: Local Contract | O67: Kikuyu
A68: 63 | B68: 63 | C68: 20220598342 | D68: Mr. Nkarero, Antony Ntiita | E68: 31621426 | F68: M | G68: 30 | H68: Clerical Officer - EL - T03AG | I68: Finance & Accounting | J68: G | K68: 0 - Active | L68: 31/01/2028 | M68: O-Level | N68: Local Contract | O68: Maasai
E69: INFORMATION COMMUNICATION & TECHNOLOGY
A70: 64 | B70: 64 | C70: 20220597964 | D70: Mr. Sing'oei, Johnson Kiplangat | E70: 35685292 | F70: M | G70: 26 | H70: Information Communication Technology Officer [2] - EL - M11AL | I70: ICT | J70: L | K70: 0 - Active | L70: 31/01/2028 | M70: Degree | N70: Local Contract | O70: Kalenjin
A71: 65 | B71: 65 | C71: 20200484010 | D71: Mr. Kirima, Vincent Mwenda | E71: 30408351 | F71: M | G71: 32 | H71: Information Communication Technology Officer [2] - EL - M11AL | I71: ICT | J71: L | K71: 0 - Active | L71: 30/06/2026 | M71: Degree | N71: Local Contract | O71: Meru
A72: 66 | B72: 66 | C72: 20220597906 | D72: Mr. Chai, David Chivatsi | E72: 30050596 | F72: M | G72: 32 | H72: Information Communication Technology Assistant [2] - EL - M11BJ | I72: ICT | J72: J | K72: 0 - Active | L72: 31/01/2028 | M72: Diploma | N72: Local Contract | O72: Mijikenda
E73: KSRIC
A74: 67 | B74: 67 | C74: 20121210938 | D74: Dr. Oluoch, George Omondi | E74: 24416334 | F74: M | G74: 39 | H74: Senior Veterinary Officer - EL - H04AP | I74: KSRIC | J74: P | K74: 0 - Active | L74: 16/09/2045 | M74: Masters | N74: Permanent | O74: Luo
A75: 68 | B75: 68 | C75: 2013091337 | D75: Ms. Ngari, Cecilia Wairimu | E75: 27494151 | F75: F | G75: 35 | H75: Assistant Research Scientist - EL - R01BL | I75: KSRIC | J75: L | K75: 0 - Active | L75: 31/12/2027 | M75: Degree | N75: Local Contract | O75: Kikuyu
A76: 69 | B76: 69 | C76: 20220598960 | D76: Ms. Asila, Loreta Anyanje | E76: 27895831 | F76: F | G76: 35 | H76: Assistant Research Scientist - EL - R01BL | I76: KSRIC | J76: L | K76: 0 - Active | L76: 30/11/2027 | M76: Degree | N76: Local Contract | O76: Luhya
A77: 70 | B77: 70 | C77: 2012024370 | D77: Ms. Antar, Munira Said A | E77: 23875841 | F77: F | G77: 40 | H77: Fellowship - EL - M16XG | I77: KSRIC | J77: G | K77: 0 - Active | L77: 02/01/2026 | M77: Masters | N77: Part Time Contract | O77: Kenyan Arab
A78: 71 | B78: 71 | C78: 20181472223 | D78: Mr. Abisai, Fredrick Angote | E78: 33852077 | F78: M | G78: 27 | H78: Fellowship - EL - M16XG | I78: KSRIC | J78: G | K78: 0 - Active | L78: 14/07/2025 | M78: 9 | N78: Part Time Contract | O78: Luhya
A79: 72 | B79: 72 | C79: 20190119343 | D79: Mr. Musau, Brian Mukeli | E79: 32487813 | F79: M | G79: 30 | H79: Fellowship - EL - M16XG | I79: KSRIC | J79: G | K79: 0 - Active | L79: 31/07/2025 | M79: Degree | N79: Part Time Contract | O79: Kamba
A80: 73 | B80: 73 | C80: 20190641465 | D80: Mr. Musalia, Miheso Hannington | E80: 22231664 | F80: M | G80: 44 | H80: Fellowship - EL - M16XG | I80: KSRIC | J80: G | K80: 0 - Active | L80: 14/07/2025 | M80: O-Level | N80: Part Time Contract | O80: Luhya
A81: 74 | B81: 74 | C81: 20210645977 | D81: Miss. Musabyimana, Valentine | E81: 782066 | F81: F | G81: 28 | H81: Fellowship - EL - M16XG | I81: KSRIC | J81: G | K81: 0 - Active | L81: 14/07/2025 | M81: Degree | N81: Part Time Contract | O81: other Kenyan
A82: 75 | B82: 75 | C82: 20210646046 | D82: Mr. Maalim, Hussein Abass | E82: 35337775 | F82: M | G82: 28 | H82: Fellowship - EL - M16XG | I82: KSRIC | J82: G | K82: 0 - Active | L82: 27/02/2026 | M82: O-Level | N82: Part Time Contract | O82: Somali-So-State
A83: 76 | B83: 76 | C83: 20210646062 | D83: Mr. Tiyo, Lawi Totana | E83: 11710039 | F83: M | G83: 51 | H83: Fellowship - EL - M16XG | I83: KSRIC | J83: G | K83: 0 - Active | L83: 27/02/2026 | M83: O-Level | N83: Part Time Contract | O83: Maasai
A84: 77 | B84: 77 | C84: 20220598512 | D84: Miss. Saitoti, Anne Sein | E84: 29443115 | F84: F | G84: 32 | H84: Fellowship - EL - M16XG | I84: KSRIC | J84: G | K84: 0 - Active | L84: 02/01/2026 | M84: Degree | N84: Part Time Contract | O84: Maasai
A85: 78 | B85: 78 | C85: 20220598546 | D85: Mr. Parkurito, Stanley Leteipan | E85: 28484103 | F85: M | G85: 33 | H85: Fellowship - EL - M16XG | I85: KSRIC | J85: G | K85: 0 - Active | L85: 30/09/2025 | M85: O-Level | N85: Part Time Contract | O85: Maasai
A86: 79 | B86: 79 | C86: 20220598740 | D86: Mr. Oluoch, Ezekiel Adino | E86: 30866902 | F86: M | G86: 32 | H86: Fellowship - EL - M16XG | I86: KSRIC | J86: G | K86: 0 - Active | L86: 02/01/2026 | M86: Degree | N86: Part Time Contract | O86: Luo
A87: 80 | B87: 80 | C87: 20220598839 | D87: Mr. Kephah, Geofrey Maranga | E87: 23065759 | F87: M | G87: 42 | H87: Curatorial Assistant [3] - EL - M16BG | I87: KSRIC | J87: G | K87: 0 - Active | L87: 31/12/2027 | M87: O-Level | N87: Local Contract | O87: Kisii
A88: 81 | B88: 81 | C88: 20220598889 | D88: Ms. Mukweyi, Pamela Khasandi | E88: 25037835 | F88: F | G88: 37 | H88: Fellowship - EL - M16XG | I88: KSRIC | J88: G | K88: 0 - Active | L88: 02/01/2026 | M88: Degree | N88: Part Time Contract | O88: Luhya
A89: 82 | B89: 82 | C89: 20240090217 | D89: Mr.. Makuani, Dennis Kotti | E89: 33133984 | F89: M | G89: 30 | H89: Fellowship - EL - M16XG | I89: KSRIC | J89: G | K89: 0 - Active | L89: 31/05/2026 | M89: Degree | N89: Part Time Contract | O89: Kamba
A90: 83 | B90: 83 | C90: 20240300939 | D90: Mr. Ngage, Tonny Onyango Ouma | E90: 32424642 | F90: M | G90: 30 | H90: Fellowship - EL - M16XG | I90: KSRIC | J90: G | K90: 0 - Active | L90: 31/07/2025 | M90: Degree | N90: Part Time Contract | O90: Luo
... A95: 88 | B95: 88 | C95: 20250067339 | D95: Miss. Fiona Kanana Kimathi | E95: 40031044 | F95: F | G95: 24 | H95: Fellowship - EL - M16XG | I95: KSRIC | J95: G | K95: 0 - Active | L95: 30/04/2026 | M95: Degree | N95: Part Time Contract | O95: Meru
E96: LIBRARY
A97: 89 | B97: 89 | C97: 20152655585 | D97: Mrs. Wafula, Dinah Nanjala | E97: 26673037 | F97: F | G97: 36 | H97: Librarian [2] - EL - M05AK | I97: Library | J97: K | K97: 0 - Active | L97: 05/08/2048 | M97: Degree | N97: Permanent | O97: Luhya
A98: 90 | B98: 90 | C98: 20160708685 | D98: Mr. Ongata, Evans NickOwuor | E98: 27758071 | F98: M | G98: 34 | H98: Clerical Officer - EL - T03AG | I98: Library | J98: G | K98: 0 - Active | L98: 30/09/2025 | M98: O-Level | N98: Local Contract | O98: Luo
A99: 91 | B99: 91 | C99: 20220598253 | D99: Mr. Ahomo, Geoff Henderson | E99: 32316111 | F99: M | G99: 30 | H99: Clerical Officer - EL - T03AG | I99: Library | J99: G | K99: 0 - Active | L99: 31/01/2028 | M99: O-Level | N99: Local Contract | O99: Luo
A100: 71 | B100: 71 | C100: 20181472223 | D100: Mr. Abisai, Fredrick Angote | E100: 33852077 | F100: M | G100: 27 | H100: Fellowship - EL - M16XG | I100: KSRIC | J100: G | K100: 0 - Active | L100: 14/07/2025 | M100: 9 | N100: Part Time Contract | O100: Luhya
A101: 92 | B101: 92 | C101: 19930980996 | D101: Mr. Kivite, Joachim Maundu | E101: 8966122 | F101: M | G101: 57 | H101: Human Resource Assistant [2] - EL - C04BJ | I101: Public Relations & Marketing | J101: J | K101: 0 - Active | L101: 29/12/2027 | M101: A-Level | N101: Permanent | O101: Kamba
E102: NON COMMUNICABLE DISEASES
A103: 93 | B103: 93 | C103: 19950950775 | D103: Mr. Jillani, Edward Ngalla | E103: 8456642 | F103: M | G103: 58 | H103: Senior Research Scientist [1] - ET - R01AQ | I103: Non-Communicable Diseases | J103: Q | K103: 0 - Active | L103: 13/06/2036 | M103: PhD | N103: Permanent | O103: Mijikenda
A104: 94 | B104: 94 | C104: 20089223944 | D104: Ms. Kimani, Clare Njoki | E104: 23837529 | F104: F | G104: 43 | H104: Senior Research Scientist [2] - ET - R01AP | I104: Non-Communicable Diseases | J104: P | K104: 0 - Active | L104: 22/09/2051 | M104: PhD | N104: Permanent | O104: Kikuyu
A105: 95 | B105: 95 | C105: 19961316667 | D105: Dr. Ndung'u, Michael Njenga | E105: 7466013 | F105: M | G105: 59 | H105: Research Scientist [1] - ET - R01AN | I105: Non-Communicable Diseases | J105: N | K105: 0 - Active | L105: 02/11/2035 | M105: PhD | N105: Permanent | O105: kikuyu
A106: 96 | B106: 96 | C106: 20077017719 | D106: Mr. Katana, Gift Thoya | E106: 26202665 | F106: M | G106: 36 | H106: Laboratory Assistant [1] - EL - L07BJ | I106: Non-Communicable Diseases | J106: J | K106: 0 - Active | L106: 29/05/2048 | M106: Diploma | N106: Permanent | O106: Mijikenda
E107: ONE HEALTH
A108: 97 | B108: 97 | C108: 20089223839 | D108: Dr. Kamau, Joseph Muiruri | E108: 13646799 | F108: M | G108: 50 | H108: Senior Research Scientist [2] - ET - R01AP | I108: Reproductive Health & Biology | J108: P | K108: 0 - Active | L108: 28/10/2044 | M108: PhD | N108: Permanent | O108: Kikuyu
A109: 98 | B109: 98 | C109: 20106534472 | D109: Mr. Mwandime, Victor Mwaliko | E109: 23523136 | F109: M | G109: 41 | H109: Assistant Research Scientist - EL - R01BL | I109: One Health | J109: L | K109: 0 - Active | L109: 01/04/2044 | M109: Degree | N109: Permanent | O109: Taita
A110: 99 | B110: 99 | C110: 20114215731 | D110: Mr. Mutura, Samson Kamawe | E110: 12710851 | F110: M | G110: 51 | H110: Assistant Research Scientist - EL - R01BL | I110: One Health | J110: L | K110: 0 - Active | L110: 26/04/2034 | M110: Degree | N110: Permanent | O110: Kamba
A111: 100 | B111: 100 | C111: 20190118042 | D111: Mr. Mwaura, Patrick Waweru | E111: 28561000 | F111: M | G111: 35 | H111: Assistant Research Scientist - EL - R01BL | I111: One Health | J111: L | K111: 0 - Active | L111: 01/04/2027 | M111: Degree | N111: Local Contract | O111: Kikuyu
A112: 101 | B112: 101 | C112: 20181472320 | D112: Ms. Akunda, Irene Karegi | E112: 29577586 | F112: F | G112: 32 | H112: Fellowship - EL - M16XG | I112: One Health | J112: G | K112: 0 - Active | L112: 29/02/2028 | M112: Degree | N112: Local Contract | O112: Kisii
A113: 102 | B113: 102 | C113: 20210645935 | D113: Ms. Chege, Mary Njeri | E113: 27819882 | F113: F | G113: 34 | H113: Fellowship - EL - M16XG | I113: One Health | J113: G | K113: 0 - Active | L113: 30/09/2027 | M113: Degree | N113: Local Contract | O113: Kikuyu
A114: 103 | B114: 103 | C114: 20250089161 | D114: Ms. Daisy Karwitha | E114: 35664999 | F114: F | G114: 26 | H114: Assistant Research Scientist - EL - R01BL | I114: One Health | J114: L | K114: 0 - Active | L114: 28/02/2028 | M114: Degree | N114: Local Contract | O114: Kikuyu
...
